Workbook

Sheet Base de sorteio
A1: Base de sorteio do Bloco A: uma linha por estabelecimento candidato
A2: Número aleatório | B2: place_id | C2: Nome | D2: Município | E2: UF | F2: Nível REGIC 2018 | G2: Estrato | H2: Ordem no estrato | I2: Chave de sorteio | J2: Link do Google Maps | K2: Endereço | L2: Capitais da busca | M2: Nº de termos que acharam
A3: =RAND() | B3: ChIJ0caB7AeNf5ERLJd-Yw-Nbrw | C3: 1000 Presentes Vip | D3: Rio Branco | E3: AC | F3: Capitais Regionais C | G3: Capital regional | H3: =IF(G3="fora do recorte","",SUMPRODUCT(($G$3:$G$1723=G3)*($A$3:$A$1723<=A3))) | I3: =IF(H3="","",G3&"|"&H3) | J3: https://www.google.com/maps/search/?api=1&query=1000%20Presentes%20Vip&query_place_id=ChIJ0caB7AeNf5ERLJd-Yw-Nbrw | K3: Av. Ceará, 877 - Base, Rio Branco - AC, 69905-066, Brasil | L3: Rio Branco | M3: 1
A4: =RAND() | B4: ChIJO4YACEqNf5ERKIsRlaX-8-M | C4: Acre Importações | D4: Rio Branco | E4: AC | F4: Capitais Regionais C | G4: Capital regional | H4: =IF(G4="fora do recorte","",SUMPRODUCT(($G$3:$G$1723=G4)*($A$3:$A$1723<=A4))) | I4: =IF(H4="","",G4&"|"&H4) | J4: https://www.google.com/maps/search/?api=1&query=Acre%20Importa%C3%A7%C3%B5es&query_place_id=ChIJO4YACEqNf5ERKIsRlaX-8-M | K4: R. Quintino Bocaiuva, 1621 - Bosque, Rio Branco - AC, 69900-070 - Bosque, Rio Branco - AC, 69900-526, Brasil | L4: Rio Branco | M4: 1
A5: =RAND() | B5: ChIJT1ogVfKNf5ERX_7DdpLnx8o | C5: Actions Geek | D5: Rio Branco | E5: AC | F5: Capitais Regionais C | G5: Capital regional | H5: =IF(G5="fora do recorte","",SUMPRODUCT(($G$3:$G$1723=G5)*($A$3:$A$1723<=A5))) | I5: =IF(H5="","",G5&"|"&H5) | J5: https://www.google.com/maps/search/?api=1&query=Actions%20Geek&query_place_id=ChIJT1ogVfKNf5ERX_7DdpLnx8o | K5: R. Cedro, 117 - Novo Horizonte, Rio Branco - AC, 69921-120, Brasil | L5: Rio Branco | M5: 3
A6: =RAND() | B6: ChIJeSqczFWMf5ER4mlOg6vDcT0 | C6: Americanas | D6: Rio Branco | E6: AC | F6: Capitais Regionais C | G6: Capital regional | H6: =IF(G6="fora do recorte","",SUMPRODUCT(($G$3:$G$1723=G6)*($A$3:$A$1723<=A6))) | I6: =IF(H6="","",G6&"|"&H6) | J6: https://www.google.com/maps/search/?api=1&query=Americanas&query_place_id=ChIJeSqczFWMf5ER4mlOg6vDcT0 | K6: Via Verde Shopping - Estr. da Floresta, 2320 - Floresta Sul, Rio Branco - AC, 69914-220, Brasil | L6: Rio Branco | M6: 1
A7: =RAND() | B7: ChIJm0XoJSyNf5ERmuz9HqoT63A | C7: Americanas | D7: Rio Branco | E7: AC | F7: Capitais Regionais C | G7: Capital regional | H7: =IF(G7="fora do recorte","",SUMPRODUCT(($G$3:$G$1723=G7)*($A$3:$A$1723<=A7))) | I7: =IF(H7="","",G7&"|"&H7) | J7: https://www.google.com/maps/search/?api=1&query=Americanas&query_place_id=ChIJm0XoJSyNf5ERmuz9HqoT63A | K7: Av. Getúlio Vargas, 1348 - Bosque, Rio Branco - AC, 69940-046, Brasil | L7: Rio Branco | M7: 1
A8: =RAND() | B8: ChIJdc9EPmmNf5ERNz1jV9lDnJw | C8: Brincando com Nelinha | D8: Rio Branco | E8: AC | F8: Capitais Regionais C | G8: Capital regional | H8: =IF(G8="fora do recorte","",SUMPRODUCT(($G$3:$G$1723=G8)*($A$3:$A$1723<=A8))) | I8: =IF(H8="","",G8&"|"&H8) | J8: https://www.google.com/maps/search/?api=1&query=Brincando%20com%20Nelinha&query_place_id=ChIJdc9EPmmNf5ERNz1jV9lDnJw | K8: R. São Pedro, 113 - Sobral, Rio Branco - AC, 69911-180, Brasil | L8: Rio Branco | M8: 2
A9: =RAND() | B9: ChIJE9IvPYqNf5ERNjv4F--VtDw | C9: Cantinho Eletrônico, papelaria, artigo de presente e Lan house | D9: Rio Branco | E9: AC | F9: Capitais Regionais C | G9: Capital regional | H9: =IF(G9="fora do recorte","",SUMPRODUCT(($G$3:$G$1723=G9)*($A$3:$A$1723<=A9))) | I9: =IF(H9="","",G9&"|"&H9) | J9: https://www.google.com/maps/search/?api=1&query=Cantinho%20Eletr%C3%B4nico%2C%20papelaria%2C%20artigo%20de%20presente%20e%20Lan%20house&query_place_id=ChIJE9IvPYqNf5ERNjv4F--VtDw | K9: Tv. Judia, 944 - Santa Inês, Rio Branco - AC, 69907-758, Brasil | L9: Rio Branco | M9: 1
A10: =RAND() | B10: ChIJlx060F6Mf5ERsHd3kI2Kz50 | C10: Casa de Brinquedo | D10: Rio Branco | E10: AC | F10: Capitais Regionais C | G10: Capital regional | H10: =IF(G10="fora do recorte","",SUMPRODUCT(($G$3:$G$1723=G10)*($A$3:$A$1723<=A10))) | I10: =IF(H10="","",G10&"|"&H10) | J10: https://www.google.com/maps/search/?api=1&query=Casa%20de%20Brinquedo&query_place_id=ChIJlx060F6Mf5ERsHd3kI2Kz50 | K10: Av. Nações Unidas, 357 - José Augusto, Rio Branco - AC, 69900-721, Brasil | L10: Rio Branco | M10: 2
A11: =RAND() | B11: ChIJORUoEuqNf5ERmSLGJ7D3BUI | C11: Decks & Dungeons | D11: Rio Branco | E11: AC | F11: Capitais Regionais C | G11: Capital regional | H11: =IF(G11="fora do recorte","",SUMPRODUCT(($G$3:$G$1723=G11)*($A$3:$A$1723<=A11))) | I11: =IF(H11="","",G11&"|"&H11) | J11: https://www.google.com/maps/search/?api=1&query=Decks%20%26%20Dungeons&query_place_id=ChIJORUoEuqNf5ERmSLGJ7D3BUI | K11: R. das Rosas, 229 - Jardim Primavera, Rio Branco - AC, 69919-602, Brasil | L11: Rio Branco | M11: 2
A12: =RAND() | B12: ChIJz2CeJ3SMf5ER2iBb01SF_as | C12: Duda Presentes | D12: Rio Branco | E12: AC | F12: Capitais Regionais C | G12: Capital regional | H12: =IF(G12="fora do recorte","",SUMPRODUCT(($G$3:$G$1723=G12)*($A$3:$A$1723<=A12))) | I12: =IF(H12="","",G12&"|"&H12) | J12: https://www.google.com/maps/search/?api=1&query=Duda%20Presentes&query_place_id=ChIJz2CeJ3SMf5ER2iBb01SF_as | K12: Av. Antônio da Rocha Viana, 4275 - Vila Nova, Rio Branco - AC, 69921-084, Brasil | L12: Rio Branco | M12: 1
A13: =RAND() | B13: ChIJ_fuVrJCNf5ER5VwqwmDWOQ0 | C13: Emporium Nerd | D13: Rio Branco | E13: AC | F13: Capitais Regionais C | G13: Capital regional | H13: =IF(G13="fora do recorte","",SUMPRODUCT(($G$3:$G$1723=G13)*($A$3:$A$1723<=A13))) | I13: =IF(H13="","",G13&"|"&H13) | J13: https://www.google.com/maps/search/?api=1&query=Emporium%20Nerd&query_place_id=ChIJ_fuVrJCNf5ER5VwqwmDWOQ0 | K13: R. Seis de Agosto, 931 - 6 de Agosto, Rio Branco - AC, 69905-684, Brasil | L13: Rio Branco | M13: 2
A14: =RAND() | B14: ChIJr7mTWeSNf5ER7u2wlBtUMq8 | C14: Fox Games - Via Verde Shopping - Floresta Sul | D14: Rio Branco | E14: AC | F14: Capitais Regionais C | G14: Capital regional | H14: =IF(G14="fora do recorte","",SUMPRODUCT(($G$3:$G$1723=G14)*($A$3:$A$1723<=A14))) | I14: =IF(H14="","",G14&"|"&H14) | J14: https://www.google.com/maps/search/?api=1&query=Fox%20Games%20-%20Via%20Verde%20Shopping%20-%20Floresta%20Sul&query_place_id=ChIJr7mTWeSNf5ER7u2wlBtUMq8 | K14: Estr. da Floresta, 2320 - Pi 1 - Floresta Sul, Rio Branco - AC, 69912-443, Brasil | L14: Rio Branco | M14: 1
... A1703: =RAND() | B1703: ChIJKXD-OZlZzpQRfcjYR9ZCqak | C1703: sheep toys | D1703: São Paulo | E1703: SP | F1703: Grande Metrópole Nacional | G1703: Metrópole | H1703: =IF(G1703="fora do recorte","",SUMPRODUCT(($G$3:$G$1723=G1703)*($A$3:$A$1723<=A1703))) | I1703: =IF(H1703="","",G1703&"|"&H1703) | J1703: https://www.google.com/maps/search/?api=1&query=sheep%20toys&query_place_id=ChIJKXD-OZlZzpQRfcjYR9ZCqak | K1703: Av. Sen. Queirós, 305 - 8 andar sala 1 - Centro Histórico de São Paulo, São Paulo - SP, 01017-040, Brasil | L1703: São Paulo | M1703: 1
A1704: =RAND() | B1704: ChIJpZbpu_zVBQcRuPFD4K5R8Co | C1704: Taverna: Game & Café | D1704: Arapiraca | E1704: AL | G1704: fora do recorte | H1704: =IF(G1704="fora do recorte","",SUMPRODUCT(($G$3:$G$1723=G1704)*($A$3:$A$1723<=A1704))) | I1704: =IF(H1704="","",G1704&"|"&H1704) | J1704: https://www.google.com/maps/search/?api=1&query=Taverna%3A%20Game%20%26%20Caf%C3%A9&query_place_id=ChIJpZbpu_zVBQcRuPFD4K5R8Co | K1704: R. Srg. Benevides Montes, 214 - Primavera, Arapiraca - AL, 57300-230, Brasil | L1704: Maceió | M1704: 3
A1705: =RAND() | B1705: ChIJOxz30nqrOQcRX7Hke7sTIqQ | C1705: Brinquedoteca Sonho de Criança | D1705: Itabuna | E1705: BA | G1705: fora do recorte | H1705: =IF(G1705="fora do recorte","",SUMPRODUCT(($G$3:$G$1723=G1705)*($A$3:$A$1723<=A1705))) | I1705: =IF(H1705="","",G1705&"|"&H1705) | J1705: https://www.google.com/maps/search/?api=1&query=Brinquedoteca%20Sonho%20de%20Crian%C3%A7a&query_place_id=ChIJOxz30nqrOQcRX7Hke7sTIqQ | K1705: R. Pernambuco, 314 - Jardim Vitoria, Itabuna - BA, 45605-510, Brasil | L1705: Vitória | M1705: 1
A1706: =RAND() | B1706: ChIJV3s2yaE7RgcRE85rRfLI7Zg | C1706: BatePapo | D1706: Vitória da Conquista | E1706: BA | G1706: fora do recorte | H1706: =IF(G1706="fora do recorte","",SUMPRODUCT(($G$3:$G$1723=G1706)*($A$3:$A$1723<=A1706))) | I1706: =IF(H1706="","",G1706&"|"&H1706) | J1706: https://www.google.com/maps/search/?api=1&query=BatePapo&query_place_id=ChIJV3s2yaE7RgcRE85rRfLI7Zg | K1706: Av. Alziro Prates, 71 - Candeias, Vitória da Conquista - BA, 45028-075, Brasil | L1706: Vitória | M1706: 1
A1707: =RAND() | B1707: ChIJKUt41jAltgARthoxe_e-_pY | C1707: Toca do Lobo - Locadora de Jogos Lúdicos | D1707: Linhares | E1707: ES | G1707: fora do recorte | H1707: =IF(G1707="fora do recorte","",SUMPRODUCT(($G$3:$G$1723=G1707)*($A$3:$A$1723<=A1707))) | I1707: =IF(H1707="","",G1707&"|"&H1707) | J1707: https://www.google.com/maps/search/?api=1&query=Toca%20do%20Lobo%20-%20Locadora%20de%20Jogos%20L%C3%BAdicos&query_place_id=ChIJKUt41jAltgARthoxe_e-_pY | K1707: R. Carlos Almeida Neto, nº 14 - quadra 15 - Juparanã, Linhares - ES, 29900-600, Brasil | L1707: Vitória | M1707: 1
A1708: =RAND() | B1708: ChIJlR3mn93bYZMRP6xg5L4vg_M | C1708: Loja Fantasma Card Game Center | D1708: Rio Verde | E1708: GO | G1708: fora do recorte | H1708: =IF(G1708="fora do recorte","",SUMPRODUCT(($G$3:$G$1723=G1708)*($A$3:$A$1723<=A1708))) | I1708: =IF(H1708="","",G1708&"|"&H1708) | J1708: https://www.google.com/maps/search/?api=1&query=Loja%20Fantasma%20Card%20Game%20Center&query_place_id=ChIJlR3mn93bYZMRP6xg5L4vg_M | K1708: Av. Jk, 140 - Q.02 L.35 SALA 2 - Res. Tocantins, Rio Verde - GO, 75909-456, Brasil | L1708: Rio Branco | M1708: 1
A1709: =RAND() | B1709: ChIJq92vt8sxpJQR-lNNTdp0RLQ | C1709: TABLE GAMES (Burgers) | D1709: Araguari | E1709: MG | G1709: fora do recorte | H1709: =IF(G1709="fora do recorte","",SUMPRODUCT(($G$3:$G$1723=G1709)*($A$3:$A$1723<=A1709))) | I1709: =IF(H1709="","",G1709&"|"&H1709) | J1709: https://www.google.com/maps/search/?api=1&query=TABLE%20GAMES%20%28Burgers%29&query_place_id=ChIJq92vt8sxpJQR-lNNTdp0RLQ | K1709: Av. Cel. Belchior de Godói, 1330 - Santa Terezinha, Araguari - MG, 38447-218, Brasil | L1709: Boa Vista; Teresina | M1709: 2
A1710: =RAND() | B1710: ChIJCdEZv21PpJQRg6vLc_9tIcc | C1710: Mestre dos Jogos LudoBar | D1710: Uberlândia | E1710: MG | G1710: fora do recorte | H1710: =IF(G1710="fora do recorte","",SUMPRODUCT(($G$3:$G$1723=G1710)*($A$3:$A$1723<=A1710))) | I1710: =IF(H1710="","",G1710&"|"&H1710) | J1710: https://www.google.com/maps/search/?api=1&query=Mestre%20dos%20Jogos%20LudoBar&query_place_id=ChIJCdEZv21PpJQRg6vLc_9tIcc | K1710: R. João Balbino, 537 - Santa Mônica, Uberlândia - MG, 38408-265, Brasil | L1710: Palmas | M1710: 1
A1711: =RAND() | B1711: ChIJzcQ9t_ND65QRqkeUm-aANaE | C1711: BoardGame in Box | D1711: Londrina | E1711: PR | G1711: fora do recorte | H1711: =IF(G1711="fora do recorte","",SUMPRODUCT(($G$3:$G$1723=G1711)*($A$3:$A$1723<=A1711))) | I1711: =IF(H1711="","",G1711&"|"&H1711) | J1711: https://www.google.com/maps/search/?api=1&query=BoardGame%20in%20Box&query_place_id=ChIJzcQ9t_ND65QRqkeUm-aANaE | K1711: R. Raja Gabaglia, 326 - Quebec, Londrina - PR, 86060-190, Brasil | L1711: Natal | M1711: 1
A1712: =RAND() | B1712: ChIJaWBHOg21lwARHT8gg8Y7xEg | C1712: Armazém dos Jogos | D1712: Rio das Ostras | E1712: RJ | G1712: fora do recorte | H1712: =IF(G1712="fora do recorte","",SUMPRODUCT(($G$3:$G$1723=G1712)*($A$3:$A$1723<=A1712))) | I1712: =IF(H1712="","",G1712&"|"&H1712) | J1712: https://www.google.com/maps/search/?api=1&query=Armaz%C3%A9m%20dos%20Jogos&query_place_id=ChIJaWBHOg21lwARHT8gg8Y7xEg | K1712: R. Niterói, 580 - Jardim Mariléa, Rio das Ostras - RJ, 28895-547, Brasil | L1712: Rio Branco | M1712: 2
A1713: =RAND() | B1713: ChIJO9bPE0GdEZURRD6c41YpCRI | C1713: Beer & Boards | D1713: Rio Grande | E1713: RS | G1713: fora do recorte | H1713: =IF(G1713="fora do recorte","",SUMPRODUCT(($G$3:$G$1723=G1713)*($A$3:$A$1723<=A1713))) | I1713: =IF(H1713="","",G1713&"|"&H1713) | J1713: https://www.google.com/maps/search/?api=1&query=Beer%20%26%20Boards&query_place_id=ChIJO9bPE0GdEZURRD6c41YpCRI | K1713: R. Gen. Abreu, 342 - Cidade Nova, Rio Grande - RS, 96202-570, Brasil | L1713: Aracaju; Belém; Boa Vista; Campo Grande; Natal; Porto Velho; Rio de Janeiro | M1713: 3
A1714: =RAND() | B1714: ChIJqUbogQucEZURHO-GUHAfDs4 | C1714: Stop Games | D1714: Rio Grande | E1714: RS | G1714: fora do recorte | H1714: =IF(G1714="fora do recorte","",SUMPRODUCT(($G$3:$G$1723=G1714)*($A$3:$A$1723<=A1714))) | I1714: =IF(H1714="","",G1714&"|"&H1714) | J1714: https://www.google.com/maps/search/?api=1&query=Stop%20Games&query_place_id=ChIJqUbogQucEZURHO-GUHAfDs4 | K1714: R. Dom Bosco, 484 - Cidade Nova, Rio Grande - RS, 96211-090, Brasil | L1714: Campo Grande; Rio Branco | M1714: 1
A1715: =RAND() | B1715: ChIJN40KG6z645QR2XQSR2syQMY | C1715: Loja Happy Nerd | D1715: Joaçaba | E1715: SC | G1715: fora do recorte | H1715: =IF(G1715="fora do recorte","",SUMPRODUCT(($G$3:$G$1723=G1715)*($A$3:$A$1723<=A1715))) | I1715: =IF(H1715="","",G1715&"|"&H1715) | J1715: https://www.google.com/maps/search/?api=1&query=Loja%20Happy%20Nerd&query_place_id=ChIJN40KG6z645QR2XQSR2syQMY | K1715: R. Frei Edgar, 89 - Sl 05 - Centro, Joaçaba - SC, 89600-000, Brasil | L1715: Campo Grande; Cuiabá | M1715: 2
... A1723: =RAND() | B1723: ChIJfbpAYqzLyZQRNv5blbdB9Kk | C1723: Bardos Game Store | D1723: São João da Boa Vista | E1723: SP | G1723: fora do recorte | H1723: =IF(G1723="fora do recorte","",SUMPRODUCT(($G$3:$G$1723=G1723)*($A$3:$A$1723<=A1723))) | I1723: =IF(H1723="","",G1723&"|"&H1723) | J1723: https://www.google.com/maps/search/?api=1&query=Bardos%20Game%20Store&query_place_id=ChIJfbpAYqzLyZQRNv5blbdB9Kk | K1723: R. Cel. Ernesto de Oliveira, 440 - Centro, São João da Boa Vista - SP, 13870-249, Brasil | L1723: Boa Vista; João Pessoa | M1723: 8

Sheet Amostragem
A1: Amostragem do Bloco A: registro das casas sorteadas por estrato
A2: Nº do item | B2: Estrato | C2: Ordem no estrato | D2: Número aleatório sorteado | E2: place_id | F2: Nome do estabelecimento | G2: Município | H2: UF | I2: Link do Google Maps | J2: Tem fotos no Maps? | K2: Fotos comprovam espaço de jogo? | L2: Tem Instagram? | M2: Instagram comprova espaço de jogo? | N2: É do tipo? | O2: Casas do tipo acumuladas no estrato | P2: Nº de avaliações no Maps | Q2: Usuário do Instagram | R2: Nº de publicações no Instagram | S2: Data da última publicação | T2: Observação
A3: =ROW()-2 | B3: Metrópole | C3: 1 | D3: =IFERROR(INDEX('Base de sorteio'!$A$3:$A$1723,MATCH($B3&"|"&$C3,'Base de sorteio'!$I$3:$I$1723,0)),"") | E3: =IFERROR(INDEX('Base de sorteio'!$B$3:$B$1723,MATCH($B3&"|"&$C3,'Base de sorteio'!$I$3:$I$1723,0)),"") | F3: =IFERROR(INDEX('Base de sorteio'!$C$3:$C$1723,MATCH($B3&"|"&$C3,'Base de sorteio'!$I$3:$I$1723,0)),"") | G3: =IFERROR(INDEX('Base de sorteio'!$D$3:$D$1723,MATCH($B3&"|"&$C3,'Base de sorteio'!$I$3:$I$1723,0)),"") | H3: =IFERROR(INDEX('Base de sorteio'!$E$3:$E$1723,MATCH($B3&"|"&$C3,'Base de sorteio'!$I$3:$I$1723,0)),"") | I3: =IF(E3="","",HYPERLINK(IFERROR(INDEX('Base de sorteio'!$J$3:$J$1723,MATCH($B3&"|"&$C3,'Base de sorteio'!$I$3:$I$1723,0)),""),"abrir")) | N3: =IF(AND(K3="",M3=""),"",IF(OR(K3="sim",M3="sim"),"sim",IF(OR(K3="inconclusivo",M3="inconclusivo"),"inconclusivo","não"))) | O3: =IF(N3="sim",COUNTIFS($B$3:$B3,$B3,$N$3:$N3,"sim"),"")
A4: =ROW()-2 | B4: Metrópole | C4: 2 | D4: =IFERROR(INDEX('Base de sorteio'!$A$3:$A$1723,MATCH($B4&"|"&$C4,'Base de sorteio'!$I$3:$I$1723,0)),"") | E4: =IFERROR(INDEX('Base de sorteio'!$B$3:$B$1723,MATCH($B4&"|"&$C4,'Base de sorteio'!$I$3:$I$1723,0)),"") | F4: =IFERROR(INDEX('Base de sorteio'!$C$3:$C$1723,MATCH($B4&"|"&$C4,'Base de sorteio'!$I$3:$I$1723,0)),"") | G4: =IFERROR(INDEX('Base de sorteio'!$D$3:$D$1723,MATCH($B4&"|"&$C4,'Base de sorteio'!$I$3:$I$1723,0)),"") | H4: =IFERROR(INDEX('Base de sorteio'!$E$3:$E$1723,MATCH($B4&"|"&$C4,'Base de sorteio'!$I$3:$I$1723,0)),"") | I4: =IF(E4="","",HYPERLINK(IFERROR(INDEX('Base de sorteio'!$J$3:$J$1723,MATCH($B4&"|"&$C4,'Base de sorteio'!$I$3:$I$1723,0)),""),"abrir")) | N4: =IF(AND(K4="",M4=""),"",IF(OR(K4="sim",M4="sim"),"sim",IF(OR(K4="inconclusivo",M4="inconclusivo"),"inconclusivo","não"))) | O4: =IF(N4="sim",COUNTIFS($B$3:$B4,$B4,$N$3:$N4,"sim"),"")
A5: =ROW()-2 | B5: Metrópole | C5: 3 | D5: =IFERROR(INDEX('Base de sorteio'!$A$3:$A$1723,MATCH($B5&"|"&$C5,'Base de sorteio'!$I$3:$I$1723,0)),"") | E5: =IFERROR(INDEX('Base de sorteio'!$B$3:$B$1723,MATCH($B5&"|"&$C5,'Base de sorteio'!$I$3:$I$1723,0)),"") | F5: =IFERROR(INDEX('Base de sorteio'!$C$3:$C$1723,MATCH($B5&"|"&$C5,'Base de sorteio'!$I$3:$I$1723,0)),"") | G5: =IFERROR(INDEX('Base de sorteio'!$D$3:$D$1723,MATCH($B5&"|"&$C5,'Base de sorteio'!$I$3:$I$1723,0)),"") | H5: =IFERROR(INDEX('Base de sorteio'!$E$3:$E$1723,MATCH($B5&"|"&$C5,'Base de sorteio'!$I$3:$I$1723,0)),"") | I5: =IF(E5="","",HYPERLINK(IFERROR(INDEX('Base de sorteio'!$J$3:$J$1723,MATCH($B5&"|"&$C5,'Base de sorteio'!$I$3:$I$1723,0)),""),"abrir")) | N5: =IF(AND(K5="",M5=""),"",IF(OR(K5="sim",M5="sim"),"sim",IF(OR(K5="inconclusivo",M5="inconclusivo"),"inconclusivo","não"))) | O5: =IF(N5="sim",COUNTIFS($B$3:$B5,$B5,$N$3:$N5,"sim"),"")
A6: =ROW()-2 | B6: Metrópole | C6: 4 | D6: =IFERROR(INDEX('Base de sorteio'!$A$3:$A$1723,MATCH($B6&"|"&$C6,'Base de sorteio'!$I$3:$I$1723,0)),"") | E6: =IFERROR(INDEX('Base de sorteio'!$B$3:$B$1723,MATCH($B6&"|"&$C6,'Base de sorteio'!$I$3:$I$1723,0)),"") | F6: =IFERROR(INDEX('Base de sorteio'!$C$3:$C$1723,MATCH($B6&"|"&$C6,'Base de sorteio'!$I$3:$I$1723,0)),"") | G6: =IFERROR(INDEX('Base de sorteio'!$D$3:$D$1723,MATCH($B6&"|"&$C6,'Base de sorteio'!$I$3:$I$1723,0)),"") | H6: =IFERROR(INDEX('Base de sorteio'!$E$3:$E$1723,MATCH($B6&"|"&$C6,'Base de sorteio'!$I$3:$I$1723,0)),"") | I6: =IF(E6="","",HYPERLINK(IFERROR(INDEX('Base de sorteio'!$J$3:$J$1723,MATCH($B6&"|"&$C6,'Base de sorteio'!$I$3:$I$1723,0)),""),"abrir")) | N6: =IF(AND(K6="",M6=""),"",IF(OR(K6="sim",M6="sim"),"sim",IF(OR(K6="inconclusivo",M6="inconclusivo"),"inconclusivo","não"))) | O6: =IF(N6="sim",COUNTIFS($B$3:$B6,$B6,$N$3:$N6,"sim"),"")
A7: =ROW()-2 | B7: Metrópole | C7: 5 | D7: =IFERROR(INDEX('Base de sorteio'!$A$3:$A$1723,MATCH($B7&"|"&$C7,'Base de sorteio'!$I$3:$I$1723,0)),"") | E7: =IFERROR(INDEX('Base de sorteio'!$B$3:$B$1723,MATCH($B7&"|"&$C7,'Base de sorteio'!$I$3:$I$1723,0)),"") | F7: =IFERROR(INDEX('Base de sorteio'!$C$3:$C$1723,MATCH($B7&"|"&$C7,'Base de sorteio'!$I$3:$I$1723,0)),"") | G7: =IFERROR(INDEX('Base de sorteio'!$D$3:$D$1723,MATCH($B7&"|"&$C7,'Base de sorteio'!$I$3:$I$1723,0)),"") | H7: =IFERROR(INDEX('Base de sorteio'!$E$3:$E$1723,MATCH($B7&"|"&$C7,'Base de sorteio'!$I$3:$I$1723,0)),"") | I7: =IF(E7="","",HYPERLINK(IFERROR(INDEX('Base de sorteio'!$J$3:$J$1723,MATCH($B7&"|"&$C7,'Base de sorteio'!$I$3:$I$1723,0)),""),"abrir")) | N7: =IF(AND(K7="",M7=""),"",IF(OR(K7="sim",M7="sim"),"sim",IF(OR(K7="inconclusivo",M7="inconclusivo"),"inconclusivo","não"))) | O7: =IF(N7="sim",COUNTIFS($B$3:$B7,$B7,$N$3:$N7,"sim"),"")
A8: =ROW()-2 | B8: Metrópole | C8: 6 | D8: =IFERROR(INDEX('Base de sorteio'!$A$3:$A$1723,MATCH($B8&"|"&$C8,'Base de sorteio'!$I$3:$I$1723,0)),"") | E8: =IFERROR(INDEX('Base de sorteio'!$B$3:$B$1723,MATCH($B8&"|"&$C8,'Base de sorteio'!$I$3:$I$1723,0)),"") | F8: =IFERROR(INDEX('Base de sorteio'!$C$3:$C$1723,MATCH($B8&"|"&$C8,'Base de sorteio'!$I$3:$I$1723,0)),"") | G8: =IFERROR(INDEX('Base de sorteio'!$D$3:$D$1723,MATCH($B8&"|"&$C8,'Base de sorteio'!$I$3:$I$1723,0)),"") | H8: =IFERROR(INDEX('Base de sorteio'!$E$3:$E$1723,MATCH($B8&"|"&$C8,'Base de sorteio'!$I$3:$I$1723,0)),"") | I8: =IF(E8="","",HYPERLINK(IFERROR(INDEX('Base de sorteio'!$J$3:$J$1723,MATCH($B8&"|"&$C8,'Base de sorteio'!$I$3:$I$1723,0)),""),"abrir")) | N8: =IF(AND(K8="",M8=""),"",IF(OR(K8="sim",M8="sim"),"sim",IF(OR(K8="inconclusivo",M8="inconclusivo"),"inconclusivo","não"))) | O8: =IF(N8="sim",COUNTIFS($B$3:$B8,$B8,$N$3:$N8,"sim"),"")
A9: =ROW()-2 | B9: Metrópole | C9: 7 | D9: =IFERROR(INDEX('Base de sorteio'!$A$3:$A$1723,MATCH($B9&"|"&$C9,'Base de sorteio'!$I$3:$I$1723,0)),"") | E9: =IFERROR(INDEX('Base de sorteio'!$B$3:$B$1723,MATCH($B9&"|"&$C9,'Base de sorteio'!$I$3:$I$1723,0)),"") | F9: =IFERROR(INDEX('Base de sorteio'!$C$3:$C$1723,MATCH($B9&"|"&$C9,'Base de sorteio'!$I$3:$I$1723,0)),"") | G9: =IFERROR(INDEX('Base de sorteio'!$D$3:$D$1723,MATCH($B9&"|"&$C9,'Base de sorteio'!$I$3:$I$1723,0)),"") | H9: =IFERROR(INDEX('Base de sorteio'!$E$3:$E$1723,MATCH($B9&"|"&$C9,'Base de sorteio'!$I$3:$I$1723,0)),"") | I9: =IF(E9="","",HYPERLINK(IFERROR(INDEX('Base de sorteio'!$J$3:$J$1723,MATCH($B9&"|"&$C9,'Base de sorteio'!$I$3:$I$1723,0)),""),"abrir")) | N9: =IF(AND(K9="",M9=""),"",IF(OR(K9="sim",M9="sim"),"sim",IF(OR(K9="inconclusivo",M9="inconclusivo"),"inconclusivo","não"))) | O9: =IF(N9="sim",COUNTIFS($B$3:$B9,$B9,$N$3:$N9,"sim"),"")
A10: =ROW()-2 | B10: Metrópole | C10: 8 | D10: =IFERROR(INDEX('Base de sorteio'!$A$3:$A$1723,MATCH($B10&"|"&$C10,'Base de sorteio'!$I$3:$I$1723,0)),"") | E10: =IFERROR(INDEX('Base de sorteio'!$B$3:$B$1723,MATCH($B10&"|"&$C10,'Base de sorteio'!$I$3:$I$1723,0)),"") | F10: =IFERROR(INDEX('Base de sorteio'!$C$3:$C$1723,MATCH($B10&"|"&$C10,'Base de sorteio'!$I$3:$I$1723,0)),"") | G10: =IFERROR(INDEX('Base de sorteio'!$D$3:$D$1723,MATCH($B10&"|"&$C10,'Base de sorteio'!$I$3:$I$1723,0)),"") | H10: =IFERROR(INDEX('Base de sorteio'!$E$3:$E$1723,MATCH($B10&"|"&$C10,'Base de sorteio'!$I$3:$I$1723,0)),"") | I10: =IF(E10="","",HYPERLINK(IFERROR(INDEX('Base de sorteio'!$J$3:$J$1723,MATCH($B10&"|"&$C10,'Base de sorteio'!$I$3:$I$1723,0)),""),"abrir")) | N10: =IF(AND(K10="",M10=""),"",IF(OR(K10="sim",M10="sim"),"sim",IF(OR(K10="inconclusivo",M10="inconclusivo"),"inconclusivo","não"))) | O10: =IF(N10="sim",COUNTIFS($B$3:$B10,$B10,$N$3:$N10,"sim"),"")
A11: =ROW()-2 | B11: Metrópole | C11: 9 | D11: =IFERROR(INDEX('Base de sorteio'!$A$3:$A$1723,MATCH($B11&"|"&$C11,'Base de sorteio'!$I$3:$I$1723,0)),"") | E11: =IFERROR(INDEX('Base de sorteio'!$B$3:$B$1723,MATCH($B11&"|"&$C11,'Base de sorteio'!$I$3:$I$1723,0)),"") | F11: =IFERROR(INDEX('Base de sorteio'!$C$3:$C$1723,MATCH($B11&"|"&$C11,'Base de sorteio'!$I$3:$I$1723,0)),"") | G11: =IFERROR(INDEX('Base de sorteio'!$D$3:$D$1723,MATCH($B11&"|"&$C11,'Base de sorteio'!$I$3:$I$1723,0)),"") | H11: =IFERROR(INDEX('Base de sorteio'!$E$3:$E$1723,MATCH($B11&"|"&$C11,'Base de sorteio'!$I$3:$I$1723,0)),"") | I11: =IF(E11="","",HYPERLINK(IFERROR(INDEX('Base de sorteio'!$J$3:$J$1723,MATCH($B11&"|"&$C11,'Base de sorteio'!$I$3:$I$1723,0)),""),"abrir")) | N11: =IF(AND(K11="",M11=""),"",IF(OR(K11="sim",M11="sim"),"sim",IF(OR(K11="inconclusivo",M11="inconclusivo"),"inconclusivo","não"))) | O11: =IF(N11="sim",COUNTIFS($B$3:$B11,$B11,$N$3:$N11,"sim"),"")
A12: =ROW()-2 | B12: Metrópole | C12: 10 | D12: =IFERROR(INDEX('Base de sorteio'!$A$3:$A$1723,MATCH($B12&"|"&$C12,'Base de sorteio'!$I$3:$I$1723,0)),"") | E12: =IFERROR(INDEX('Base de sorteio'!$B$3:$B$1723,MATCH($B12&"|"&$C12,'Base de sorteio'!$I$3:$I$1723,0)),"") | F12: =IFERROR(INDEX('Base de sorteio'!$C$3:$C$1723,MATCH($B12&"|"&$C12,'Base de sorteio'!$I$3:$I$1723,0)),"") | G12: =IFERROR(INDEX('Base de sorteio'!$D$3:$D$1723,MATCH($B12&"|"&$C12,'Base de sorteio'!$I$3:$I$1723,0)),"") | H12: =IFERROR(INDEX('Base de sorteio'!$E$3:$E$1723,MATCH($B12&"|"&$C12,'Base de sorteio'!$I$3:$I$1723,0)),"") | I12: =IF(E12="","",HYPERLINK(IFERROR(INDEX('Base de sorteio'!$J$3:$J$1723,MATCH($B12&"|"&$C12,'Base de sorteio'!$I$3:$I$1723,0)),""),"abrir")) | N12: =IF(AND(K12="",M12=""),"",IF(OR(K12="sim",M12="sim"),"sim",IF(OR(K12="inconclusivo",M12="inconclusivo"),"inconclusivo","não"))) | O12: =IF(N12="sim",COUNTIFS($B$3:$B12,$B12,$N$3:$N12,"sim"),"")
A13: =ROW()-2 | B13: Metrópole | C13: 11 | D13: =IFERROR(INDEX('Base de sorteio'!$A$3:$A$1723,MATCH($B13&"|"&$C13,'Base de sorteio'!$I$3:$I$1723,0)),"") | E13: =IFERROR(INDEX('Base de sorteio'!$B$3:$B$1723,MATCH($B13&"|"&$C13,'Base de sorteio'!$I$3:$I$1723,0)),"") | F13: =IFERROR(INDEX('Base de sorteio'!$C$3:$C$1723,MATCH($B13&"|"&$C13,'Base de sorteio'!$I$3:$I$1723,0)),"") | G13: =IFERROR(INDEX('Base de sorteio'!$D$3:$D$1723,MATCH($B13&"|"&$C13,'Base de sorteio'!$I$3:$I$1723,0)),"") | H13: =IFERROR(INDEX('Base de sorteio'!$E$3:$E$1723,MATCH($B13&"|"&$C13,'Base de sorteio'!$I$3:$I$1723,0)),"") | I13: =IF(E13="","",HYPERLINK(IFERROR(INDEX('Base de sorteio'!$J$3:$J$1723,MATCH($B13&"|"&$C13,'Base de sorteio'!$I$3:$I$1723,0)),""),"abrir")) | N13: =IF(AND(K13="",M13=""),"",IF(OR(K13="sim",M13="sim"),"sim",IF(OR(K13="inconclusivo",M13="inconclusivo"),"inconclusivo","não"))) | O13: =IF(N13="sim",COUNTIFS($B$3:$B13,$B13,$N$3:$N13,"sim"),"")
A14: =ROW()-2 | B14: Metrópole | C14: 12 | D14: =IFERROR(INDEX('Base de sorteio'!$A$3:$A$1723,MATCH($B14&"|"&$C14,'Base de sorteio'!$I$3:$I$1723,0)),"") | E14: =IFERROR(INDEX('Base de sorteio'!$B$3:$B$1723,MATCH($B14&"|"&$C14,'Base de sorteio'!$I$3:$I$1723,0)),"") | F14: =IFERROR(INDEX('Base de sorteio'!$C$3:$C$1723,MATCH($B14&"|"&$C14,'Base de sorteio'!$I$3:$I$1723,0)),"") | G14: =IFERROR(INDEX('Base de sorteio'!$D$3:$D$1723,MATCH($B14&"|"&$C14,'Base de sorteio'!$I$3:$I$1723,0)),"") | H14: =IFERROR(INDEX('Base de sorteio'!$E$3:$E$1723,MATCH($B14&"|"&$C14,'Base de sorteio'!$I$3:$I$1723,0)),"") | I14: =IF(E14="","",HYPERLINK(IFERROR(INDEX('Base de sorteio'!$J$3:$J$1723,MATCH($B14&"|"&$C14,'Base de sorteio'!$I$3:$I$1723,0)),""),"abrir")) | N14: =IF(AND(K14="",M14=""),"",IF(OR(K14="sim",M14="sim"),"sim",IF(OR(K14="inconclusivo",M14="inconclusivo"),"inconclusivo","não"))) | O14: =IF(N14="sim",COUNTIFS($B$3:$B14,$B14,$N$3:$N14,"sim"),"")
... A1703: =ROW()-2 | B1703: Capital regional | C1703: 759 | D1703: =IFERROR(INDEX('Base de sorteio'!$A$3:$A$1723,MATCH($B1703&"|"&$C1703,'Base de sorteio'!$I$3:$I$1723,0)),"") | E1703: =IFERROR(INDEX('Base de sorteio'!$B$3:$B$1723,MATCH($B1703&"|"&$C1703,'Base de sorteio'!$I$3:$I$1723,0)),"") | F1703: =IFERROR(INDEX('Base de sorteio'!$C$3:$C$1723,MATCH($B1703&"|"&$C1703,'Base de sorteio'!$I$3:$I$1723,0)),"") | G1703: =IFERROR(INDEX('Base de sorteio'!$D$3:$D$1723,MATCH($B1703&"|"&$C1703,'Base de sorteio'!$I$3:$I$1723,0)),"") | H1703: =IFERROR(INDEX('Base de sorteio'!$E$3:$E$1723,MATCH($B1703&"|"&$C1703,'Base de sorteio'!$I$3:$I$1723,0)),"") | I1703: =IF(E1703="","",HYPERLINK(IFERROR(INDEX('Base de sorteio'!$J$3:$J$1723,MATCH($B1703&"|"&$C1703,'Base de sorteio'!$I$3:$I$1723,0)),""),"abrir")) | N1703: =IF(AND(K1703="",M1703=""),"",IF(OR(K1703="sim",M1703="sim"),"sim",IF(OR(K1703="inconclusivo",M1703="inconclusivo"),"inconclusivo","não"))) | O1703: =IF(N1703="sim",COUNTIFS($B$3:$B1703,$B1703,$N$3:$N1703,"sim"),"")

Sheet Resumo
A1: Resumo da amostragem por estrato
A2: Estrato | B2: Candidatos na base | C2: Casas verificadas | D2: Casas do tipo | E2: Meta de casas do tipo | F2: Faltam | G2: Proporção de casas do tipo
A3: Metrópole | B3: =COUNTIF('Base de sorteio'!$G:$G,A3) | C3: =COUNTIFS(Amostragem!$B$3:$B$1703,A3,Amostragem!$K$3:$K$1703,"<>") | D3: =COUNTIFS(Amostragem!$B$3:$B$1703,A3,Amostragem!$N$3:$N$1703,"sim") | E3: 45 | F3: =MAX(0,E3-D3) | G3: =IF(C3=0,"",D3/C3)
A4: Capital regional | B4: =COUNTIF('Base de sorteio'!$G:$G,A4) | C4: =COUNTIFS(Amostragem!$B$3:$B$1703,A4,Amostragem!$K$3:$K$1703,"<>") | D4: =COUNTIFS(Amostragem!$B$3:$B$1703,A4,Amostragem!$N$3:$N$1703,"sim") | E4: 45 | F4: =MAX(0,E4-D4) | G4: =IF(C4=0,"",D4/C4)
A5: Total | B5: =SUM(B3:B4) | C5: =SUM(C3:C4) | D5: =SUM(D3:D4) | E5: =SUM(E3:E4) | F5: =SUM(F3:F4) | G5: =IF(C5=0,"",D5/C5)
