Workbook
Name P_R01: premissas!$G$5
Name P_R02: premissas!$G$6
Name P_R03: premissas!$G$7
Name P_R04: premissas!$G$8
Name P_R05: premissas!$G$9
Name P_R06: premissas!$G$10
Name P_R07: premissas!$G$11
Name P_R08: premissas!$G$12
Name P_R09: premissas!$G$13
Name P_R10: premissas!$G$14
Name P_R11: premissas!$G$15
Name P_R12: premissas!$G$16
Name P_R13: premissas!$G$17
Name P_R14: premissas!$G$18
Name P_C01: premissas!$G$19
Name P_C02: premissas!$G$20
Name P_C03: premissas!$G$21
Name P_C04: premissas!$G$22
Name P_C05: premissas!$G$23
Name P_C06: premissas!$G$24
Name P_C07: premissas!$G$25
Name P_C08: premissas!$G$26
Name P_C09: premissas!$G$27
Name P_C10: premissas!$G$28
Name P_C11: premissas!$G$29
Name P_C12: premissas!$G$30
Name P_C13: premissas!$G$31
Name P_I01: premissas!$G$32
Name P_I02: premissas!$G$33
Name P_I03: premissas!$G$34
Name P_I04: premissas!$G$35
Name P_I05: premissas!$G$36
Name P_I06: premissas!$G$37
Name P_I07: premissas!$G$38
Name P_I08: premissas!$G$39
Name P_M01: premissas!$G$40
Name P_M02: premissas!$G$41
Name FOLHA_REF: pessoal!$E$11
Name P_CEN: premissas!$D$2

Sheet premissas
A1: Registro de premissas do modelo financeiro
A2: Cenário ativo (1 = pessimista, 2 = provável, 3 = otimista) | D2: 2
A4: ID | B4: Premissa | C4: Unidade | D4: Pessimista | E4: Provável | F4: Otimista | G4: Valor usado | H4: Fonte | I4: Nível | J4: Justificativa da faixa | K4: Impacto no VPL
A5: R01 | B5: Mesas do salão | C5: mesas | D5: 8 | E5: 10 | F5: 11 | G5: =CHOOSE($D$2,D5,E5,F5) | H5: B3: São Jogue Paralela (10) e Bela Vista (11), informação do autor | I5: N5 | J5: Formato de referência igual a uma unidade da São Jogue; 8 se o ponto for menor. | K5: Alto
A6: R02 | B6: Pessoas por grupo de mesa | C6: pessoas | D6: 2.8 | E6: 3.6 | F6: 4.4 | G6: =CHOOSE($D$2,D6,E6,F6) | H6: B3, 4 visitas (out/2026) | I6: N5 | J6: Média das visitas 3.6, de 2.4 a 4.6. | K6: Alto
A7: R03 | B7: Permanência média | C7: min | D7: 137 | E7: 109 | F7: 83 | G7: =CHOOSE($D$2,D7,E7,F7) | H7: B3, 4 visitas (out/2026) | I7: N5 | J7: Médias por visita de 83 a 137 min; permanência maior reduz o giro. | K7: Alto
A8: R04 | B8: Taxa de ocupação, fim de semana (sex a dom) | C8: % das mesas | D8: 0.25 | E8: 0.35 | F8: 0.45 | G8: =CHOOSE($D$2,D8,E8,F8) | H8: B3, noites de sexta e sábado (out/2026) | I8: N5 + N6 | J8: Noite de sexta e sábado: 26.9% a 60.3% (média 41.7%). O dia inteiro fica abaixo do pico da noite. | K8: Alto
A9: R05 | B9: Taxa de ocupação, dia útil (seg a qui) | C9: % das mesas | D9: 0.1 | E9: 0.18 | F9: 0.25 | G9: =CHOOSE($D$2,D9,E9,F9) | H9: Estimativa do autor | I9: N6 | J9: Cerca de metade do fim de semana. As visitas medem o pico, por orientação; sem dado de dia útil. | K9: Alto
A10: R06 | B10: Taxa de entrada, fim de semana | C10: R$ por pessoa | D10: 25 | E10: 28 | F10: 30 | G10: =CHOOSE($D$2,D10,E10,F10) | H10: São Jogue: NFC-e de out/2026 e informação do autor | I10: N3 + N5 | J10: R$ 28,00 por 3 h de sexta a domingo na São Jogue; faixa de ± R$ 3,00. | K10: Baixo
A11: R07 | B11: Taxa de entrada, dia útil | C11: R$ por pessoa | D11: 20 | E11: 22 | F11: 25 | G11: =CHOOSE($D$2,D11,E11,F11) | H11: São Jogue: informação do autor | I11: N3 | J11: R$ 22,00 de segunda a quinta na São Jogue. | K11: Baixo
A12: R08 | B12: Gasto com alimentos e bebidas | C12: R$ por pessoa | D12: 18 | E12: 24 | F12: 32 | G12: =CHOOSE($D$2,D12,E12,F12) | H12: B3, 4 NFC-e das mesas dos observadores; cardápio da São Jogue (B1) | I12: N3 + N5 | J12: Média de R$ 23.91 por pessoa nas notas (sem taxa, jogos e serviço); hambúrguer a R$ 45,00 e drinque a R$ 28,00 no cardápio. | K12: Médio
A13: R09 | B13: Aluguéis de jogos | C13: aluguéis por mês | D13: 10 | E13: 30 | F13: 60 | G13: =CHOOSE($D$2,D13,E13,F13) | H13: Estimativa do autor | I13: N6 | J13: Serviço oferecido pela São Jogue; volume não observado. | K13: Baixo
A14: R10 | B14: Preço médio do aluguel de jogo | C14: R$ | D14: 15 | E14: 30 | F14: 40 | G14: =CHOOSE($D$2,D14,E14,F14) | H14: Tabela da São Jogue (4 dias: R$ 15,00 a R$ 60,00) | I14: N3 | J14: Categoria prata como provável. | K14: Baixo
A15: R11 | B15: Ocupação no mês 1 | C15: % da madura | D15: 0.3 | E15: 0.4 | F15: 0.5 | G15: =CHOOSE($D$2,D15,E15,F15) | H15: Estimativa do autor (_instrucoes, §5) | I15: N6 | J15: Sem ocupação madura no mês 1. | K15: Baixo
A16: R12 | B16: Meses até a maturidade | C16: meses | D16: 12 | E16: 9 | F16: 6 | G16: =CHOOSE($D$2,D16,E16,F16) | H16: Estimativa do autor (_instrucoes, §5) | I16: N6 | J16: Rampa de 6 a 12 meses. | K16: Baixo
... A41: M02 | B41: Semanas por mês | C41: semanas | D41: 4.3333333 | E41: 4.3333333 | F41: 4.3333333 | G41: =CHOOSE($D$2,D41,E41,F41) | H41: Calendário | I41: N1 | J41: 52 semanas ÷ 12 meses. | K41: Baixo
A43: Fonte: elaboração própria com dados dos Blocos B1, B3 e B4 (out/2026). Níveis de evidência N1 (mais confiável) a N6 (estimativa do autor), conforme _instrucoes/8_financeiro.md. Impacto no VPL pelo tornado (aba sensibilidade): 5 maiores = Alto, 5 seguintes = Médio.

Sheet pessoal
A1: Quadro de pessoal de referência e salários de admissão em Salvador
A2: Cargo | B2: CBO | C2: Quantidade | D2: Salário mensal (R$) | E2: Total mensal (R$) | F2: Fonte
A3: Gerente | B3: 141510 | C3: 1 | D3: 2500 | E3: =C3*D3 | F3: CAGED, admissões ago/2025-jul/2026, Salvador, CNAE 56, mediana
A4: Cozinheiro | B4: 513205 | C4: 2 | D4: 1700 | E4: =C4*D4 | F4: CAGED, admissões ago/2025-jul/2026, Salvador, CNAE 56, mediana
A5: Auxiliar de cozinha | B5: 513505 | C5: 1 | D5: 1625.09 | E5: =C5*D5 | F5: CAGED, admissões ago/2025-jul/2026, Salvador, CNAE 56, mediana
A6: Garçom | B6: 513405 | C6: 3 | D6: 1625.09 | E6: =C6*D6 | F6: CAGED, admissões ago/2025-jul/2026, Salvador, CNAE 56, mediana
A7: Atendente de bar e balcão | B7: 513435 | C7: 1 | D7: 1625.09 | E7: =C7*D7 | F7: CAGED, admissões ago/2025-jul/2026, Salvador, CNAE 56, mediana
A8: Operador de caixa | B8: 421125 | C8: 1 | D8: 1625.09 | E8: =C8*D8 | F8: CAGED, admissões ago/2025-jul/2026, Salvador, CNAE 56, mediana
A9: Instrutor de jogos (recreador) | B9: 371410 | C9: 2 | D9: 1653.75 | E9: =C9*D9 | F9: CAGED, admissões ago/2025-jul/2026, Salvador, todas as atividades, mediana (CNAE 56 com amostra pequena)
A10: Auxiliar de limpeza | B10: 514320 | C10: 1 | D10: 1625.09 | E10: =C10*D10 | F10: CAGED, admissões ago/2025-jul/2026, Salvador, CNAE 56, mediana
A11: Total | C11: =SUM(C3:C10) | E11: =SUM(E3:E10)
A13: Fonte: Novo CAGED (MTE), salário de admissão, mediana, ago/2025 a jul/2026 (B4). Encargos e fator do quadro na aba premissas (C06 e C07).

Sheet simples
A1: Simples Nacional: faixas dos anexos I e III e alíquota efetiva por ano
A3: Anexo I
A4: Faixa | B4: RBT12 mínima (R$) | C4: RBT12 máxima (R$) | D4: Alíquota nominal (%) | E4: Parcela a deduzir (R$)
A5: 1 | B5: 0 | C5: 180000 | D5: 4 | E5: 0
A6: 2 | B6: 180000.01 | C6: 360000 | D6: 7.3 | E6: 5940
A7: 3 | B7: 360000.01 | C7: 720000 | D7: 9.5 | E7: 13860
A8: 4 | B8: 720000.01 | C8: 1800000 | D8: 10.7 | E8: 22500
A9: 5 | B9: 1800000 | C9: 3600000 | D9: 14.3 | E9: 87300
A10: 6 | B10: 3600000 | C10: 4800000 | D10: 19 | E10: 378000
A12: Anexo III
A13: Faixa | B13: RBT12 mínima (R$) | C13: RBT12 máxima (R$) | D13: Alíquota nominal (%) | E13: Parcela a deduzir (R$)
A14: 1 | B14: 0 | C14: 180000 | D14: 6 | E14: 0
A15: 2 | B15: 180000.01 | C15: 360000 | D15: 11.2 | E15: 9360
A16: 3 | B16: 360000.01 | C16: 720000 | D16: 13.5 | E16: 17640
A17: 4 | B17: 720000.01 | C17: 1800000 | D17: 16 | E17: 35640
A18: 5 | B18: 1800000 | C18: 3600000 | D18: 21 | E18: 125640
A19: 6 | B19: 3600000 | C19: 4800000 | D19: 33 | E19: 648000
A22: Ano | B22: 1 | C22: 2 | D22: 3 | E22: 4 | F22: 5
A23: Receita bruta do ano (R$) | B23: =SUMIF(receitas!$C$3:$BJ$3,B22,receitas!$C$12:$BJ$12) | C23: =SUMIF(receitas!$C$3:$BJ$3,C22,receitas!$C$12:$BJ$12) | D23: =SUMIF(receitas!$C$3:$BJ$3,D22,receitas!$C$12:$BJ$12) | E23: =SUMIF(receitas!$C$3:$BJ$3,E22,receitas!$C$12:$BJ$12) | F23: =SUMIF(receitas!$C$3:$BJ$3,F22,receitas!$C$12:$BJ$12)
A24: Alíquota efetiva, anexo I (A&B) | B24: =IF(B23<=0,0,MAX(0,(B23*LOOKUP(B23,$B$5:$B$10,$D$5:$D$10)/100-LOOKUP(B23,$B$5:$B$10,$E$5:$E$10))/B23)) | C24: =IF(C23<=0,0,MAX(0,(C23*LOOKUP(C23,$B$5:$B$10,$D$5:$D$10)/100-LOOKUP(C23,$B$5:$B$10,$E$5:$E$10))/C23)) | D24: =IF(D23<=0,0,MAX(0,(D23*LOOKUP(D23,$B$5:$B$10,$D$5:$D$10)/100-LOOKUP(D23,$B$5:$B$10,$E$5:$E$10))/D23)) | E24: =IF(E23<=0,0,MAX(0,(E23*LOOKUP(E23,$B$5:$B$10,$D$5:$D$10)/100-LOOKUP(E23,$B$5:$B$10,$E$5:$E$10))/E23)) | F24: =IF(F23<=0,0,MAX(0,(F23*LOOKUP(F23,$B$5:$B$10,$D$5:$D$10)/100-LOOKUP(F23,$B$5:$B$10,$E$5:$E$10))/F23))
A25: Alíquota efetiva, anexo III (taxa de entrada e aluguel de jogos) | B25: =IF(B23<=0,0,MAX(0,(B23*LOOKUP(B23,$B$14:$B$19,$D$14:$D$19)/100-LOOKUP(B23,$B$14:$B$19,$E$14:$E$19))/B23)) | C25: =IF(C23<=0,0,MAX(0,(C23*LOOKUP(C23,$B$14:$B$19,$D$14:$D$19)/100-LOOKUP(C23,$B$14:$B$19,$E$14:$E$19))/C23)) | D25: =IF(D23<=0,0,MAX(0,(D23*LOOKUP(D23,$B$14:$B$19,$D$14:$D$19)/100-LOOKUP(D23,$B$14:$B$19,$E$14:$E$19))/D23)) | E25: =IF(E23<=0,0,MAX(0,(E23*LOOKUP(E23,$B$14:$B$19,$D$14:$D$19)/100-LOOKUP(E23,$B$14:$B$19,$E$14:$E$19))/E23)) | F25: =IF(F23<=0,0,MAX(0,(F23*LOOKUP(F23,$B$14:$B$19,$D$14:$D$19)/100-LOOKUP(F23,$B$14:$B$19,$E$14:$E$19))/F23))
A27: Fonte: LC 123/2006, anexos I e III, valores de 2026 (B4). Enquadramento a confirmar no cap. 8: A&B no anexo I (CNAE 5611-2/01); taxa de entrada e aluguel de jogos no anexo III. RBT12 aproximada pela receita do próprio ano.

Sheet receitas
A1: Receitas mensais projetadas (preços de out/2026)
A2: Mês | C2: 1 | D2: 2 | E2: 3 | F2: 4 | G2: 5 | H2: 6 | I2: 7 | J2: 8 | K2: 9 | L2: 10 | M2: 11 | N2: 12 | O2: 13 | P2: 14 | Q2: 15 | R2: 16 | S2: 17 | T2: 18 | U2: 19 | V2: 20 | W2: 21 | X2: 22 | Y2: 23 | Z2: 24 | AA2: 25 | AB2: 26 | AC2: 27 | AD2: 28 | AE2: 29 | AF2: 30 | AG2: 31 | AH2: 32 | AI2: 33 | AJ2: 34 | AK2: 35 | AL2: 36 | AM2: 37 | AN2: 38 | AO2: 39 | AP2: 40 | AQ2: 41 | AR2: 42 | AS2: 43 | AT2: 44 | AU2: 45 | AV2: 46 | AW2: 47 | AX2: 48 | AY2: 49 | AZ2: 50 | BA2: 51 | BB2: 52 | BC2: 53 | BD2: 54 | BE2: 55 | BF2: 56 | BG2: 57 | BH2: 58 | BI2: 59 | BJ2: 60
A3: Ano | C3: =ROUNDUP(C2/12,0) | D3: =ROUNDUP(D2/12,0) | E3: =ROUNDUP(E2/12,0) | F3: =ROUNDUP(F2/12,0) | G3: =ROUNDUP(G2/12,0) | H3: =ROUNDUP(H2/12,0) | I3: =ROUNDUP(I2/12,0) | J3: =ROUNDUP(J2/12,0) | ... BJ3: =ROUNDUP(BJ2/12,0)
A4: Fator de rampa (% da ocupação madura) | C4: =MIN(1,P_R11+(1-P_R11)*(C2-1)/(P_R12-1)) | D4: =MIN(1,P_R11+(1-P_R11)*(D2-1)/(P_R12-1)) | E4: =MIN(1,P_R11+(1-P_R11)*(E2-1)/(P_R12-1)) | F4: =MIN(1,P_R11+(1-P_R11)*(F2-1)/(P_R12-1)) | G4: =MIN(1,P_R11+(1-P_R11)*(G2-1)/(P_R12-1)) | H4: =MIN(1,P_R11+(1-P_R11)*(H2-1)/(P_R12-1)) | I4: =MIN(1,P_R11+(1-P_R11)*(I2-1)/(P_R12-1)) | J4: =MIN(1,P_R11+(1-P_R11)*(J2-1)/(P_R12-1)) | ... BJ4: =MIN(1,P_R11+(1-P_R11)*(BJ2-1)/(P_R12-1))
A5: Pessoas, fim de semana | C5: =P_R01*P_R02*(P_R13*60/P_R03)*P_R04*C4*P_M02 | D5: =P_R01*P_R02*(P_R13*60/P_R03)*P_R04*D4*P_M02 | E5: =P_R01*P_R02*(P_R13*60/P_R03)*P_R04*E4*P_M02 | F5: =P_R01*P_R02*(P_R13*60/P_R03)*P_R04*F4*P_M02 | G5: =P_R01*P_R02*(P_R13*60/P_R03)*P_R04*G4*P_M02 | H5: =P_R01*P_R02*(P_R13*60/P_R03)*P_R04*H4*P_M02 | I5: =P_R01*P_R02*(P_R13*60/P_R03)*P_R04*I4*P_M02 | J5: =P_R01*P_R02*(P_R13*60/P_R03)*P_R04*J4*P_M02 | ... BJ5: =P_R01*P_R02*(P_R13*60/P_R03)*P_R04*BJ4*P_M02
A6: Pessoas, dia útil | C6: =P_R01*P_R02*(P_R14*60/P_R03)*P_R05*C4*P_M02 | D6: =P_R01*P_R02*(P_R14*60/P_R03)*P_R05*D4*P_M02 | E6: =P_R01*P_R02*(P_R14*60/P_R03)*P_R05*E4*P_M02 | F6: =P_R01*P_R02*(P_R14*60/P_R03)*P_R05*F4*P_M02 | G6: =P_R01*P_R02*(P_R14*60/P_R03)*P_R05*G4*P_M02 | H6: =P_R01*P_R02*(P_R14*60/P_R03)*P_R05*H4*P_M02 | I6: =P_R01*P_R02*(P_R14*60/P_R03)*P_R05*I4*P_M02 | J6: =P_R01*P_R02*(P_R14*60/P_R03)*P_R05*J4*P_M02 | ... BJ6: =P_R01*P_R02*(P_R14*60/P_R03)*P_R05*BJ4*P_M02
A7: Pessoas atendidas | C7: =C5+C6 | D7: =D5+D6 | E7: =E5+E6 | F7: =F5+F6 | G7: =G5+G6 | H7: =H5+H6 | I7: =I5+I6 | J7: =J5+J6 | ... BJ7: =BJ5+BJ6
A8: Taxa de entrada, fim de semana (R$) | C8: =C5*P_R06 | D8: =D5*P_R06 | E8: =E5*P_R06 | F8: =F5*P_R06 | G8: =G5*P_R06 | H8: =H5*P_R06 | I8: =I5*P_R06 | J8: =J5*P_R06 | ... BJ8: =BJ5*P_R06
A9: Taxa de entrada, dia útil (R$) | C9: =C6*P_R07 | D9: =D6*P_R07 | E9: =E6*P_R07 | F9: =F6*P_R07 | G9: =G6*P_R07 | H9: =H6*P_R07 | I9: =I6*P_R07 | J9: =J6*P_R07 | ... BJ9: =BJ6*P_R07
A10: Alimentos e bebidas (R$) | C10: =C7*P_R08 | D10: =D7*P_R08 | E10: =E7*P_R08 | F10: =F7*P_R08 | G10: =G7*P_R08 | H10: =H7*P_R08 | I10: =I7*P_R08 | J10: =J7*P_R08 | ... BJ10: =BJ7*P_R08
A11: Aluguel de jogos (R$) | C11: =P_R09*P_R10*C4 | D11: =P_R09*P_R10*D4 | E11: =P_R09*P_R10*E4 | F11: =P_R09*P_R10*F4 | G11: =P_R09*P_R10*G4 | H11: =P_R09*P_R10*H4 | I11: =P_R09*P_R10*I4 | J11: =P_R09*P_R10*J4 | ... BJ11: =P_R09*P_R10*BJ4
A12: Receita bruta (R$) | C12: =SUM(C8:C11) | D12: =SUM(D8:D11) | E12: =SUM(E8:E11) | F12: =SUM(F8:F11) | G12: =SUM(G8:G11) | H12: =SUM(H8:H11) | I12: =SUM(I8:I11) | J12: =SUM(J8:J11) | ... BJ12: =SUM(BJ8:BJ11)

Sheet custos
A1: Custos e despesas mensais projetados (preços de out/2026)
A2: Mês | C2: 1 | D2: 2 | E2: 3 | F2: 4 | G2: 5 | H2: 6 | I2: 7 | J2: 8 | K2: 9 | L2: 10 | M2: 11 | N2: 12 | O2: 13 | P2: 14 | Q2: 15 | R2: 16 | S2: 17 | T2: 18 | U2: 19 | V2: 20 | W2: 21 | X2: 22 | Y2: 23 | Z2: 24 | AA2: 25 | AB2: 26 | AC2: 27 | AD2: 28 | AE2: 29 | AF2: 30 | AG2: 31 | AH2: 32 | AI2: 33 | AJ2: 34 | AK2: 35 | AL2: 36 | AM2: 37 | AN2: 38 | AO2: 39 | AP2: 40 | AQ2: 41 | AR2: 42 | AS2: 43 | AT2: 44 | AU2: 45 | AV2: 46 | AW2: 47 | AX2: 48 | AY2: 49 | AZ2: 50 | BA2: 51 | BB2: 52 | BC2: 53 | BD2: 54 | BE2: 55 | BF2: 56 | BG2: 57 | BH2: 58 | BI2: 59 | BJ2: 60
A3: Ano | C3: =receitas!C3 | D3: =receitas!D3 | E3: =receitas!E3 | F3: =receitas!F3 | G3: =receitas!G3 | H3: =receitas!H3 | I3: =receitas!I3 | J3: =receitas!J3 | ... BJ3: =receitas!BJ3
A4: Simples Nacional (R$) | C4: =receitas!C10*INDEX(simples!$B$24:$F$24,C3)+(receitas!C8+receitas!C9+receitas!C11)*INDEX(simples!$B$25:$F$25,C3) | D4: =receitas!D10*INDEX(simples!$B$24:$F$24,D3)+(receitas!D8+receitas!D9+receitas!D11)*INDEX(simples!$B$25:$F$25,D3) | E4: =receitas!E10*INDEX(simples!$B$24:$F$24,E3)+(receitas!E8+receitas!E9+receitas!E11)*INDEX(simples!$B$25:$F$25,E3) | F4: =receitas!F10*INDEX(simples!$B$24:$F$24,F3)+(receitas!F8+receitas!F9+receitas!F11)*INDEX(simples!$B$25:$F$25,F3) | G4: =receitas!G10*INDEX(simples!$B$24:$F$24,G3)+(receitas!G8+receitas!G9+receitas!G11)*INDEX(simples!$B$25:$F$25,G3) | H4: =receitas!H10*INDEX(simples!$B$24:$F$24,H3)+(receitas!H8+receitas!H9+receitas!H11)*INDEX(simples!$B$25:$F$25,H3) | I4: =receitas!I10*INDEX(simples!$B$24:$F$24,I3)+(receitas!I8+receitas!I9+receitas!I11)*INDEX(simples!$B$25:$F$25,I3) | J4: =receitas!J10*INDEX(simples!$B$24:$F$24,J3)+(receitas!J8+receitas!J9+receitas!J11)*INDEX(simples!$B$25:$F$25,J3) | ... BJ4: =receitas!BJ10*INDEX(simples!$B$24:$F$24,BJ3)+(receitas!BJ8+receitas!BJ9+receitas!BJ11)*INDEX(simples!$B$25:$F$25,BJ3)
A5: CMV de alimentos e bebidas (R$) | C5: =receitas!C10*P_C01 | D5: =receitas!D10*P_C01 | E5: =receitas!E10*P_C01 | F5: =receitas!F10*P_C01 | G5: =receitas!G10*P_C01 | H5: =receitas!H10*P_C01 | I5: =receitas!I10*P_C01 | J5: =receitas!J10*P_C01 | ... BJ5: =receitas!BJ10*P_C01
A6: Taxa de cartão (R$) | C6: =receitas!C12*P_C02 | D6: =receitas!D12*P_C02 | E6: =receitas!E12*P_C02 | F6: =receitas!F12*P_C02 | G6: =receitas!G12*P_C02 | H6: =receitas!H12*P_C02 | I6: =receitas!I12*P_C02 | J6: =receitas!J12*P_C02 | ... BJ6: =receitas!BJ12*P_C02
A7: Custos variáveis (R$) | C7: =SUM(C4:C6) | D7: =SUM(D4:D6) | E7: =SUM(E4:E6) | F7: =SUM(F4:F6) | G7: =SUM(G4:G6) | H7: =SUM(H4:H6) | I7: =SUM(I4:I6) | J7: =SUM(J4:J6) | ... BJ7: =SUM(BJ4:BJ6)
A8: Aluguel (R$) | C8: =P_C03*P_C04 | D8: =P_C03*P_C04 | E8: =P_C03*P_C04 | F8: =P_C03*P_C04 | G8: =P_C03*P_C04 | H8: =P_C03*P_C04 | I8: =P_C03*P_C04 | J8: =P_C03*P_C04 | ... BJ8: =P_C03*P_C04
A9: Condomínio e IPTU (R$) | C9: =C8*P_C05 | D9: =D8*P_C05 | E9: =E8*P_C05 | F9: =F8*P_C05 | G9: =G8*P_C05 | H9: =H8*P_C05 | I9: =I8*P_C05 | J9: =J8*P_C05 | ... BJ9: =BJ8*P_C05
A10: Pessoal com encargos (R$) | C10: =FOLHA_REF*P_C06*(1+P_C07) | D10: =FOLHA_REF*P_C06*(1+P_C07) | E10: =FOLHA_REF*P_C06*(1+P_C07) | F10: =FOLHA_REF*P_C06*(1+P_C07) | G10: =FOLHA_REF*P_C06*(1+P_C07) | H10: =FOLHA_REF*P_C06*(1+P_C07) | I10: =FOLHA_REF*P_C06*(1+P_C07) | J10: =FOLHA_REF*P_C06*(1+P_C07) | ... BJ10: =FOLHA_REF*P_C06*(1+P_C07)
A11: Pró-labore (R$) | C11: =P_C08 | D11: =P_C08 | E11: =P_C08 | F11: =P_C08 | G11: =P_C08 | H11: =P_C08 | I11: =P_C08 | J11: =P_C08 | ... BJ11: =P_C08
A12: Utilidades (R$) | C12: =P_C09 | D12: =P_C09 | E12: =P_C09 | F12: =P_C09 | G12: =P_C09 | H12: =P_C09 | I12: =P_C09 | J12: =P_C09 | ... BJ12: =P_C09
A13: Marketing (R$) | C13: =P_C10 | D13: =P_C10 | E13: =P_C10 | F13: =P_C10 | G13: =P_C10 | H13: =P_C10 | I13: =P_C10 | J13: =P_C10 | ... BJ13: =P_C10
A14: Contabilidade (R$) | C14: =P_C11 | D14: =P_C11 | E14: =P_C11 | F14: =P_C11 | G14: =P_C11 | H14: =P_C11 | I14: =P_C11 | J14: =P_C11 | ... BJ14: =P_C11
A15: Sistemas (R$) | C15: =P_C12 | D15: =P_C12 | E15: =P_C12 | F15: =P_C12 | G15: =P_C12 | H15: =P_C12 | I15: =P_C12 | J15: =P_C12 | ... BJ15: =P_C12
A16: Reposição do acervo (R$) | C16: =P_I05*P_C13/12 | D16: =P_I05*P_C13/12 | E16: =P_I05*P_C13/12 | F16: =P_I05*P_C13/12 | G16: =P_I05*P_C13/12 | H16: =P_I05*P_C13/12 | I16: =P_I05*P_C13/12 | J16: =P_I05*P_C13/12 | ... BJ16: =P_I05*P_C13/12
A17: Custos fixos (R$) | C17: =SUM(C8:C16) | D17: =SUM(D8:D16) | E17: =SUM(E8:E16) | F17: =SUM(F8:F16) | G17: =SUM(G8:G16) | H17: =SUM(H8:H16) | I17: =SUM(I8:I16) | J17: =SUM(J8:J16) | ... BJ17: =SUM(BJ8:BJ16)
A18: Custos totais (R$) | C18: =C7+C17 | D18: =D7+D17 | E18: =E7+E17 | F18: =F7+F17 | G18: =G7+G17 | H18: =H7+H17 | I18: =I7+I17 | J18: =J7+J17 | ... BJ18: =BJ7+BJ17

Sheet investimento
A1: Investimento inicial e depreciação
A2: Item | B2: Valor (R$) | C2: Vida útil (anos) | D2: Depreciação anual (R$)
A3: Reforma e instalações | B3: =P_I01*P_C03 | C3: 5 | D3: =IF(C3>0,B3/C3,0)
A4: Mobiliário | B4: =P_I02 | C4: 10 | D4: =IF(C4>0,B4/C4,0)
A5: Cozinha e bar | B5: =P_I03 | C5: 10 | D5: =IF(C5>0,B5/C5,0)
A6: Caixa e informática | B6: =P_I04 | C6: 5 | D6: =IF(C6>0,B6/C6,0)
A7: Acervo inicial de jogos | B7: =P_I05 | C7: 5 | D7: =IF(C7>0,B7/C7,0)
A8: Gastos pré-operacionais | B8: =P_I06 | C8: 5 | D8: =IF(C8>0,B8/C8,0)
A9: Caução do aluguel | B9: =P_I07*custos!$C$8 | C9: 0 | D9: =IF(C9>0,B9/C9,0)
A10: Capital de giro | B10: =P_I08*custos!$C$17 | C10: 0 | D10: =IF(C10>0,B10/C10,0)
A11: Total | B11: =SUM(B3:B10) | D11: =SUM(D3:D10)
A13: Fonte: aba premissas (I01 a I08, C03). Reforma depreciada em 5 anos (prazo típico de locação); caução e capital de giro voltam no ano 5. Sem valor residual dos demais itens.

Sheet dre
A1: Demonstração do resultado projetada (R$, preços de out/2026)
A2: Conta | B2: Ano 1 | C2: Ano 2 | D2: Ano 3 | E2: Ano 4 | F2: Ano 5
A3: Ano (número) | B3: 1 | C3: 2 | D3: 3 | E3: 4 | F3: 5
A4: Receita bruta | B4: =SUMIF(receitas!$C$3:$BJ$3,B$3,receitas!$C$12:$BJ$12) | C4: =SUMIF(receitas!$C$3:$BJ$3,C$3,receitas!$C$12:$BJ$12) | D4: =SUMIF(receitas!$C$3:$BJ$3,D$3,receitas!$C$12:$BJ$12) | E4: =SUMIF(receitas!$C$3:$BJ$3,E$3,receitas!$C$12:$BJ$12) | F4: =SUMIF(receitas!$C$3:$BJ$3,F$3,receitas!$C$12:$BJ$12)
A5: (-) Simples Nacional | B5: =-SUMIF(custos!$C$3:$BJ$3,B$3,custos!$C$4:$BJ$4) | C5: =-SUMIF(custos!$C$3:$BJ$3,C$3,custos!$C$4:$BJ$4) | D5: =-SUMIF(custos!$C$3:$BJ$3,D$3,custos!$C$4:$BJ$4) | E5: =-SUMIF(custos!$C$3:$BJ$3,E$3,custos!$C$4:$BJ$4) | F5: =-SUMIF(custos!$C$3:$BJ$3,F$3,custos!$C$4:$BJ$4)
A6: Receita líquida | B6: =B4+B5 | C6: =C4+C5 | D6: =D4+D5 | E6: =E4+E5 | F6: =F4+F5
A7: (-) CMV de alimentos e bebidas | B7: =-SUMIF(custos!$C$3:$BJ$3,B$3,custos!$C$5:$BJ$5) | C7: =-SUMIF(custos!$C$3:$BJ$3,C$3,custos!$C$5:$BJ$5) | D7: =-SUMIF(custos!$C$3:$BJ$3,D$3,custos!$C$5:$BJ$5) | E7: =-SUMIF(custos!$C$3:$BJ$3,E$3,custos!$C$5:$BJ$5) | F7: =-SUMIF(custos!$C$3:$BJ$3,F$3,custos!$C$5:$BJ$5)
A8: (-) Taxa de cartão | B8: =-SUMIF(custos!$C$3:$BJ$3,B$3,custos!$C$6:$BJ$6) | C8: =-SUMIF(custos!$C$3:$BJ$3,C$3,custos!$C$6:$BJ$6) | D8: =-SUMIF(custos!$C$3:$BJ$3,D$3,custos!$C$6:$BJ$6) | E8: =-SUMIF(custos!$C$3:$BJ$3,E$3,custos!$C$6:$BJ$6) | F8: =-SUMIF(custos!$C$3:$BJ$3,F$3,custos!$C$6:$BJ$6)
A9: Margem de contribuição | B9: =B6+B7+B8 | C9: =C6+C7+C8 | D9: =D6+D7+D8 | E9: =E6+E7+E8 | F9: =F6+F7+F8
A10: (-) Custos fixos | B10: =-SUMIF(custos!$C$3:$BJ$3,B$3,custos!$C$17:$BJ$17) | C10: =-SUMIF(custos!$C$3:$BJ$3,C$3,custos!$C$17:$BJ$17) | D10: =-SUMIF(custos!$C$3:$BJ$3,D$3,custos!$C$17:$BJ$17) | E10: =-SUMIF(custos!$C$3:$BJ$3,E$3,custos!$C$17:$BJ$17) | F10: =-SUMIF(custos!$C$3:$BJ$3,F$3,custos!$C$17:$BJ$17)
A11: EBITDA | B11: =B9+B10 | C11: =C9+C10 | D11: =D9+D10 | E11: =E9+E10 | F11: =F9+F10
A12: (-) Depreciação e amortização | B12: =-investimento!$D$11 | C12: =-investimento!$D$11 | D12: =-investimento!$D$11 | E12: =-investimento!$D$11 | F12: =-investimento!$D$11
A13: Lucro líquido | B13: =B11+B12 | C13: =C11+C12 | D13: =D11+D12 | E13: =E11+E12 | F13: =F11+F12
A14: Margem líquida | B14: =IF(B4=0,0,B13/B4) | C14: =IF(C4=0,0,C13/C4) | D14: =IF(D4=0,0,D13/D4) | E14: =IF(E4=0,0,E13/E4) | F14: =IF(F4=0,0,F13/F4)
A16: Fonte: abas receitas, custos e investimento. No Simples Nacional, IRPJ e CSLL estão no DAS; não há imposto sobre o lucro à parte.

Sheet fluxo_caixa
A1: Fluxo de caixa projetado (R$, preços de out/2026)
A2: Linha | B2: Ano 0 | C2: Ano 1 | D2: Ano 2 | E2: Ano 3 | F2: Ano 4 | G2: Ano 5
A3: Ano (número) | B3: 0 | C3: 1 | D3: 2 | E3: 3 | F3: 4 | G3: 5
A4: Investimento | B4: =-investimento!$B$11 | C4: 0 | D4: 0 | E4: 0 | F4: 0 | G4: 0
A5: EBITDA | B5: 0 | C5: =dre!B11 | D5: =dre!C11 | E5: =dre!D11 | F5: =dre!E11 | G5: =dre!F11
A6: Retorno da caução e do capital de giro | B6: 0 | C6: 0 | D6: 0 | E6: 0 | F6: 0 | G6: =investimento!$B$9+investimento!$B$10
A7: Fluxo líquido | B7: =SUM(B4:B6) | C7: =SUM(C4:C6) | D7: =SUM(D4:D6) | E7: =SUM(E4:E6) | F7: =SUM(F4:F6) | G7: =SUM(G4:G6)
A8: Fator de desconto | B8: =1/(1+P_M01)^B3 | C8: =1/(1+P_M01)^C3 | D8: =1/(1+P_M01)^D3 | E8: =1/(1+P_M01)^E3 | F8: =1/(1+P_M01)^F3 | G8: =1/(1+P_M01)^G3
A9: Fluxo descontado | B9: =B7*B8 | C9: =C7*C8 | D9: =D7*D8 | E9: =E7*E8 | F9: =F7*F8 | G9: =G7*G8
A10: Fluxo descontado acumulado | B10: =B9 | C10: =B10+C9 | D10: =C10+D9 | E10: =D10+E9 | F10: =E10+F9 | G10: =F10+G9
A11: Payback descontado (auxiliar) | C11: =IF(AND(B10<0,C10>=0),B3+(-B10)/C9,"") | D11: =IF(AND(C10<0,D10>=0),C3+(-C10)/D9,"") | E11: =IF(AND(D10<0,E10>=0),D3+(-D10)/E9,"") | F11: =IF(AND(E10<0,F10>=0),E3+(-E10)/F9,"") | G11: =IF(AND(F10<0,G10>=0),F3+(-F10)/G9,"")

Sheet indicadores
A1: Indicadores de viabilidade do cenário ativo
A2: Indicador | B2: Valor | C2: Unidade
A3: Cenário ativo | B3: =CHOOSE(P_CEN,"pessimista","provável","otimista")
A4: Investimento inicial | B4: =investimento!B11 | C4: R$
A5: VPL a TMA real | B5: =SUM(fluxo_caixa!B9:G9) | C5: R$
A6: TIR real | B6: =IFERROR(IRR(fluxo_caixa!B7:G7),"não há") | C6: % ao ano
A7: Payback descontado | B7: =IF(COUNT(fluxo_caixa!C11:G11)=0,"mais de 5 anos",MIN(fluxo_caixa!C11:G11)) | C7: anos
A8: Receita bruta mensal madura (mês 60) | B8: =receitas!BJ12 | C8: R$
A9: Custos fixos mensais | B9: =custos!BJ17 | C9: R$
A10: Margem de contribuição (ano 5) | B10: =dre!F9/dre!F4 | C10: % da receita bruta
A11: Receita bruta mensal de equilíbrio | B11: =B9/B10 | C11: R$
A12: Receita madura ÷ receita de equilíbrio | B12: =B8/B11 | C12: vezes
A13: Ocupação de equilíbrio, fim de semana (dia útil na mesma proporção) | B13: =P_R04*(B11-receitas!BJ11)/(B8-receitas!BJ11) | C13: % das mesas
A14: Ocupação de equilíbrio, dia útil (mesma proporção) | B14: =P_R05*(B11-receitas!BJ11)/(B8-receitas!BJ11) | C14: % das mesas
A16: Fonte: abas fluxo_caixa, dre, receitas e custos. Ocupação de equilíbrio por aproximação linear: a receita sem o aluguel de jogos cresce na proporção da ocupação.

Sheet sensibilidade
A1: Cenários, tornado e pontos de ruptura (calculados pelo script com as mesmas fórmulas)
A2: Cenário | B2: Investimento (R$) | C2: Receita mensal madura (R$) | D2: EBITDA do ano 5 (R$) | E2: VPL (R$) | F2: TIR real | G2: Payback descontado (anos)
A3: pessimista | B3: 849496.78 | C3: 19407.46 | D3: -649980.77 | E3: -2824035.8 | F3: não há | G3: mais de 5
A4: provável | B4: 503230.63 | C4: 73100.807 | D4: 23404.74 | E4: -478828.55 | F4: -0.20982423 | G4: mais de 5
A5: otimista | B5: 288832.17 | C5: 207261.46 | D5: 1302846.2 | E5: 4263293.4 | F5: 3.9404285 | G5: 0.29495333
A7: Tornado: VPL com a premissa no extremo e as demais no provável
A8: ID | B8: Premissa | C8: VPL no pessimista (R$) | D8: VPL no otimista (R$) | E8: Amplitude (R$) | F8: Ordem
A9: R03 | B9: Permanência média | C9: -867681.49 | D9: 113004.57 | E9: 980686.06 | F9: 1
A10: R02 | B10: Pessoas por grupo de mesa | C10: -902268.02 | D10: -58793.887 | E10: 843474.14 | F10: 2
A11: R04 | B11: Taxa de ocupação, fim de semana (sex a dom) | C11: -810496.41 | D11: -148443.59 | E11: 662052.82 | F11: 3
A12: R05 | B12: Taxa de ocupação, dia útil (seg a qui) | C12: -806490.08 | D12: -193065.51 | E12: 613424.57 | F12: 4
A13: R01 | B13: Mesas do salão | C13: -859192.06 | D13: -289454.77 | E13: 569737.29 | F13: 5
A14: R08 | B14: Gasto com alimentos e bebidas | C14: -663919.6 | D14: -232284 | E14: 431635.6 | F14: 6
A15: C06 | B15: Fator do quadro de pessoal | C15: -672609 | D15: -285048.11 | E15: 387560.89 | F15: 7
A16: C03 | B16: Área do ponto | C16: -629264.83 | D16: -366001.34 | E16: 263263.49 | F16: 8
A17: C04 | B17: Aluguel comercial | C17: -572439.36 | D17: -394854.15 | E17: 177585.21 | F17: 9
A18: I01 | B18: Reforma e instalações | C18: -550828.55 | D18: -406828.55 | E18: 144000 | F18: 10
A19: R06 | B19: Taxa de entrada, fim de semana | C19: -557413.1 | D19: -426461.94 | E19: 130951.16 | F19: 11
A20: C07 | B20: Encargos e provisões sobre a folha | C20: -546722.43 | D20: -419421.41 | E20: 127301.02 | F20: 12
... A42: I04 | B42: Caixa e informática | C42: -480828.55 | D42: -476828.55 | E42: 4000 | F42: 34
A44: Ponto de ruptura das premissas críticas (VPL = 0, demais no provável)
A45: ID | B45: Premissa | C45: Pessimista | D45: Provável | E45: Otimista | F45: Valor de ruptura | G45: Unidade
A46: R03 | B46: Permanência média | C46: 137 | D46: 109 | E46: 83 | F46: 86.965163 | G46: min
A47: R02 | B47: Pessoas por grupo de mesa | C47: 2.8 | D47: 3.6 | E47: 4.4 | F47: 4.5121516 | G47: pessoas
A48: R04 | B48: Taxa de ocupação, fim de semana (sex a dom) | C48: 0.25 | D48: 0.35 | E48: 0.45 | F48: 0.49502291 | G48: % das mesas
A49: R05 | B49: Taxa de ocupação, dia útil (seg a qui) | C49: 0.1 | D49: 0.18 | E49: 0.25 | F49: 0.29739345 | G49: % das mesas
A50: R01 | B50: Mesas do salão | C50: 8 | D50: 10 | E50: 11 | F50: 12.533754 | G50: mesas
A52: Fonte: elaboração própria. Valores gravados pelo script _src/extras/gerar_modelo_financeiro.py, que recalcula o modelo em Python e confere o VPL com esta planilha nos três cenários; mudar a aba premissas não atualiza esta aba (rodar o script de novo).

Sheet checagens
A1: Triangulação da receita e checagens de coerência (cenário ativo, mês 60)
A2: Checagem | B2: Modelo | C2: Referência | D2: Fonte da referência
A3: Pessoas atendidas por dia | B3: =receitas!BJ7/(P_M02*7) | C3: =P_R01*P_R02*(P_R13+P_R14)*60/P_R03/7 | D3: Capacidade: todas as mesas ocupadas todas as horas, com a permanência média
A4: Uso da capacidade | B4: =B3/C3 | D4: Tem de ficar abaixo de 100%
A5: Grupos atendidos por dia | B5: =B3/P_R02 | C5: 30.5 | D5: NFC-e emitidas por dia, São Jogue Bela Vista, 10/10 a 16/10/2026 (B3); piso, pois a nota sai só a pedido
A6: Grupos atendidos por dia (Paralela) | B6: =B3/P_R02 | C6: 16.1 | D6: NFC-e por dia, São Jogue Paralela, 17/10 a 30/10/2026 (B3), com o fim de semana da eleição
A7: Receita mensal madura × piso de vendas da Bela Vista (R$) | B7: =receitas!BJ12 | C7: 84282.302 | D7: NFC-e por dia × R$ 90.85 por nota (média das 4 notas das mesas dos observadores, sem jogos e serviço) × 30,4 dias
A8: Receita mensal madura × piso de vendas da Paralela (R$) | B8: =receitas!BJ12 | C8: 44490.002 | D8: Idem, Paralela
A9: Receita por pessoa (R$) | B9: =receitas!BJ12/receitas!BJ7 | C9: 45.425 | D9: Notas das mesas dos observadores: taxa e consumo por pessoa
A10: Taxa de entrada de fim de semana (R$) | B10: =P_R06 | C10: 18.75 | D10: Mediana do couvert ou taxa de jogo nos cardápios de 8 concorrentes (B1); acima dela, o posicionamento tem de justificar
A11: Pessoas atendidas por dia por funcionário | B11: =B3/(12*P_C06) | D11: Quadro de referência de 12 em dois turnos (aba pessoal)
A12: Visitas por ano ÷ população de Salvador | B12: =receitas!BJ7*12/C12 | C12: 2559945 | D12: População estimada de Salvador em 2026 (IBGE, B4); visitas, não pessoas distintas
A13: Meses até a maturidade | B13: =P_R12 | D13: Entre 6 e 12 meses (_instrucoes, §5)
A15: Fonte: abas do modelo e Blocos B1, B3 e B4. A comparação com as notas é de ordem de grandeza: a NFC-e só é emitida quando o cliente pede.
