Workbook

Sheet Índice
A1: Dados agregados da pesquisa – TCC Luderia (B1, B3 e B4)
A2: Aba | B2: Tabela | C2: Fonte
A3: Tab 1 | B3: Tabela 1 – Casas do B1 por região e metrópole: São Paulo concentra 19 das 54; Salvador tem uma | C3: B1, Google Places API (09/2026 e 15/10/2026), coletor de entorno do Google Maps (15/10/2026), Instagram (01/09 a 01/10/2026) e cardápios
A4: Tab 2 | B4: Tabela 2 – Estatística descritiva das 54 casas do B1 | C4: B1, Google Places API (09/2026 e 15/10/2026), coletor de entorno do Google Maps (15/10/2026), Instagram (01/09 a 01/10/2026) e cardápios
A5: Tab 3 | B5: Tabela 3 – Dias de funcionamento: todas abrem de quinta a sábado; só 28% abrem na segunda | C5: B1, Google Places API (regularOpeningHours, 15/10/2026)
A6: Tab 4 | B6: Tabela 4 – Painel por região: o Sudeste reúne 31 das 54 casas; no Sul nenhuma tem metrô a até 1 km | C6: B1, Google Places API (09/2026 e 15/10/2026), coletor de entorno do Google Maps (15/10/2026), Instagram (01/09 a 01/10/2026) e cardápios
A7: Tab 5 | B7: Tabela 5 – Painel por metrópole: a cesta por pessoa varia de metrópole para metrópole | C7: B1, Google Places API (09/2026 e 15/10/2026), coletor de entorno do Google Maps (15/10/2026), Instagram (01/09 a 01/10/2026) e cardápios
A8: Tab 6 | B8: Tabela 6 – Entorno pelo Google Maps: a maioria das casas tem shopping a até 1 km; metrô perto é minoria | C8: B1, coletor de entorno do Google Maps (15/10/2026)
A9: Tab 7 | B9: Tabela 7 – Preços nos cardápios: a cesta mediana por pessoa fica em R$ 54 (metade das casas entre R$ 38,50 e R$ 70) | C9: B1, cardápios transcritos (B1_cardapios_itens_precos.xlsx)
A10: Tab 8 | B10: Tabela 8 – Couvert: encontrado no cardápio de 8 das 36 casas com cardápio | C10: B1, cardápios transcritos (B1_cardapios_itens_precos.xlsx)
A11: Tab 9 | B11: Tabela 9 – Modelos de cobrança citados no Instagram: couvert lúdico e inscrição em evento são os mais comuns | C11: B1, legendas do Instagram das casas (coletor do Instagram, 2026), análise de legendas
A12: Tab 10 | B12: Tabela 10 – Eventos no Instagram: encontros/RPG, competições e noites temáticas puxam a agenda | C12: B1, legendas do Instagram das casas (coletor do Instagram, 2026), análise de legendas
A13: Tab 11 | B13: Tabela 11 – Dia citado nos eventos: casas de jogos anunciam mais domingo e quinta; lojas, sábado | C13: B1, legendas do Instagram das casas (coletor do Instagram, 2026), análise de legendas
... A24: Dados B1 | B24: Base das 54 casas do B1 | C24: B1, Google Places API (09/2026 e 15/10/2026), coletor de entorno do Google Maps (15/10/2026), Instagram (01/09 a 01/10/2026) e cardápios
A26: Fora desta planilha, por pedido do autor (30/10/2026): comentários do B2 e dados do OpenStreetMap no entorno.
A27: Gráficos em PNG de 300 dpi em dados/Dados agregados/graficos/. Gerado por _src/extras/gerar_planilha_agregada.py.

Sheet Tab 1
A1: Tabela 1 – Casas do B1 por região e metrópole: São Paulo concentra 19 das 54; Salvador tem uma
A2: Região | B2: Metrópole | C2: Casas | D2: % do total
A3: Norte | B3: Belém | C3: =COUNTIF('Dados B1'!$B$3:$B$56,B3) | D3: =C3/C$16
A4: Nordeste | B4: Fortaleza | C4: =COUNTIF('Dados B1'!$B$3:$B$56,B4) | D4: =C4/C$16
A5: Nordeste | B5: Recife | C5: =COUNTIF('Dados B1'!$B$3:$B$56,B5) | D5: =C5/C$16
A6: Nordeste | B6: Salvador | C6: =COUNTIF('Dados B1'!$B$3:$B$56,B6) | D6: =C6/C$16
A7: Centro-Oeste | B7: Brasília | C7: =COUNTIF('Dados B1'!$B$3:$B$56,B7) | D7: =C7/C$16
A8: Centro-Oeste | B8: Goiânia | C8: =COUNTIF('Dados B1'!$B$3:$B$56,B8) | D8: =C8/C$16
A9: Sudeste | B9: São Paulo | C9: =COUNTIF('Dados B1'!$B$3:$B$56,B9) | D9: =C9/C$16
A10: Sudeste | B10: Belo Horizonte | C10: =COUNTIF('Dados B1'!$B$3:$B$56,B10) | D10: =C10/C$16
A11: Sudeste | B11: Rio de Janeiro | C11: =COUNTIF('Dados B1'!$B$3:$B$56,B11) | D11: =C11/C$16
A12: Sudeste | B12: Vitória | C12: =COUNTIF('Dados B1'!$B$3:$B$56,B12) | D12: =C12/C$16
A13: Sul | B13: Curitiba | C13: =COUNTIF('Dados B1'!$B$3:$B$56,B13) | D13: =C13/C$16
A14: Sul | B14: Florianópolis | C14: =COUNTIF('Dados B1'!$B$3:$B$56,B14) | D14: =C14/C$16
A15: Sul | B15: Porto Alegre | C15: =COUNTIF('Dados B1'!$B$3:$B$56,B15) | D15: =C15/C$16
A16: Total | C16: =SUM(C3:C15) | D16: =SUM(D3:D15)
A17: Conferência (total − casas da base; deve ser 0) | C17: =C16-COUNTA('Dados B1'!$A$3:$A$56)
A18: Fonte: B1, Google Places API (09/2026 e 15/10/2026), coletor de entorno do Google Maps (15/10/2026), Instagram (01/09 a 01/10/2026) e cardápios
A19: Nota: cada casa conta uma vez, na metrópole do endereço.

Sheet Tab 2
A1: Tabela 2 – Estatística descritiva das 54 casas do B1
A2: Grupo | B2: Variável | C2: n (com dado) | D2: Sem dado | E2: Média | F2: Mediana | G2: Desvio padrão | H2: Mínimo | I2: 1º quartil | J2: 3º quartil | K2: Máximo
A3: Google Maps | B3: Nota média no Google (1 a 5) | C3: =COUNT('Dados B1'!$D$3:$D$56) | D3: =ROWS('Dados B1'!$D$3:$D$56)-COUNT('Dados B1'!$D$3:$D$56) | E3: =IFERROR(AVERAGE('Dados B1'!$D$3:$D$56),"") | F3: =IFERROR(MEDIAN('Dados B1'!$D$3:$D$56),"") | G3: =IFERROR(STDEV('Dados B1'!$D$3:$D$56),"") | H3: =IFERROR(MIN('Dados B1'!$D$3:$D$56),"") | I3: =IFERROR(PERCENTILE('Dados B1'!$D$3:$D$56,0.25),"") | J3: =IFERROR(PERCENTILE('Dados B1'!$D$3:$D$56,0.75),"") | K3: =IFERROR(MAX('Dados B1'!$D$3:$D$56),"")
A4: Google Maps | B4: Avaliações no Google | C4: =COUNT('Dados B1'!$E$3:$E$56) | D4: =ROWS('Dados B1'!$E$3:$E$56)-COUNT('Dados B1'!$E$3:$E$56) | E4: =IFERROR(AVERAGE('Dados B1'!$E$3:$E$56),"") | F4: =IFERROR(MEDIAN('Dados B1'!$E$3:$E$56),"") | G4: =IFERROR(STDEV('Dados B1'!$E$3:$E$56),"") | H4: =IFERROR(MIN('Dados B1'!$E$3:$E$56),"") | I4: =IFERROR(PERCENTILE('Dados B1'!$E$3:$E$56,0.25),"") | J4: =IFERROR(PERCENTILE('Dados B1'!$E$3:$E$56,0.75),"") | K4: =IFERROR(MAX('Dados B1'!$E$3:$E$56),"")
A5: Horários | B5: Dias abertos por semana | C5: =COUNT('Dados B1'!$F$3:$F$56) | D5: =ROWS('Dados B1'!$F$3:$F$56)-COUNT('Dados B1'!$F$3:$F$56) | E5: =IFERROR(AVERAGE('Dados B1'!$F$3:$F$56),"") | F5: =IFERROR(MEDIAN('Dados B1'!$F$3:$F$56),"") | G5: =IFERROR(STDEV('Dados B1'!$F$3:$F$56),"") | H5: =IFERROR(MIN('Dados B1'!$F$3:$F$56),"") | I5: =IFERROR(PERCENTILE('Dados B1'!$F$3:$F$56,0.25),"") | J5: =IFERROR(PERCENTILE('Dados B1'!$F$3:$F$56,0.75),"") | K5: =IFERROR(MAX('Dados B1'!$F$3:$F$56),"")
A6: Horários | B6: Horas abertas por semana | C6: =COUNT('Dados B1'!$G$3:$G$56) | D6: =ROWS('Dados B1'!$G$3:$G$56)-COUNT('Dados B1'!$G$3:$G$56) | E6: =IFERROR(AVERAGE('Dados B1'!$G$3:$G$56),"") | F6: =IFERROR(MEDIAN('Dados B1'!$G$3:$G$56),"") | G6: =IFERROR(STDEV('Dados B1'!$G$3:$G$56),"") | H6: =IFERROR(MIN('Dados B1'!$G$3:$G$56),"") | I6: =IFERROR(PERCENTILE('Dados B1'!$G$3:$G$56,0.25),"") | J6: =IFERROR(PERCENTILE('Dados B1'!$G$3:$G$56,0.75),"") | K6: =IFERROR(MAX('Dados B1'!$G$3:$G$56),"")
A7: Horários | B7: Abertura mais cedo (hora do dia) | C7: =COUNT('Dados B1'!$H$3:$H$56) | D7: =ROWS('Dados B1'!$H$3:$H$56)-COUNT('Dados B1'!$H$3:$H$56) | E7: =IFERROR(AVERAGE('Dados B1'!$H$3:$H$56),"") | F7: =IFERROR(MEDIAN('Dados B1'!$H$3:$H$56),"") | G7: =IFERROR(STDEV('Dados B1'!$H$3:$H$56),"") | H7: =IFERROR(MIN('Dados B1'!$H$3:$H$56),"") | I7: =IFERROR(PERCENTILE('Dados B1'!$H$3:$H$56,0.25),"") | J7: =IFERROR(PERCENTILE('Dados B1'!$H$3:$H$56,0.75),"") | K7: =IFERROR(MAX('Dados B1'!$H$3:$H$56),"")
A8: Horários | B8: Fechamento mais tarde (25 = 1h) | C8: =COUNT('Dados B1'!$I$3:$I$56) | D8: =ROWS('Dados B1'!$I$3:$I$56)-COUNT('Dados B1'!$I$3:$I$56) | E8: =IFERROR(AVERAGE('Dados B1'!$I$3:$I$56),"") | F8: =IFERROR(MEDIAN('Dados B1'!$I$3:$I$56),"") | G8: =IFERROR(STDEV('Dados B1'!$I$3:$I$56),"") | H8: =IFERROR(MIN('Dados B1'!$I$3:$I$56),"") | I8: =IFERROR(PERCENTILE('Dados B1'!$I$3:$I$56,0.25),"") | J8: =IFERROR(PERCENTILE('Dados B1'!$I$3:$I$56,0.75),"") | K8: =IFERROR(MAX('Dados B1'!$I$3:$I$56),"")
A9: Entorno (Maps) | B9: Estações de metrô até 500 m | C9: =COUNT('Dados B1'!$Q$3:$Q$56) | D9: =ROWS('Dados B1'!$Q$3:$Q$56)-COUNT('Dados B1'!$Q$3:$Q$56) | E9: =IFERROR(AVERAGE('Dados B1'!$Q$3:$Q$56),"") | F9: =IFERROR(MEDIAN('Dados B1'!$Q$3:$Q$56),"") | G9: =IFERROR(STDEV('Dados B1'!$Q$3:$Q$56),"") | H9: =IFERROR(MIN('Dados B1'!$Q$3:$Q$56),"") | I9: =IFERROR(PERCENTILE('Dados B1'!$Q$3:$Q$56,0.25),"") | J9: =IFERROR(PERCENTILE('Dados B1'!$Q$3:$Q$56,0.75),"") | K9: =IFERROR(MAX('Dados B1'!$Q$3:$Q$56),"")
A10: Entorno (Maps) | B10: Estações de metrô até 1000 m | C10: =COUNT('Dados B1'!$R$3:$R$56) | D10: =ROWS('Dados B1'!$R$3:$R$56)-COUNT('Dados B1'!$R$3:$R$56) | E10: =IFERROR(AVERAGE('Dados B1'!$R$3:$R$56),"") | F10: =IFERROR(MEDIAN('Dados B1'!$R$3:$R$56),"") | G10: =IFERROR(STDEV('Dados B1'!$R$3:$R$56),"") | H10: =IFERROR(MIN('Dados B1'!$R$3:$R$56),"") | I10: =IFERROR(PERCENTILE('Dados B1'!$R$3:$R$56,0.25),"") | J10: =IFERROR(PERCENTILE('Dados B1'!$R$3:$R$56,0.75),"") | K10: =IFERROR(MAX('Dados B1'!$R$3:$R$56),"")
A11: Entorno (Maps) | B11: Distância ao metrô mais próximo (m) | C11: =COUNT('Dados B1'!$S$3:$S$56) | D11: =ROWS('Dados B1'!$S$3:$S$56)-COUNT('Dados B1'!$S$3:$S$56) | E11: =IFERROR(AVERAGE('Dados B1'!$S$3:$S$56),"") | F11: =IFERROR(MEDIAN('Dados B1'!$S$3:$S$56),"") | G11: =IFERROR(STDEV('Dados B1'!$S$3:$S$56),"") | H11: =IFERROR(MIN('Dados B1'!$S$3:$S$56),"") | I11: =IFERROR(PERCENTILE('Dados B1'!$S$3:$S$56,0.25),"") | J11: =IFERROR(PERCENTILE('Dados B1'!$S$3:$S$56,0.75),"") | K11: =IFERROR(MAX('Dados B1'!$S$3:$S$56),"")
A12: Entorno (Maps) | B12: Distância ao shopping mais próximo (m) | C12: =COUNT('Dados B1'!$T$3:$T$56) | D12: =ROWS('Dados B1'!$T$3:$T$56)-COUNT('Dados B1'!$T$3:$T$56) | E12: =IFERROR(AVERAGE('Dados B1'!$T$3:$T$56),"") | F12: =IFERROR(MEDIAN('Dados B1'!$T$3:$T$56),"") | G12: =IFERROR(STDEV('Dados B1'!$T$3:$T$56),"") | H12: =IFERROR(MIN('Dados B1'!$T$3:$T$56),"") | I12: =IFERROR(PERCENTILE('Dados B1'!$T$3:$T$56,0.25),"") | J12: =IFERROR(PERCENTILE('Dados B1'!$T$3:$T$56,0.75),"") | K12: =IFERROR(MAX('Dados B1'!$T$3:$T$56),"")
A13: Instagram | B13: Seguidores | C13: =COUNT('Dados B1'!$U$3:$U$56) | D13: =ROWS('Dados B1'!$U$3:$U$56)-COUNT('Dados B1'!$U$3:$U$56) | E13: =IFERROR(AVERAGE('Dados B1'!$U$3:$U$56),"") | F13: =IFERROR(MEDIAN('Dados B1'!$U$3:$U$56),"") | G13: =IFERROR(STDEV('Dados B1'!$U$3:$U$56),"") | H13: =IFERROR(MIN('Dados B1'!$U$3:$U$56),"") | I13: =IFERROR(PERCENTILE('Dados B1'!$U$3:$U$56,0.25),"") | J13: =IFERROR(PERCENTILE('Dados B1'!$U$3:$U$56,0.75),"") | K13: =IFERROR(MAX('Dados B1'!$U$3:$U$56),"")
A14: Instagram | B14: Posts desde a criação do perfil | C14: =COUNT('Dados B1'!$V$3:$V$56) | D14: =ROWS('Dados B1'!$V$3:$V$56)-COUNT('Dados B1'!$V$3:$V$56) | E14: =IFERROR(AVERAGE('Dados B1'!$V$3:$V$56),"") | F14: =IFERROR(MEDIAN('Dados B1'!$V$3:$V$56),"") | G14: =IFERROR(STDEV('Dados B1'!$V$3:$V$56),"") | H14: =IFERROR(MIN('Dados B1'!$V$3:$V$56),"") | I14: =IFERROR(PERCENTILE('Dados B1'!$V$3:$V$56,0.25),"") | J14: =IFERROR(PERCENTILE('Dados B1'!$V$3:$V$56,0.75),"") | K14: =IFERROR(MAX('Dados B1'!$V$3:$V$56),"")
A15: Instagram | B15: Idade do perfil (anos) | C15: =COUNT('Dados B1'!$W$3:$W$56) | D15: =ROWS('Dados B1'!$W$3:$W$56)-COUNT('Dados B1'!$W$3:$W$56) | E15: =IFERROR(AVERAGE('Dados B1'!$W$3:$W$56),"") | F15: =IFERROR(MEDIAN('Dados B1'!$W$3:$W$56),"") | G15: =IFERROR(STDEV('Dados B1'!$W$3:$W$56),"") | H15: =IFERROR(MIN('Dados B1'!$W$3:$W$56),"") | I15: =IFERROR(PERCENTILE('Dados B1'!$W$3:$W$56,0.25),"") | J15: =IFERROR(PERCENTILE('Dados B1'!$W$3:$W$56,0.75),"") | K15: =IFERROR(MAX('Dados B1'!$W$3:$W$56),"")
A16: Instagram | B16: Posts de 01/09 a 01/10/2026 | C16: =COUNT('Dados B1'!$X$3:$X$56) | D16: =ROWS('Dados B1'!$X$3:$X$56)-COUNT('Dados B1'!$X$3:$X$56) | E16: =IFERROR(AVERAGE('Dados B1'!$X$3:$X$56),"") | F16: =IFERROR(MEDIAN('Dados B1'!$X$3:$X$56),"") | G16: =IFERROR(STDEV('Dados B1'!$X$3:$X$56),"") | H16: =IFERROR(MIN('Dados B1'!$X$3:$X$56),"") | I16: =IFERROR(PERCENTILE('Dados B1'!$X$3:$X$56,0.25),"") | J16: =IFERROR(PERCENTILE('Dados B1'!$X$3:$X$56,0.75),"") | K16: =IFERROR(MAX('Dados B1'!$X$3:$X$56),"")
A17: Instagram | B17: Interações por post | C17: =COUNT('Dados B1'!$Y$3:$Y$56) | D17: =ROWS('Dados B1'!$Y$3:$Y$56)-COUNT('Dados B1'!$Y$3:$Y$56) | E17: =IFERROR(AVERAGE('Dados B1'!$Y$3:$Y$56),"") | F17: =IFERROR(MEDIAN('Dados B1'!$Y$3:$Y$56),"") | G17: =IFERROR(STDEV('Dados B1'!$Y$3:$Y$56),"") | H17: =IFERROR(MIN('Dados B1'!$Y$3:$Y$56),"") | I17: =IFERROR(PERCENTILE('Dados B1'!$Y$3:$Y$56,0.25),"") | J17: =IFERROR(PERCENTILE('Dados B1'!$Y$3:$Y$56,0.75),"") | K17: =IFERROR(MAX('Dados B1'!$Y$3:$Y$56),"")
A18: Instagram | B18: Engajamento (interações por post ÷ seguidores) | C18: =COUNT('Dados B1'!$Z$3:$Z$56) | D18: =ROWS('Dados B1'!$Z$3:$Z$56)-COUNT('Dados B1'!$Z$3:$Z$56) | E18: =IFERROR(AVERAGE('Dados B1'!$Z$3:$Z$56),"") | F18: =IFERROR(MEDIAN('Dados B1'!$Z$3:$Z$56),"") | G18: =IFERROR(STDEV('Dados B1'!$Z$3:$Z$56),"") | H18: =IFERROR(MIN('Dados B1'!$Z$3:$Z$56),"") | I18: =IFERROR(PERCENTILE('Dados B1'!$Z$3:$Z$56,0.25),"") | J18: =IFERROR(PERCENTILE('Dados B1'!$Z$3:$Z$56,0.75),"") | K18: =IFERROR(MAX('Dados B1'!$Z$3:$Z$56),"")
A19: Cardápio | B19: Itens com preço no cardápio | C19: =COUNT('Dados B1'!$AA$3:$AA$56) | D19: =ROWS('Dados B1'!$AA$3:$AA$56)-COUNT('Dados B1'!$AA$3:$AA$56) | E19: =IFERROR(AVERAGE('Dados B1'!$AA$3:$AA$56),"") | F19: =IFERROR(MEDIAN('Dados B1'!$AA$3:$AA$56),"") | G19: =IFERROR(STDEV('Dados B1'!$AA$3:$AA$56),"") | H19: =IFERROR(MIN('Dados B1'!$AA$3:$AA$56),"") | I19: =IFERROR(PERCENTILE('Dados B1'!$AA$3:$AA$56,0.25),"") | J19: =IFERROR(PERCENTILE('Dados B1'!$AA$3:$AA$56,0.75),"") | K19: =IFERROR(MAX('Dados B1'!$AA$3:$AA$56),"")
A20: Cardápio | B20: Couvert ou taxa de jogo (R$, casas que cobram) | C20: =COUNT('Dados B1'!$AD$3:$AD$56) | D20: =ROWS('Dados B1'!$AD$3:$AD$56)-COUNT('Dados B1'!$AD$3:$AD$56) | E20: =IFERROR(AVERAGE('Dados B1'!$AD$3:$AD$56),"") | F20: =IFERROR(MEDIAN('Dados B1'!$AD$3:$AD$56),"") | G20: =IFERROR(STDEV('Dados B1'!$AD$3:$AD$56),"") | H20: =IFERROR(MIN('Dados B1'!$AD$3:$AD$56),"") | I20: =IFERROR(PERCENTILE('Dados B1'!$AD$3:$AD$56,0.25),"") | J20: =IFERROR(PERCENTILE('Dados B1'!$AD$3:$AD$56,0.75),"") | K20: =IFERROR(MAX('Dados B1'!$AD$3:$AD$56),"")
A21: Cardápio | B21: Bebida, mediana do cardápio (R$) | C21: =COUNT('Dados B1'!$AE$3:$AE$56) | D21: =ROWS('Dados B1'!$AE$3:$AE$56)-COUNT('Dados B1'!$AE$3:$AE$56) | E21: =IFERROR(AVERAGE('Dados B1'!$AE$3:$AE$56),"") | F21: =IFERROR(MEDIAN('Dados B1'!$AE$3:$AE$56),"") | G21: =IFERROR(STDEV('Dados B1'!$AE$3:$AE$56),"") | H21: =IFERROR(MIN('Dados B1'!$AE$3:$AE$56),"") | I21: =IFERROR(PERCENTILE('Dados B1'!$AE$3:$AE$56,0.25),"") | J21: =IFERROR(PERCENTILE('Dados B1'!$AE$3:$AE$56,0.75),"") | K21: =IFERROR(MAX('Dados B1'!$AE$3:$AE$56),"")
A22: Cardápio | B22: Entrada ou prato, mediana (R$) | C22: =COUNT('Dados B1'!$AF$3:$AF$56) | D22: =ROWS('Dados B1'!$AF$3:$AF$56)-COUNT('Dados B1'!$AF$3:$AF$56) | E22: =IFERROR(AVERAGE('Dados B1'!$AF$3:$AF$56),"") | F22: =IFERROR(MEDIAN('Dados B1'!$AF$3:$AF$56),"") | G22: =IFERROR(STDEV('Dados B1'!$AF$3:$AF$56),"") | H22: =IFERROR(MIN('Dados B1'!$AF$3:$AF$56),"") | I22: =IFERROR(PERCENTILE('Dados B1'!$AF$3:$AF$56,0.25),"") | J22: =IFERROR(PERCENTILE('Dados B1'!$AF$3:$AF$56,0.75),"") | K22: =IFERROR(MAX('Dados B1'!$AF$3:$AF$56),"")
A23: Cardápio | B23: Cesta por pessoa, nível baixo (R$) | C23: =COUNT('Dados B1'!$AG$3:$AG$56) | D23: =ROWS('Dados B1'!$AG$3:$AG$56)-COUNT('Dados B1'!$AG$3:$AG$56) | E23: =IFERROR(AVERAGE('Dados B1'!$AG$3:$AG$56),"") | F23: =IFERROR(MEDIAN('Dados B1'!$AG$3:$AG$56),"") | G23: =IFERROR(STDEV('Dados B1'!$AG$3:$AG$56),"") | H23: =IFERROR(MIN('Dados B1'!$AG$3:$AG$56),"") | I23: =IFERROR(PERCENTILE('Dados B1'!$AG$3:$AG$56,0.25),"") | J23: =IFERROR(PERCENTILE('Dados B1'!$AG$3:$AG$56,0.75),"") | K23: =IFERROR(MAX('Dados B1'!$AG$3:$AG$56),"")
A24: Cardápio | B24: Cesta por pessoa, nível mediano (R$) | C24: =COUNT('Dados B1'!$AH$3:$AH$56) | D24: =ROWS('Dados B1'!$AH$3:$AH$56)-COUNT('Dados B1'!$AH$3:$AH$56) | E24: =IFERROR(AVERAGE('Dados B1'!$AH$3:$AH$56),"") | F24: =IFERROR(MEDIAN('Dados B1'!$AH$3:$AH$56),"") | G24: =IFERROR(STDEV('Dados B1'!$AH$3:$AH$56),"") | H24: =IFERROR(MIN('Dados B1'!$AH$3:$AH$56),"") | I24: =IFERROR(PERCENTILE('Dados B1'!$AH$3:$AH$56,0.25),"") | J24: =IFERROR(PERCENTILE('Dados B1'!$AH$3:$AH$56,0.75),"") | K24: =IFERROR(MAX('Dados B1'!$AH$3:$AH$56),"")
A25: Cardápio | B25: Cesta por pessoa, nível alto (R$) | C25: =COUNT('Dados B1'!$AI$3:$AI$56) | D25: =ROWS('Dados B1'!$AI$3:$AI$56)-COUNT('Dados B1'!$AI$3:$AI$56) | E25: =IFERROR(AVERAGE('Dados B1'!$AI$3:$AI$56),"") | F25: =IFERROR(MEDIAN('Dados B1'!$AI$3:$AI$56),"") | G25: =IFERROR(STDEV('Dados B1'!$AI$3:$AI$56),"") | H25: =IFERROR(MIN('Dados B1'!$AI$3:$AI$56),"") | I25: =IFERROR(PERCENTILE('Dados B1'!$AI$3:$AI$56,0.25),"") | J25: =IFERROR(PERCENTILE('Dados B1'!$AI$3:$AI$56,0.75),"") | K25: =IFERROR(MAX('Dados B1'!$AI$3:$AI$56),"")
A26: Acervo | B26: Títulos no acervo publicado | C26: =COUNT('Dados B1'!$AO$3:$AO$56) | D26: =ROWS('Dados B1'!$AO$3:$AO$56)-COUNT('Dados B1'!$AO$3:$AO$56) | E26: =IFERROR(AVERAGE('Dados B1'!$AO$3:$AO$56),"") | F26: =IFERROR(MEDIAN('Dados B1'!$AO$3:$AO$56),"") | G26: =IFERROR(STDEV('Dados B1'!$AO$3:$AO$56),"") | H26: =IFERROR(MIN('Dados B1'!$AO$3:$AO$56),"") | I26: =IFERROR(PERCENTILE('Dados B1'!$AO$3:$AO$56,0.25),"") | J26: =IFERROR(PERCENTILE('Dados B1'!$AO$3:$AO$56,0.75),"") | K26: =IFERROR(MAX('Dados B1'!$AO$3:$AO$56),"")
A27: Fonte: B1, Google Places API (09/2026 e 15/10/2026), coletor de entorno do Google Maps (15/10/2026), Instagram (01/09 a 01/10/2026) e cardápios
A28: Nota: desvio padrão amostral; quartis pelo método inclusivo. Engajamento em fração (0,01 = 1%).
A29: Entorno sem OpenStreetMap: shoppings de porte fora. Distância ao metrô vazia onde a cidade não tem metrô lido (Curitiba, Florianópolis, Belém, Goiânia, Vitória).

Sheet Tab 3
A1: Tabela 3 – Dias de funcionamento: todas abrem de quinta a sábado; só 28% abrem na segunda
A2: Dia | B2: Casas que abrem | C2: Casas com horário | D2: % das casas
A3: Segunda | B3: =COUNTIF('Dados B1'!$J$3:$J$56,1) | C3: =COUNT('Dados B1'!$J$3:$J$56) | D3: =B3/C3
A4: Terça | B4: =COUNTIF('Dados B1'!$K$3:$K$56,1) | C4: =COUNT('Dados B1'!$K$3:$K$56) | D4: =B4/C4
A5: Quarta | B5: =COUNTIF('Dados B1'!$L$3:$L$56,1) | C5: =COUNT('Dados B1'!$L$3:$L$56) | D5: =B5/C5
A6: Quinta | B6: =COUNTIF('Dados B1'!$M$3:$M$56,1) | C6: =COUNT('Dados B1'!$M$3:$M$56) | D6: =B6/C6
A7: Sexta | B7: =COUNTIF('Dados B1'!$N$3:$N$56,1) | C7: =COUNT('Dados B1'!$N$3:$N$56) | D7: =B7/C7
A8: Sábado | B8: =COUNTIF('Dados B1'!$O$3:$O$56,1) | C8: =COUNT('Dados B1'!$O$3:$O$56) | D8: =B8/C8
A9: Domingo | B9: =COUNTIF('Dados B1'!$P$3:$P$56,1) | C9: =COUNT('Dados B1'!$P$3:$P$56) | D9: =B9/C9
A10: Fonte: B1, Google Places API (regularOpeningHours, 15/10/2026)
A11: Nota: contagem não exclusiva (cada casa abre em vários dias); cada linha tem o próprio total.

Sheet Tab 4
A1: Tabela 4 – Painel por região: o Sudeste reúne 31 das 54 casas; no Sul nenhuma tem metrô a até 1 km
A2: Região | B2: casas | C2: nota (mediana) | D2: horas abertas por semana (média) | E2: abre domingo (%) | F2: abre segunda (%) | G2: metrô até 1000 m (% das casas) | H2: seguidores (mediana) | I2: casas com cesta | J2: cesta mediana (mediana, R$)
A3: Norte | B3: =COUNTIF('Dados B1'!$C$3:$C$56,$A3) | C3: {=IFERROR(MEDIAN(IF('Dados B1'!$C$3:$C$56=$A3,IF('Dados B1'!$D$3:$D$56<>"",'Dados B1'!$D$3:$D$56))),"")} | D3: =IFERROR(AVERAGEIFS('Dados B1'!$G$3:$G$56,'Dados B1'!$C$3:$C$56,$A3),"") | E3: =IFERROR(AVERAGEIFS('Dados B1'!$P$3:$P$56,'Dados B1'!$C$3:$C$56,$A3),"") | F3: =IFERROR(AVERAGEIFS('Dados B1'!$J$3:$J$56,'Dados B1'!$C$3:$C$56,$A3),"") | G3: =IFERROR(COUNTIFS('Dados B1'!$C$3:$C$56,$A3,'Dados B1'!$R$3:$R$56,">0")/COUNTIF('Dados B1'!$C$3:$C$56,$A3),"") | H3: {=IFERROR(MEDIAN(IF('Dados B1'!$C$3:$C$56=$A3,IF('Dados B1'!$U$3:$U$56<>"",'Dados B1'!$U$3:$U$56))),"")} | I3: =COUNTIFS('Dados B1'!$C$3:$C$56,$A3,'Dados B1'!$AH$3:$AH$56,"<>") | J3: {=IFERROR(MEDIAN(IF('Dados B1'!$C$3:$C$56=$A3,IF('Dados B1'!$AH$3:$AH$56<>"",'Dados B1'!$AH$3:$AH$56))),"")}
A4: Nordeste | B4: =COUNTIF('Dados B1'!$C$3:$C$56,$A4) | C4: {=IFERROR(MEDIAN(IF('Dados B1'!$C$3:$C$56=$A4,IF('Dados B1'!$D$3:$D$56<>"",'Dados B1'!$D$3:$D$56))),"")} | D4: =IFERROR(AVERAGEIFS('Dados B1'!$G$3:$G$56,'Dados B1'!$C$3:$C$56,$A4),"") | E4: =IFERROR(AVERAGEIFS('Dados B1'!$P$3:$P$56,'Dados B1'!$C$3:$C$56,$A4),"") | F4: =IFERROR(AVERAGEIFS('Dados B1'!$J$3:$J$56,'Dados B1'!$C$3:$C$56,$A4),"") | G4: =IFERROR(COUNTIFS('Dados B1'!$C$3:$C$56,$A4,'Dados B1'!$R$3:$R$56,">0")/COUNTIF('Dados B1'!$C$3:$C$56,$A4),"") | H4: {=IFERROR(MEDIAN(IF('Dados B1'!$C$3:$C$56=$A4,IF('Dados B1'!$U$3:$U$56<>"",'Dados B1'!$U$3:$U$56))),"")} | I4: =COUNTIFS('Dados B1'!$C$3:$C$56,$A4,'Dados B1'!$AH$3:$AH$56,"<>") | J4: {=IFERROR(MEDIAN(IF('Dados B1'!$C$3:$C$56=$A4,IF('Dados B1'!$AH$3:$AH$56<>"",'Dados B1'!$AH$3:$AH$56))),"")}
A5: Centro-Oeste | B5: =COUNTIF('Dados B1'!$C$3:$C$56,$A5) | C5: {=IFERROR(MEDIAN(IF('Dados B1'!$C$3:$C$56=$A5,IF('Dados B1'!$D$3:$D$56<>"",'Dados B1'!$D$3:$D$56))),"")} | D5: =IFERROR(AVERAGEIFS('Dados B1'!$G$3:$G$56,'Dados B1'!$C$3:$C$56,$A5),"") | E5: =IFERROR(AVERAGEIFS('Dados B1'!$P$3:$P$56,'Dados B1'!$C$3:$C$56,$A5),"") | F5: =IFERROR(AVERAGEIFS('Dados B1'!$J$3:$J$56,'Dados B1'!$C$3:$C$56,$A5),"") | G5: =IFERROR(COUNTIFS('Dados B1'!$C$3:$C$56,$A5,'Dados B1'!$R$3:$R$56,">0")/COUNTIF('Dados B1'!$C$3:$C$56,$A5),"") | H5: {=IFERROR(MEDIAN(IF('Dados B1'!$C$3:$C$56=$A5,IF('Dados B1'!$U$3:$U$56<>"",'Dados B1'!$U$3:$U$56))),"")} | I5: =COUNTIFS('Dados B1'!$C$3:$C$56,$A5,'Dados B1'!$AH$3:$AH$56,"<>") | J5: {=IFERROR(MEDIAN(IF('Dados B1'!$C$3:$C$56=$A5,IF('Dados B1'!$AH$3:$AH$56<>"",'Dados B1'!$AH$3:$AH$56))),"")}
A6: Sudeste | B6: =COUNTIF('Dados B1'!$C$3:$C$56,$A6) | C6: {=IFERROR(MEDIAN(IF('Dados B1'!$C$3:$C$56=$A6,IF('Dados B1'!$D$3:$D$56<>"",'Dados B1'!$D$3:$D$56))),"")} | D6: =IFERROR(AVERAGEIFS('Dados B1'!$G$3:$G$56,'Dados B1'!$C$3:$C$56,$A6),"") | E6: =IFERROR(AVERAGEIFS('Dados B1'!$P$3:$P$56,'Dados B1'!$C$3:$C$56,$A6),"") | F6: =IFERROR(AVERAGEIFS('Dados B1'!$J$3:$J$56,'Dados B1'!$C$3:$C$56,$A6),"") | G6: =IFERROR(COUNTIFS('Dados B1'!$C$3:$C$56,$A6,'Dados B1'!$R$3:$R$56,">0")/COUNTIF('Dados B1'!$C$3:$C$56,$A6),"") | H6: {=IFERROR(MEDIAN(IF('Dados B1'!$C$3:$C$56=$A6,IF('Dados B1'!$U$3:$U$56<>"",'Dados B1'!$U$3:$U$56))),"")} | I6: =COUNTIFS('Dados B1'!$C$3:$C$56,$A6,'Dados B1'!$AH$3:$AH$56,"<>") | J6: {=IFERROR(MEDIAN(IF('Dados B1'!$C$3:$C$56=$A6,IF('Dados B1'!$AH$3:$AH$56<>"",'Dados B1'!$AH$3:$AH$56))),"")}
A7: Sul | B7: =COUNTIF('Dados B1'!$C$3:$C$56,$A7) | C7: {=IFERROR(MEDIAN(IF('Dados B1'!$C$3:$C$56=$A7,IF('Dados B1'!$D$3:$D$56<>"",'Dados B1'!$D$3:$D$56))),"")} | D7: =IFERROR(AVERAGEIFS('Dados B1'!$G$3:$G$56,'Dados B1'!$C$3:$C$56,$A7),"") | E7: =IFERROR(AVERAGEIFS('Dados B1'!$P$3:$P$56,'Dados B1'!$C$3:$C$56,$A7),"") | F7: =IFERROR(AVERAGEIFS('Dados B1'!$J$3:$J$56,'Dados B1'!$C$3:$C$56,$A7),"") | G7: =IFERROR(COUNTIFS('Dados B1'!$C$3:$C$56,$A7,'Dados B1'!$R$3:$R$56,">0")/COUNTIF('Dados B1'!$C$3:$C$56,$A7),"") | H7: {=IFERROR(MEDIAN(IF('Dados B1'!$C$3:$C$56=$A7,IF('Dados B1'!$U$3:$U$56<>"",'Dados B1'!$U$3:$U$56))),"")} | I7: =COUNTIFS('Dados B1'!$C$3:$C$56,$A7,'Dados B1'!$AH$3:$AH$56,"<>") | J7: {=IFERROR(MEDIAN(IF('Dados B1'!$C$3:$C$56=$A7,IF('Dados B1'!$AH$3:$AH$56<>"",'Dados B1'!$AH$3:$AH$56))),"")}
A8: Total | B8: =SUM(B3:B7) | C8: =MEDIAN('Dados B1'!$D$3:$D$56) | D8: =AVERAGE('Dados B1'!$G$3:$G$56) | E8: =AVERAGE('Dados B1'!$P$3:$P$56) | F8: =AVERAGE('Dados B1'!$J$3:$J$56) | G8: =COUNTIF('Dados B1'!$R$3:$R$56,">0")/COUNTA('Dados B1'!$A$3:$A$56) | H8: =MEDIAN('Dados B1'!$U$3:$U$56) | I8: =COUNT('Dados B1'!$AH$3:$AH$56) | J8: =MEDIAN('Dados B1'!$AH$3:$AH$56)
A9: Fonte: B1, Google Places API (09/2026 e 15/10/2026), coletor de entorno do Google Maps (15/10/2026), Instagram (01/09 a 01/10/2026) e cardápios
A10: Nota: medianas calculadas só entre as casas com dado; cesta só nas casas com couvert, bebida e prato encontrados.

Sheet Tab 5
A1: Tabela 5 – Painel por metrópole: a cesta por pessoa varia de metrópole para metrópole
A2: Metrópole | B2: Região | C2: casas | D2: nota (mediana) | E2: horas abertas por semana (média) | F2: abre domingo (%) | G2: abre segunda (%) | H2: metrô até 1000 m (% das casas) | I2: seguidores (mediana) | J2: casas com cesta | K2: cesta mediana (mediana, R$)
A3: Belém | B3: Norte | C3: =COUNTIF('Dados B1'!$B$3:$B$56,$A3) | D3: {=IFERROR(MEDIAN(IF('Dados B1'!$B$3:$B$56=$A3,IF('Dados B1'!$D$3:$D$56<>"",'Dados B1'!$D$3:$D$56))),"")} | E3: =IFERROR(AVERAGEIFS('Dados B1'!$G$3:$G$56,'Dados B1'!$B$3:$B$56,$A3),"") | F3: =IFERROR(AVERAGEIFS('Dados B1'!$P$3:$P$56,'Dados B1'!$B$3:$B$56,$A3),"") | G3: =IFERROR(AVERAGEIFS('Dados B1'!$J$3:$J$56,'Dados B1'!$B$3:$B$56,$A3),"") | H3: =IFERROR(COUNTIFS('Dados B1'!$B$3:$B$56,$A3,'Dados B1'!$R$3:$R$56,">0")/COUNTIF('Dados B1'!$B$3:$B$56,$A3),"") | I3: {=IFERROR(MEDIAN(IF('Dados B1'!$B$3:$B$56=$A3,IF('Dados B1'!$U$3:$U$56<>"",'Dados B1'!$U$3:$U$56))),"")} | J3: =COUNTIFS('Dados B1'!$B$3:$B$56,$A3,'Dados B1'!$AH$3:$AH$56,"<>") | K3: {=IFERROR(MEDIAN(IF('Dados B1'!$B$3:$B$56=$A3,IF('Dados B1'!$AH$3:$AH$56<>"",'Dados B1'!$AH$3:$AH$56))),"")}
A4: Fortaleza | B4: Nordeste | C4: =COUNTIF('Dados B1'!$B$3:$B$56,$A4) | D4: {=IFERROR(MEDIAN(IF('Dados B1'!$B$3:$B$56=$A4,IF('Dados B1'!$D$3:$D$56<>"",'Dados B1'!$D$3:$D$56))),"")} | E4: =IFERROR(AVERAGEIFS('Dados B1'!$G$3:$G$56,'Dados B1'!$B$3:$B$56,$A4),"") | F4: =IFERROR(AVERAGEIFS('Dados B1'!$P$3:$P$56,'Dados B1'!$B$3:$B$56,$A4),"") | G4: =IFERROR(AVERAGEIFS('Dados B1'!$J$3:$J$56,'Dados B1'!$B$3:$B$56,$A4),"") | H4: =IFERROR(COUNTIFS('Dados B1'!$B$3:$B$56,$A4,'Dados B1'!$R$3:$R$56,">0")/COUNTIF('Dados B1'!$B$3:$B$56,$A4),"") | I4: {=IFERROR(MEDIAN(IF('Dados B1'!$B$3:$B$56=$A4,IF('Dados B1'!$U$3:$U$56<>"",'Dados B1'!$U$3:$U$56))),"")} | J4: =COUNTIFS('Dados B1'!$B$3:$B$56,$A4,'Dados B1'!$AH$3:$AH$56,"<>") | K4: {=IFERROR(MEDIAN(IF('Dados B1'!$B$3:$B$56=$A4,IF('Dados B1'!$AH$3:$AH$56<>"",'Dados B1'!$AH$3:$AH$56))),"")}
A5: Recife | B5: Nordeste | C5: =COUNTIF('Dados B1'!$B$3:$B$56,$A5) | D5: {=IFERROR(MEDIAN(IF('Dados B1'!$B$3:$B$56=$A5,IF('Dados B1'!$D$3:$D$56<>"",'Dados B1'!$D$3:$D$56))),"")} | E5: =IFERROR(AVERAGEIFS('Dados B1'!$G$3:$G$56,'Dados B1'!$B$3:$B$56,$A5),"") | F5: =IFERROR(AVERAGEIFS('Dados B1'!$P$3:$P$56,'Dados B1'!$B$3:$B$56,$A5),"") | G5: =IFERROR(AVERAGEIFS('Dados B1'!$J$3:$J$56,'Dados B1'!$B$3:$B$56,$A5),"") | H5: =IFERROR(COUNTIFS('Dados B1'!$B$3:$B$56,$A5,'Dados B1'!$R$3:$R$56,">0")/COUNTIF('Dados B1'!$B$3:$B$56,$A5),"") | I5: {=IFERROR(MEDIAN(IF('Dados B1'!$B$3:$B$56=$A5,IF('Dados B1'!$U$3:$U$56<>"",'Dados B1'!$U$3:$U$56))),"")} | J5: =COUNTIFS('Dados B1'!$B$3:$B$56,$A5,'Dados B1'!$AH$3:$AH$56,"<>") | K5: {=IFERROR(MEDIAN(IF('Dados B1'!$B$3:$B$56=$A5,IF('Dados B1'!$AH$3:$AH$56<>"",'Dados B1'!$AH$3:$AH$56))),"")}
A6: Salvador | B6: Nordeste | C6: =COUNTIF('Dados B1'!$B$3:$B$56,$A6) | D6: {=IFERROR(MEDIAN(IF('Dados B1'!$B$3:$B$56=$A6,IF('Dados B1'!$D$3:$D$56<>"",'Dados B1'!$D$3:$D$56))),"")} | E6: =IFERROR(AVERAGEIFS('Dados B1'!$G$3:$G$56,'Dados B1'!$B$3:$B$56,$A6),"") | F6: =IFERROR(AVERAGEIFS('Dados B1'!$P$3:$P$56,'Dados B1'!$B$3:$B$56,$A6),"") | G6: =IFERROR(AVERAGEIFS('Dados B1'!$J$3:$J$56,'Dados B1'!$B$3:$B$56,$A6),"") | H6: =IFERROR(COUNTIFS('Dados B1'!$B$3:$B$56,$A6,'Dados B1'!$R$3:$R$56,">0")/COUNTIF('Dados B1'!$B$3:$B$56,$A6),"") | I6: {=IFERROR(MEDIAN(IF('Dados B1'!$B$3:$B$56=$A6,IF('Dados B1'!$U$3:$U$56<>"",'Dados B1'!$U$3:$U$56))),"")} | J6: =COUNTIFS('Dados B1'!$B$3:$B$56,$A6,'Dados B1'!$AH$3:$AH$56,"<>") | K6: {=IFERROR(MEDIAN(IF('Dados B1'!$B$3:$B$56=$A6,IF('Dados B1'!$AH$3:$AH$56<>"",'Dados B1'!$AH$3:$AH$56))),"")}
A7: Brasília | B7: Centro-Oeste | C7: =COUNTIF('Dados B1'!$B$3:$B$56,$A7) | D7: {=IFERROR(MEDIAN(IF('Dados B1'!$B$3:$B$56=$A7,IF('Dados B1'!$D$3:$D$56<>"",'Dados B1'!$D$3:$D$56))),"")} | E7: =IFERROR(AVERAGEIFS('Dados B1'!$G$3:$G$56,'Dados B1'!$B$3:$B$56,$A7),"") | F7: =IFERROR(AVERAGEIFS('Dados B1'!$P$3:$P$56,'Dados B1'!$B$3:$B$56,$A7),"") | G7: =IFERROR(AVERAGEIFS('Dados B1'!$J$3:$J$56,'Dados B1'!$B$3:$B$56,$A7),"") | H7: =IFERROR(COUNTIFS('Dados B1'!$B$3:$B$56,$A7,'Dados B1'!$R$3:$R$56,">0")/COUNTIF('Dados B1'!$B$3:$B$56,$A7),"") | I7: {=IFERROR(MEDIAN(IF('Dados B1'!$B$3:$B$56=$A7,IF('Dados B1'!$U$3:$U$56<>"",'Dados B1'!$U$3:$U$56))),"")} | J7: =COUNTIFS('Dados B1'!$B$3:$B$56,$A7,'Dados B1'!$AH$3:$AH$56,"<>") | K7: {=IFERROR(MEDIAN(IF('Dados B1'!$B$3:$B$56=$A7,IF('Dados B1'!$AH$3:$AH$56<>"",'Dados B1'!$AH$3:$AH$56))),"")}
A8: Goiânia | B8: Centro-Oeste | C8: =COUNTIF('Dados B1'!$B$3:$B$56,$A8) | D8: {=IFERROR(MEDIAN(IF('Dados B1'!$B$3:$B$56=$A8,IF('Dados B1'!$D$3:$D$56<>"",'Dados B1'!$D$3:$D$56))),"")} | E8: =IFERROR(AVERAGEIFS('Dados B1'!$G$3:$G$56,'Dados B1'!$B$3:$B$56,$A8),"") | F8: =IFERROR(AVERAGEIFS('Dados B1'!$P$3:$P$56,'Dados B1'!$B$3:$B$56,$A8),"") | G8: =IFERROR(AVERAGEIFS('Dados B1'!$J$3:$J$56,'Dados B1'!$B$3:$B$56,$A8),"") | H8: =IFERROR(COUNTIFS('Dados B1'!$B$3:$B$56,$A8,'Dados B1'!$R$3:$R$56,">0")/COUNTIF('Dados B1'!$B$3:$B$56,$A8),"") | I8: {=IFERROR(MEDIAN(IF('Dados B1'!$B$3:$B$56=$A8,IF('Dados B1'!$U$3:$U$56<>"",'Dados B1'!$U$3:$U$56))),"")} | J8: =COUNTIFS('Dados B1'!$B$3:$B$56,$A8,'Dados B1'!$AH$3:$AH$56,"<>") | K8: {=IFERROR(MEDIAN(IF('Dados B1'!$B$3:$B$56=$A8,IF('Dados B1'!$AH$3:$AH$56<>"",'Dados B1'!$AH$3:$AH$56))),"")}
A9: Belo Horizonte | B9: Sudeste | C9: =COUNTIF('Dados B1'!$B$3:$B$56,$A9) | D9: {=IFERROR(MEDIAN(IF('Dados B1'!$B$3:$B$56=$A9,IF('Dados B1'!$D$3:$D$56<>"",'Dados B1'!$D$3:$D$56))),"")} | E9: =IFERROR(AVERAGEIFS('Dados B1'!$G$3:$G$56,'Dados B1'!$B$3:$B$56,$A9),"") | F9: =IFERROR(AVERAGEIFS('Dados B1'!$P$3:$P$56,'Dados B1'!$B$3:$B$56,$A9),"") | G9: =IFERROR(AVERAGEIFS('Dados B1'!$J$3:$J$56,'Dados B1'!$B$3:$B$56,$A9),"") | H9: =IFERROR(COUNTIFS('Dados B1'!$B$3:$B$56,$A9,'Dados B1'!$R$3:$R$56,">0")/COUNTIF('Dados B1'!$B$3:$B$56,$A9),"") | I9: {=IFERROR(MEDIAN(IF('Dados B1'!$B$3:$B$56=$A9,IF('Dados B1'!$U$3:$U$56<>"",'Dados B1'!$U$3:$U$56))),"")} | J9: =COUNTIFS('Dados B1'!$B$3:$B$56,$A9,'Dados B1'!$AH$3:$AH$56,"<>") | K9: {=IFERROR(MEDIAN(IF('Dados B1'!$B$3:$B$56=$A9,IF('Dados B1'!$AH$3:$AH$56<>"",'Dados B1'!$AH$3:$AH$56))),"")}
A10: Rio de Janeiro | B10: Sudeste | C10: =COUNTIF('Dados B1'!$B$3:$B$56,$A10) | D10: {=IFERROR(MEDIAN(IF('Dados B1'!$B$3:$B$56=$A10,IF('Dados B1'!$D$3:$D$56<>"",'Dados B1'!$D$3:$D$56))),"")} | E10: =IFERROR(AVERAGEIFS('Dados B1'!$G$3:$G$56,'Dados B1'!$B$3:$B$56,$A10),"") | F10: =IFERROR(AVERAGEIFS('Dados B1'!$P$3:$P$56,'Dados B1'!$B$3:$B$56,$A10),"") | G10: =IFERROR(AVERAGEIFS('Dados B1'!$J$3:$J$56,'Dados B1'!$B$3:$B$56,$A10),"") | H10: =IFERROR(COUNTIFS('Dados B1'!$B$3:$B$56,$A10,'Dados B1'!$R$3:$R$56,">0")/COUNTIF('Dados B1'!$B$3:$B$56,$A10),"") | I10: {=IFERROR(MEDIAN(IF('Dados B1'!$B$3:$B$56=$A10,IF('Dados B1'!$U$3:$U$56<>"",'Dados B1'!$U$3:$U$56))),"")} | J10: =COUNTIFS('Dados B1'!$B$3:$B$56,$A10,'Dados B1'!$AH$3:$AH$56,"<>") | K10: {=IFERROR(MEDIAN(IF('Dados B1'!$B$3:$B$56=$A10,IF('Dados B1'!$AH$3:$AH$56<>"",'Dados B1'!$AH$3:$AH$56))),"")}
A11: São Paulo | B11: Sudeste | C11: =COUNTIF('Dados B1'!$B$3:$B$56,$A11) | D11: {=IFERROR(MEDIAN(IF('Dados B1'!$B$3:$B$56=$A11,IF('Dados B1'!$D$3:$D$56<>"",'Dados B1'!$D$3:$D$56))),"")} | E11: =IFERROR(AVERAGEIFS('Dados B1'!$G$3:$G$56,'Dados B1'!$B$3:$B$56,$A11),"") | F11: =IFERROR(AVERAGEIFS('Dados B1'!$P$3:$P$56,'Dados B1'!$B$3:$B$56,$A11),"") | G11: =IFERROR(AVERAGEIFS('Dados B1'!$J$3:$J$56,'Dados B1'!$B$3:$B$56,$A11),"") | H11: =IFERROR(COUNTIFS('Dados B1'!$B$3:$B$56,$A11,'Dados B1'!$R$3:$R$56,">0")/COUNTIF('Dados B1'!$B$3:$B$56,$A11),"") | I11: {=IFERROR(MEDIAN(IF('Dados B1'!$B$3:$B$56=$A11,IF('Dados B1'!$U$3:$U$56<>"",'Dados B1'!$U$3:$U$56))),"")} | J11: =COUNTIFS('Dados B1'!$B$3:$B$56,$A11,'Dados B1'!$AH$3:$AH$56,"<>") | K11: {=IFERROR(MEDIAN(IF('Dados B1'!$B$3:$B$56=$A11,IF('Dados B1'!$AH$3:$AH$56<>"",'Dados B1'!$AH$3:$AH$56))),"")}
A12: Vitória | B12: Sudeste | C12: =COUNTIF('Dados B1'!$B$3:$B$56,$A12) | D12: {=IFERROR(MEDIAN(IF('Dados B1'!$B$3:$B$56=$A12,IF('Dados B1'!$D$3:$D$56<>"",'Dados B1'!$D$3:$D$56))),"")} | E12: =IFERROR(AVERAGEIFS('Dados B1'!$G$3:$G$56,'Dados B1'!$B$3:$B$56,$A12),"") | F12: =IFERROR(AVERAGEIFS('Dados B1'!$P$3:$P$56,'Dados B1'!$B$3:$B$56,$A12),"") | G12: =IFERROR(AVERAGEIFS('Dados B1'!$J$3:$J$56,'Dados B1'!$B$3:$B$56,$A12),"") | H12: =IFERROR(COUNTIFS('Dados B1'!$B$3:$B$56,$A12,'Dados B1'!$R$3:$R$56,">0")/COUNTIF('Dados B1'!$B$3:$B$56,$A12),"") | I12: {=IFERROR(MEDIAN(IF('Dados B1'!$B$3:$B$56=$A12,IF('Dados B1'!$U$3:$U$56<>"",'Dados B1'!$U$3:$U$56))),"")} | J12: =COUNTIFS('Dados B1'!$B$3:$B$56,$A12,'Dados B1'!$AH$3:$AH$56,"<>") | K12: {=IFERROR(MEDIAN(IF('Dados B1'!$B$3:$B$56=$A12,IF('Dados B1'!$AH$3:$AH$56<>"",'Dados B1'!$AH$3:$AH$56))),"")}
A13: Curitiba | B13: Sul | C13: =COUNTIF('Dados B1'!$B$3:$B$56,$A13) | D13: {=IFERROR(MEDIAN(IF('Dados B1'!$B$3:$B$56=$A13,IF('Dados B1'!$D$3:$D$56<>"",'Dados B1'!$D$3:$D$56))),"")} | E13: =IFERROR(AVERAGEIFS('Dados B1'!$G$3:$G$56,'Dados B1'!$B$3:$B$56,$A13),"") | F13: =IFERROR(AVERAGEIFS('Dados B1'!$P$3:$P$56,'Dados B1'!$B$3:$B$56,$A13),"") | G13: =IFERROR(AVERAGEIFS('Dados B1'!$J$3:$J$56,'Dados B1'!$B$3:$B$56,$A13),"") | H13: =IFERROR(COUNTIFS('Dados B1'!$B$3:$B$56,$A13,'Dados B1'!$R$3:$R$56,">0")/COUNTIF('Dados B1'!$B$3:$B$56,$A13),"") | I13: {=IFERROR(MEDIAN(IF('Dados B1'!$B$3:$B$56=$A13,IF('Dados B1'!$U$3:$U$56<>"",'Dados B1'!$U$3:$U$56))),"")} | J13: =COUNTIFS('Dados B1'!$B$3:$B$56,$A13,'Dados B1'!$AH$3:$AH$56,"<>") | K13: {=IFERROR(MEDIAN(IF('Dados B1'!$B$3:$B$56=$A13,IF('Dados B1'!$AH$3:$AH$56<>"",'Dados B1'!$AH$3:$AH$56))),"")}
A14: Florianópolis | B14: Sul | C14: =COUNTIF('Dados B1'!$B$3:$B$56,$A14) | D14: {=IFERROR(MEDIAN(IF('Dados B1'!$B$3:$B$56=$A14,IF('Dados B1'!$D$3:$D$56<>"",'Dados B1'!$D$3:$D$56))),"")} | E14: =IFERROR(AVERAGEIFS('Dados B1'!$G$3:$G$56,'Dados B1'!$B$3:$B$56,$A14),"") | F14: =IFERROR(AVERAGEIFS('Dados B1'!$P$3:$P$56,'Dados B1'!$B$3:$B$56,$A14),"") | G14: =IFERROR(AVERAGEIFS('Dados B1'!$J$3:$J$56,'Dados B1'!$B$3:$B$56,$A14),"") | H14: =IFERROR(COUNTIFS('Dados B1'!$B$3:$B$56,$A14,'Dados B1'!$R$3:$R$56,">0")/COUNTIF('Dados B1'!$B$3:$B$56,$A14),"") | I14: {=IFERROR(MEDIAN(IF('Dados B1'!$B$3:$B$56=$A14,IF('Dados B1'!$U$3:$U$56<>"",'Dados B1'!$U$3:$U$56))),"")} | J14: =COUNTIFS('Dados B1'!$B$3:$B$56,$A14,'Dados B1'!$AH$3:$AH$56,"<>") | K14: {=IFERROR(MEDIAN(IF('Dados B1'!$B$3:$B$56=$A14,IF('Dados B1'!$AH$3:$AH$56<>"",'Dados B1'!$AH$3:$AH$56))),"")}
A15: Porto Alegre | B15: Sul | C15: =COUNTIF('Dados B1'!$B$3:$B$56,$A15) | D15: {=IFERROR(MEDIAN(IF('Dados B1'!$B$3:$B$56=$A15,IF('Dados B1'!$D$3:$D$56<>"",'Dados B1'!$D$3:$D$56))),"")} | E15: =IFERROR(AVERAGEIFS('Dados B1'!$G$3:$G$56,'Dados B1'!$B$3:$B$56,$A15),"") | F15: =IFERROR(AVERAGEIFS('Dados B1'!$P$3:$P$56,'Dados B1'!$B$3:$B$56,$A15),"") | G15: =IFERROR(AVERAGEIFS('Dados B1'!$J$3:$J$56,'Dados B1'!$B$3:$B$56,$A15),"") | H15: =IFERROR(COUNTIFS('Dados B1'!$B$3:$B$56,$A15,'Dados B1'!$R$3:$R$56,">0")/COUNTIF('Dados B1'!$B$3:$B$56,$A15),"") | I15: {=IFERROR(MEDIAN(IF('Dados B1'!$B$3:$B$56=$A15,IF('Dados B1'!$U$3:$U$56<>"",'Dados B1'!$U$3:$U$56))),"")} | J15: =COUNTIFS('Dados B1'!$B$3:$B$56,$A15,'Dados B1'!$AH$3:$AH$56,"<>") | K15: {=IFERROR(MEDIAN(IF('Dados B1'!$B$3:$B$56=$A15,IF('Dados B1'!$AH$3:$AH$56<>"",'Dados B1'!$AH$3:$AH$56))),"")}
A16: Total | C16: =SUM(C3:C15) | D16: =MEDIAN('Dados B1'!$D$3:$D$56) | E16: =AVERAGE('Dados B1'!$G$3:$G$56) | F16: =AVERAGE('Dados B1'!$P$3:$P$56) | G16: =AVERAGE('Dados B1'!$J$3:$J$56) | H16: =COUNTIF('Dados B1'!$R$3:$R$56,">0")/COUNTA('Dados B1'!$A$3:$A$56) | I16: =MEDIAN('Dados B1'!$U$3:$U$56) | J16: =COUNT('Dados B1'!$AH$3:$AH$56) | K16: =MEDIAN('Dados B1'!$AH$3:$AH$56)
A17: Fonte: B1, Google Places API (09/2026 e 15/10/2026), coletor de entorno do Google Maps (15/10/2026), Instagram (01/09 a 01/10/2026) e cardápios
A18: Nota: o gráfico mostra a mediana da cesta mediana das casas com cesta em cada metrópole; metrópoles sem cesta ficam fora.

Sheet Tab 6
A1: Tabela 6 – Entorno pelo Google Maps: a maioria das casas tem shopping a até 1 km; metrô perto é minoria
A2: Distância (linha reta) | B2: Metrô: casas | C2: Metrô: % | D2: Shopping: casas | E2: Shopping: %
A3: Até 500 m | B3: =COUNTIFS('Dados B1'!$S$3:$S$56,"<=500") | C3: =B3/B$9 | D3: =COUNTIFS('Dados B1'!$T$3:$T$56,"<=500") | E3: =D3/D$9
A4: De 501 a 1000 m | B4: =COUNTIFS('Dados B1'!$S$3:$S$56,">500",'Dados B1'!$S$3:$S$56,"<=1000") | C4: =B4/B$9 | D4: =COUNTIFS('Dados B1'!$T$3:$T$56,">500",'Dados B1'!$T$3:$T$56,"<=1000") | E4: =D4/D$9
A5: De 1001 a 2000 m | B5: =COUNTIFS('Dados B1'!$S$3:$S$56,">1000",'Dados B1'!$S$3:$S$56,"<=2000") | C5: =B5/B$9 | D5: =COUNTIFS('Dados B1'!$T$3:$T$56,">1000",'Dados B1'!$T$3:$T$56,"<=2000") | E5: =D5/D$9
A6: Mais de 2000 m | B6: =COUNTIFS('Dados B1'!$S$3:$S$56,">2000") | C6: =B6/B$9 | D6: =COUNTIFS('Dados B1'!$T$3:$T$56,">2000") | E6: =D6/D$9
A7: Sem leitura (cidade sem metrô ou leitura a mais de 50 km) | B7: =COUNTA('Dados B1'!$A$3:$A$56)-COUNT('Dados B1'!$S$3:$S$56) | C7: =B7/B$9 | D7: =COUNTA('Dados B1'!$A$3:$A$56)-COUNT('Dados B1'!$T$3:$T$56) | E7: =D7/D$9
A8: Conferência (total − casas; deve ser 0) | B8: =B9-COUNTA('Dados B1'!$A$3:$A$56) | D8: =D9-COUNTA('Dados B1'!$A$3:$A$56)
A9: Total | B9: =SUM(B3:B7) | C9: =SUM(C3:C7) | D9: =SUM(D3:D7) | E9: =SUM(E3:E7)
A10: Fonte: B1, coletor de entorno do Google Maps (15/10/2026)
A11: Nota: sem dados do OpenStreetMap (porte do shopping fora). Shopping de qualquer porte lido pelo Maps.

Sheet Tab 7
A1: Tabela 7 – Preços nos cardápios: a cesta mediana por pessoa fica em R$ 54 (metade das casas entre R$ 38,50 e R$ 70)
A2: Categoria | B2: Casas com preço | C2: 1º quartil (R$) | D2: Mediana (R$) | E2: 3º quartil (R$)
A3: Couvert ou taxa de jogo (casas que cobram) | B3: =COUNT('Dados B1'!$AD$3:$AD$56) | C3: =IFERROR(PERCENTILE('Dados B1'!$AD$3:$AD$56,0.25),"") | D3: =IFERROR(MEDIAN('Dados B1'!$AD$3:$AD$56),"") | E3: =IFERROR(PERCENTILE('Dados B1'!$AD$3:$AD$56,0.75),"")
A4: Bebida | B4: =COUNT('Dados B1'!$AE$3:$AE$56) | C4: =IFERROR(PERCENTILE('Dados B1'!$AE$3:$AE$56,0.25),"") | D4: =IFERROR(MEDIAN('Dados B1'!$AE$3:$AE$56),"") | E4: =IFERROR(PERCENTILE('Dados B1'!$AE$3:$AE$56,0.75),"")
A5: Entrada ou prato | B5: =COUNT('Dados B1'!$AF$3:$AF$56) | C5: =IFERROR(PERCENTILE('Dados B1'!$AF$3:$AF$56,0.25),"") | D5: =IFERROR(MEDIAN('Dados B1'!$AF$3:$AF$56),"") | E5: =IFERROR(PERCENTILE('Dados B1'!$AF$3:$AF$56,0.75),"")
A6: Hambúrguer | B6: =COUNT('Dados B1'!$AJ$3:$AJ$56) | C6: =IFERROR(PERCENTILE('Dados B1'!$AJ$3:$AJ$56,0.25),"") | D6: =IFERROR(MEDIAN('Dados B1'!$AJ$3:$AJ$56),"") | E6: =IFERROR(PERCENTILE('Dados B1'!$AJ$3:$AJ$56,0.75),"")
A7: Batata | B7: =COUNT('Dados B1'!$AK$3:$AK$56) | C7: =IFERROR(PERCENTILE('Dados B1'!$AK$3:$AK$56,0.25),"") | D7: =IFERROR(MEDIAN('Dados B1'!$AK$3:$AK$56),"") | E7: =IFERROR(PERCENTILE('Dados B1'!$AK$3:$AK$56,0.75),"")
A8: Cerveja | B8: =COUNT('Dados B1'!$AL$3:$AL$56) | C8: =IFERROR(PERCENTILE('Dados B1'!$AL$3:$AL$56,0.25),"") | D8: =IFERROR(MEDIAN('Dados B1'!$AL$3:$AL$56),"") | E8: =IFERROR(PERCENTILE('Dados B1'!$AL$3:$AL$56,0.75),"")
A9: Refrigerante | B9: =COUNT('Dados B1'!$AM$3:$AM$56) | C9: =IFERROR(PERCENTILE('Dados B1'!$AM$3:$AM$56,0.25),"") | D9: =IFERROR(MEDIAN('Dados B1'!$AM$3:$AM$56),"") | E9: =IFERROR(PERCENTILE('Dados B1'!$AM$3:$AM$56,0.75),"")
A10: Drinks | B10: =COUNT('Dados B1'!$AN$3:$AN$56) | C10: =IFERROR(PERCENTILE('Dados B1'!$AN$3:$AN$56,0.25),"") | D10: =IFERROR(MEDIAN('Dados B1'!$AN$3:$AN$56),"") | E10: =IFERROR(PERCENTILE('Dados B1'!$AN$3:$AN$56,0.75),"")
A11: Cesta por pessoa, nível baixo | B11: =COUNT('Dados B1'!$AG$3:$AG$56) | C11: =IFERROR(PERCENTILE('Dados B1'!$AG$3:$AG$56,0.25),"") | D11: =IFERROR(MEDIAN('Dados B1'!$AG$3:$AG$56),"") | E11: =IFERROR(PERCENTILE('Dados B1'!$AG$3:$AG$56,0.75),"")
A12: Cesta por pessoa, nível mediano | B12: =COUNT('Dados B1'!$AH$3:$AH$56) | C12: =IFERROR(PERCENTILE('Dados B1'!$AH$3:$AH$56,0.25),"") | D12: =IFERROR(MEDIAN('Dados B1'!$AH$3:$AH$56),"") | E12: =IFERROR(PERCENTILE('Dados B1'!$AH$3:$AH$56,0.75),"")
A13: Cesta por pessoa, nível alto | B13: =COUNT('Dados B1'!$AI$3:$AI$56) | C13: =IFERROR(PERCENTILE('Dados B1'!$AI$3:$AI$56,0.25),"") | D13: =IFERROR(MEDIAN('Dados B1'!$AI$3:$AI$56),"") | E13: =IFERROR(PERCENTILE('Dados B1'!$AI$3:$AI$56,0.75),"")
A14: Fonte: B1, cardápios transcritos (B1_cardapios_itens_precos.xlsx)
A15: Nota: cada casa entra com a mediana do próprio cardápio na categoria; quartis entre as casas.
A16: Cesta = couvert + bebida + entrada ou prato, só nas casas em que os três foram encontrados.

Sheet Tab 8
A1: Tabela 8 – Couvert: encontrado no cardápio de 8 das 36 casas com cardápio
A2: Situação | B2: Casas | C2: % do total
A3: Couvert ou taxa de jogo encontrado no cardápio | B3: =COUNTIFS('Dados B1'!$AB$3:$AB$56,1,'Dados B1'!$AC$3:$AC$56,1) | C3: =B3/B$6
A4: Couvert não encontrado no cardápio | B4: =COUNTIF('Dados B1'!$AB$3:$AB$56,1)-B3 | C4: =B4/B$6
A5: Sem cardápio transcrito | B5: =COUNTA('Dados B1'!$A$3:$A$56)-COUNTIF('Dados B1'!$AB$3:$AB$56,1) | C5: =B5/B$6
A6: Total | B6: =SUM(B3:B5) | C6: =SUM(C3:C5)
A7: Conferência (total − casas; deve ser 0) | B7: =B6-COUNTA('Dados B1'!$A$3:$A$56)
A8: Fonte: B1, cardápios transcritos (B1_cardapios_itens_precos.xlsx)
A9: Nota: "não encontrado" não quer dizer que a casa não cobra; o couvert pode estar fora do cardápio coletado.

Sheet Tab 9
A1: Tabela 9 – Modelos de cobrança citados no Instagram: couvert lúdico e inscrição em evento são os mais comuns
A2: Modelo | B2: Posts que citam | C2: Estabelecimentos que citam | D2: Casas de jogos que citam | E2: Casas de jogos (total) | F2: Casas de jogos (%) | G2: Lojas que citam | H2: Lojas (total) | I2: Lojas (%)
A3: couvert lúdico ou taxa de entrada | B3: 816 | C3: 34 | D3: 21 | E3: 23 | F3: =D3/E3 | G3: 13 | H3: 24 | I3: =G3/H3
A4: entrada gratuita | B4: 582 | C4: 31 | D4: 19 | E4: 23 | F4: =D4/E4 | G4: 12 | H4: 24 | I4: =G4/H4
A5: cobrança por hora | B5: 55 | C5: 19 | D5: 11 | E5: 23 | F5: =D5/E5 | G5: 8 | H5: 24 | I5: =G5/H5
A6: cobrança por turno ou período | B6: 114 | C6: 25 | D6: 16 | E6: 23 | F6: =D6/E6 | G6: 9 | H6: 24 | I6: =G6/H6
A7: dia livre (sem limite de tempo) | B7: 579 | C7: 30 | D7: 18 | E7: 23 | F7: =D7/E7 | G7: 12 | H7: 24 | I7: =G7/H7
A8: passaporte ou pacote de visitas | B8: 142 | C8: 28 | D8: 18 | E8: 23 | F8: =D8/E8 | G8: 10 | H8: 24 | I8: =G8/H8
A9: assinatura ou plano mensal | B9: 214 | C9: 15 | D9: 9 | E9: 23 | F9: =D9/E9 | G9: 6 | H9: 24 | I9: =G9/H9
A10: consumação mínima ou isenção por consumo | B10: 140 | C10: 17 | D10: 5 | E10: 23 | F10: =D10/E10 | G10: 12 | H10: 24 | I10: =G10/H10
A11: preço diferente por dia da semana | B11: 46 | C11: 11 | D11: 9 | E11: 23 | F11: =D11/E11 | G11: 2 | H11: 24 | I11: =G11/H11
A12: rodízio ou buffet com jogos | B12: 189 | C12: 12 | D12: 8 | E12: 23 | F12: =D12/E12 | G12: 4 | H12: 24 | I12: =G12/H12
A13: aluguel de jogos | B13: 138 | C13: 21 | D13: 13 | E13: 23 | F13: =D13/E13 | G13: 8 | H13: 24 | I13: =G13/H13
A14: inscrição em evento ou torneio | B14: 3549 | C14: 45 | D14: 21 | E14: 23 | F14: =D14/E14 | G14: 24 | H14: 24 | I14: =G14/H14
A15: Fonte: B1, legendas do Instagram das casas (coletor do Instagram, 2026), análise de legendas
A16: Nota: contagem não exclusiva (um post pode citar vários modelos).

Sheet Tab 10
A1: Tabela 10 – Eventos no Instagram: encontros/RPG, competições e noites temáticas puxam a agenda
A2: Categoria | B2: Posts | C2: Estabelecimentos | D2: Casas de jogos com o evento | E2: Casas de jogos (total) | F2: Casas de jogos: posts por casa por mês | G2: Lojas com o evento | H2: Lojas (total) | I2: Lojas: posts por casa por mês
A3: todos os eventos prováveis | B3: 2237 | C3: 45 | D3: 22 | E3: 22 | F3: 3.23 | G3: 23 | H3: 23 | I3: 5.01
A4: noite temática | B4: 456 | C4: 41 | D4: 22 | E4: 22 | F4: 1.22 | G4: 19 | H4: 23 | I4: 0.49
A5: workshop/aula | B5: 105 | C5: 27 | D5: 13 | E5: 22 | F5: 0.21 | G5: 14 | H5: 23 | I5: 0.18
A6: competição | B6: 1231 | C6: 44 | D6: 21 | E6: 22 | F6: 1.22 | G6: 23 | H6: 23 | I6: 3.29
A7: quiz/bingo | B7: 125 | C7: 13 | D7: 11 | E7: 22 | F7: 0.45 | G7: 2 | H7: 23 | I7: 0.03
A8: encontro/RPG | B8: 1190 | C8: 41 | D8: 21 | E8: 22 | F8: 1.63 | G8: 20 | H8: 23 | I8: 2.75
A9: sorteio (não é evento; referência) | B9: 329 | C9: 35 | D9: 14 | E9: 22 | F9: 0.41 | G9: 21 | H9: 23 | I9: 0.8
A10: Fonte: B1, legendas do Instagram das casas (coletor do Instagram, 2026), análise de legendas
A11: Nota: categorias não exclusivas; o gráfico mostra posts por casa por mês, sem "todos os eventos" e sem sorteio (que não é evento).

Sheet Tab 11
A1: Tabela 11 – Dia citado nos eventos: casas de jogos anunciam mais domingo e quinta; lojas, sábado
A2: Dia | B2: Casas de jogos: eventos que citam | C2: Casas de jogos: % dos eventos | D2: Casas de jogos: estabelecimentos | E2: Lojas: eventos que citam | F2: Lojas: % dos eventos | G2: Lojas: estabelecimentos
A3: segunda | B3: 37 | C3: 0.043 | D3: 15 | E3: 37 | F3: 0.027 | G3: 10
A4: terça | B4: 59 | C4: 0.069 | D4: 14 | E4: 146 | F4: 0.105 | G4: 14
A5: quarta | B5: 103 | C5: 0.121 | D5: 17 | E5: 181 | F5: 0.131 | G5: 15
A6: quinta | B6: 121 | C6: 0.142 | D6: 18 | E6: 67 | F6: 0.048 | G6: 13
A7: sexta | B7: 86 | C7: 0.101 | D7: 17 | E7: 207 | F7: 0.15 | G7: 17
A8: sábado | B8: 79 | C8: 0.093 | D8: 17 | E8: 329 | F8: 0.238 | G8: 18
A9: domingo | B9: 145 | C9: 0.17 | D9: 20 | E9: 136 | F9: 0.098 | G9: 15
A10: Fonte: B1, legendas do Instagram das casas (coletor do Instagram, 2026), análise de legendas
A11: Nota: % sobre os eventos prováveis de cada tipo de casa; um evento pode citar mais de um dia ou nenhum.

Sheet Tab 12
A1: Tabela 12 – Temas das legendas do Instagram: programação, varejo e preço dominam
A2: Código | B2: Tema | C2: Posts com o tema | D2: % dos posts | E2: % ponderado por estabelecimento | F2: Estabelecimentos com o tema
A3: ACV | B3: Acervo de jogos | C3: 830 | D3: 0.07 | E3: 0.084 | F3: 40
A4: MED | B4: Mediação lúdica (monitoria) | C4: 378 | D4: 0.032 | E4: 0.048 | F4: 31
A5: ATD | B5: Atendimento e hospitalidade | C5: 483 | D5: 0.04 | E5: 0.063 | F5: 40
A6: AB | B6: Alimentos e bebidas | C6: 2510 | D6: 0.21 | E6: 0.223 | F6: 42
A7: PRC | B7: Preço e valor percebido | C7: 3224 | D7: 0.27 | E7: 0.284 | F7: 45
A8: AMB | B8: Ambiente físico e conforto | C8: 415 | D8: 0.035 | E8: 0.038 | F8: 41
A9: CAP | B9: Capacidade, reserva e fila | C9: 1366 | D9: 0.114 | E9: 0.152 | F9: 45
A10: PRG | B10: Programação e atrações | C10: 6303 | D10: 0.528 | E10: 0.534 | F10: 45
A11: COMU | B11: Comunidade de jogadores | C11: 431 | D11: 0.036 | E11: 0.042 | F11: 38
A12: VAR | B12: Varejo e pós-venda | C12: 3789 | D12: 0.317 | E12: 0.355 | F12: 45
A13: LOC | B13: Localização e acesso | C13: 1305 | D13: 0.109 | E13: 0.156 | F13: 38
A14: INC | B14: Segurança, inclusão e respeito | C14: 219 | D14: 0.018 | E14: 0.024 | F14: 33
... A24: SOR | B24: Sorteio ou concurso (só legendas) | C24: 735 | D24: 0.062 | E24: 0.063 | F24: 42
A25: Fonte: B1, legendas do Instagram das casas (coletor do Instagram, 2026), análise de legendas
A26: Nota: temas não exclusivos; o % ponderado dá peso igual a cada estabelecimento. Comparação com o B2 retirada desta planilha.

Sheet Tab 13
A1: Tabela 13 – Os 20 jogos mais presentes nos acervos publicados (30 acervos): Catan, Saboteur e Potion Explosion lideram
A2: Jogo | B2: Casas com o jogo | C2: Jogadores (mín.) | D2: Jogadores (máx.) | E2: Duração (min) | F2: Preço provável (R$) | G2: Aluguel (mediana, R$)
A3: Catan: O Jogo | B3: 28 | C3: 3 | D3: 4 | E3: 90 | F3: 349.88 | G3: 40
A4: Saboteur | B4: 27 | C4: 3 | D4: 10 | E4: 30 | F4: 105 | G4: 17.5
A5: Potion Explosion | B5: 26 | C5: 2 | D5: 4 | E5: 45 | F5: 389.94 | G5: 35
A6: 7 Wonders | B6: 25 | C6: 2 | D6: 7 | E6: 30 | F6: 304.9 | G6: 40
A7: Bandido | B7: 25 | C7: 1 | D7: 4 | E7: 15 | F7: 64.9 | G7: 15
A8: Concept | B8: 25 | C8: 4 | D8: 12 | E8: 40 | F8: 299.95 | G8: 30
A9: 7 Wonders Duel | B9: 24 | C9: 2 | D9: 2 | E9: 30 | F9: 249.9 | G9: 30
A10: Azul | B10: 24 | C10: 2 | D10: 4 | E10: 45 | F10: 344.45 | G10: 37.5
A11: Taco Gato Cabra Queijo Pizza | B11: 24 | C11: 2 | D11: 8 | E11: 10 | F11: 62.5 | G11: 15
A12: The Mind | B12: 24 | C12: 2 | D12: 4 | E12: 15 | F12: 79.95 | G12: 15
A13: The Resistance | B13: 24 | C13: 5 | D13: 10 | E13: 30 | F13: 159.9 | G13: 25
A14: Ticket to Ride | B14: 24 | C14: 2 | D14: 5 | E14: 45 | F14: 405 | G14: 35
... A22: Love Letter | B22: 22 | C22: 2 | D22: 4 | E22: 20 | F22: 89.89 | G22: 20
A23: Fonte: B1, acervos publicados (acervodejogos, Ludopedia, Rejoy e listas das casas) e preços de lojas (B1_cesta_jogos.xlsx)
A24: Nota: preço vazio = jogo sem preço nas lojas consultadas.

Sheet Tab 14
A1: Tabela 14 – Custo do acervo inicial: de R$ 40 mil (acervo pequeno) a R$ 119 mil (acervo grande)
A2: Tamanho do acervo | B2: Títulos | C2: Núcleo com preço | D2: Títulos restantes | E2: Custo otimista (R$) | F2: Custo provável (R$) | G2: Custo pessimista (R$)
A3: Pequeno (1º quartil dos acervos) | B3: 222 | C3: 77 | D3: =B3-C3 | E3: 40131.59 | F3: 42928.78 | G3: 44732.45
A4: Mediano (mediana dos acervos) | B4: 322 | C4: 77 | D4: =B4-C4 | E4: 57273.26 | F4: 60884.32 | G4: 63281.49
A5: Grande (3º quartil dos acervos) | B5: 622 | C5: 77 | D5: =B5-C5 | E5: 108698.28 | F5: 114750.94 | G5: 118928.59
A6: Fonte: B1, acervos publicados e preços de lojas (B1_cesta_jogos.xlsx, aba acervo_inicial)
A7: Nota: títulos restantes (fora do núcleo com preço) pelo preço médio do núcleo.

Sheet Tab 15
A1: Tabela 15 – Contagem direta na São Jogue: grupos ficam de 1h20 a 2h na mesa
A2: Medida | B2: 10/10 Bela Vista | C2: 16/10 Bela Vista | D2: 17/10 Paralela
A3: Horas observadas | B3: 3.32 | C3: 2.48 | D3: 2.47
A4: Grupos que entraram (porta) | B4: 14 | C4: 4 | D4: 3
A5: Pessoas que entraram | B5: 38 | C5: 10 | D5: 13
A6: Pessoas por hora | B6: =IFERROR(B5/B3,"") | C6: =IFERROR(C5/C3,"") | D6: =IFERROR(D5/D3,"")
A7: Pessoas por grupo (porta) | B7: =IFERROR(B5/B4,"") | C7: =IFERROR(C5/C4,"") | D7: =IFERROR(D5/D4,"")
A8: Permanência média pela porta (min) | B8: 99.4 | C8: 61.8 | D8: 53.3
A9: Grupos acompanhados na mesa | B9: 9 | C9: 7 | D9: 4
A10: Pessoas nas mesas | B10: 41 | C10: 17 | D10: 12
A11: Pessoas por grupo (mesa) | B11: =IFERROR(B10/B9,"") | C11: =IFERROR(C10/C9,"") | D11: =IFERROR(D10/D9,"")
A12: Permanência média na mesa (min) | B12: 116.2 | C12: 82.9 | D12: 99.5
A13: Permanência mediana na mesa (min) | B13: 121 | C13: 95 | D13: 91.5
A14: Fonte: B3, contagem direta nas unidades da São Jogue (app de observação, 10/10, 16/10 e 17/10/2026)
A15: Nota: visitas de cerca de 3 h, do lado de fora; 10/10 só com o POV1.

Sheet Tab 16
A1: Tabela 16 – População e renda das capitais do B1: Salvador e Belém têm a menor renda do trabalho do grupo
A2: Capital | B2: UF | C2: População 2022 | D2: População estimada 2026 | E2: População de 20 a 39 anos (2022) | F2: % de 20 a 39 anos | G2: Renda média, 14 anos ou mais (2022, R$) | H2: Renda mediana, 14 anos ou mais (2022, R$) | I2: Renda habitual do trabalho (2º tri. 2026, R$)
A3: Florianópolis | B3: SC | C3: 537211 | D3: 598370 | E3: 185946 | F3: =E3/C3 | G3: 4222.88 | H3: 2100 | I3: 6861
A4: Porto Alegre | B4: RS | C4: 1332845 | D4: 1388791 | E4: 391627 | F4: =E4/C4 | G4: 3749.45 | H4: 1900 | I4: 6402
A5: Curitiba | B5: PR | C5: 1773718 | D5: 1832183 | E5: 551000 | F5: =E5/C5 | G5: 3685.62 | H5: 2000 | I5: 6134
A6: Brasília | B6: DF | C6: 2817381 | D6: 3009996 | E6: 914611 | F6: =E6/C6 | G6: 3629.16 | H6: 1500 | I6: 6007
A7: Vitória | B7: ES | C7: 322869 | D7: 343935 | E7: 96495 | F7: =E7/C7 | G7: 3950.45 | H7: 1800 | I7: 5982
A8: Goiânia | B8: GO | C8: 1437366 | D8: 1511709 | E8: 474870 | F8: =E8/C8 | G8: 3202.02 | H8: 1500 | I8: 5496
A9: São Paulo | B9: SP | C9: 11451999 | D9: 11911337 | E9: 3559246 | F9: =E9/C9 | G9: 3216.65 | H9: 1500 | I9: 5431
A10: Belo Horizonte | B10: MG | C10: 2315560 | D10: 2415451 | E10: 702819 | F10: =E10/C10 | G10: 3206.74 | H10: 1500 | I10: 5130
A11: Rio de Janeiro | B11: RJ | C11: 6211223 | D11: 6731133 | E11: 1834349 | F11: =E11/C11 | G11: 2964.14 | H11: 1250 | I11: 5027
A12: Fortaleza | B12: CE | C12: 2428708 | D12: 2582360 | E12: 790398 | F12: =E12/C12 | G12: 2014.23 | H12: 1212 | I12: 3887
A13: Recife | B13: PE | C13: 1488920 | D13: 1588983 | E13: 447131 | F13: =E13/C13 | G13: 2728.51 | H13: 1212 | I13: 3758
A14: Salvador | B14: BA | C14: 2417678 | D14: 2559945 | E14: 736849 | F14: =E14/C14 | G14: 2089.3 | H14: 1212 | I14: 3417
A15: Belém | B15: PA | C15: 1303403 | D15: 1396157 | E15: 404656 | F15: =E15/C15 | G15: 1998.96 | H15: 1200 | I15: 3406
A16: Fonte: B4, IBGE: Censo 2022, estimativas de população 2026 e PNAD Contínua (2º trimestre de 2026)

Sheet Tab 17
A1: Tabela 17 – Aluguel comercial por m²: Salvador está entre as capitais mais caras do grupo
A2: Capital | B2: UF | C2: Locação comercial (R$/m²) | D2: Estimativa, mediana (R$/m²) | E2: Valor usado (R$/m²) | F2: Variação em 12 meses | G2: Origem do valor
A3: São Paulo | B3: SP | C3: 61.742989 | E3: =IF(C3<>"",C3,D3) | F3: 0.078221866 | G3: FipeZap comercial
A4: Recife | B4: PE | D4: 57.32 | E4: =IF(C4<>"",C4,D4) | G4: estimado (residencial × razão comercial/residencial)
A5: Rio de Janeiro | B5: RJ | C5: 56.980749 | E5: =IF(C5<>"",C5,D5) | F5: 0.21339627 | G5: FipeZap comercial
A6: Belém | B6: PA | D6: 56.02 | E6: =IF(C6<>"",C6,D6) | G6: estimado (residencial × razão comercial/residencial)
A7: Salvador | B7: BA | C7: 54.145255 | E7: =IF(C7<>"",C7,D7) | F7: 0.18855597 | G7: FipeZap comercial
A8: Florianópolis | B8: SC | C8: 51.77842 | E8: =IF(C8<>"",C8,D8) | F8: 0.074392232 | G8: FipeZap comercial
A9: Vitória | B9: ES | D9: 48.9 | E9: =IF(C9<>"",C9,D9) | G9: estimado (residencial × razão comercial/residencial)
A10: Curitiba | B10: PR | C10: 46.234575 | E10: =IF(C10<>"",C10,D10) | F10: 0.12846141 | G10: FipeZap comercial
A11: Brasília | B11: DF | C11: 44.19515 | E11: =IF(C11<>"",C11,D11) | F11: 0.0765629 | G11: FipeZap comercial
A12: Goiânia | B12: GO | D12: 38.63 | E12: =IF(C12<>"",C12,D12) | G12: estimado (residencial × razão comercial/residencial)
A13: Belo Horizonte | B13: MG | C13: 37.859152 | E13: =IF(C13<>"",C13,D13) | F13: 0.087934972 | G13: FipeZap comercial
A14: Fortaleza | B14: CE | D14: 37.24 | E14: =IF(C14<>"",C14,D14) | G14: estimado (residencial × razão comercial/residencial)
A15: Porto Alegre | B15: RS | C15: 34.728919 | E15: =IF(C15<>"",C15,D15) | F15: 0.028469123 | G15: FipeZap comercial
A16: Fonte: B4, FipeZap (índice de locação comercial e residencial, julho de 2026)
A17: Nota: onde o FipeZap não cobre o comercial, estimativa pelo residencial vezes a razão comercial/residencial das capitais cobertas.

Sheet Tab 18
A1: Tabela 18 – Salário de admissão em alimentação: Salvador paga perto do salário mínimo e abaixo das capitais
A2: Ocupação | B2: Salvador: admissões | C2: Salvador: salário mediano (R$) | D2: 27 capitais: admissões | E2: 27 capitais: salário mediano (R$) | F2: Salvador ÷ 27 capitais | G2: Amostra pequena em Salvador
A3: Gerente de restaurante | B3: 158 | C3: 2500 | D3: 7387 | E3: 2700 | F3: =C3/E3 | G3: não
A4: Gerente de bar | B4: 14 | C4: 2500 | D4: 1404 | E4: 2500 | F4: =C4/E4 | G4: sim
A5: Cozinheiro geral | B5: 1827 | C5: 1700 | D5: 54113 | E5: 1872.16 | F5: =C5/E5 | G5: não
A6: Recreador | B6: 8 | C6: 1625.09 | D6: 1188 | E6: 1669.2 | F6: =C6/E6 | G6: sim
A7: Operador de caixa | B7: 600 | C7: 1625.09 | D7: 14316 | E7: 1733.45 | F7: =C7/E7 | G7: não
A8: Garçom | B8: 1595 | C8: 1625.09 | D8: 43378 | E8: 1750.68 | F8: =C8/E8 | G8: não
A9: Cumim | B9: 601 | C9: 1625.09 | D9: 15978 | E9: 1700 | F9: =C9/E9 | G9: não
A10: Barman | B10: 351 | C10: 1625.09 | D10: 9253 | E10: 1771 | F10: =C10/E10 | G10: não
A11: Atendente de lanchonete | B11: 2943 | C11: 1625.09 | D11: 125235 | E11: 1688.53 | F11: =C11/E11 | G11: não
A12: Auxiliar nos serviços de alimentação | B12: 2737 | C12: 1625.09 | D12: 113010 | E12: 1787 | F12: =C12/E12 | G12: não
A13: Faxineiro | B13: 1470 | C13: 1625.09 | D13: 31783 | E13: 1703 | F13: =C13/E13 | G13: não
A14: Atendente de lojas e mercados | B14: 854 | C14: 1625.09 | D14: 19178 | E14: 1712 | F14: =C14/E14 | G14: não
A15: Fonte: B4, Novo CAGED (admissões de 08/2025 a 07/2026, CNAE 56 – alimentação)

Sheet Tab 19
A1: Tabela 19 – Simples Nacional, anexos I e III: alíquota efetiva no teto de cada faixa
A2: Anexo | B2: Faixa | C2: Receita bruta em 12 meses, de (R$) | D2: Até (R$) | E2: Alíquota nominal | F2: Parcela a deduzir (R$) | G2: Alíquota efetiva no teto da faixa
A3: I | B3: 1 | C3: 0 | D3: 180000 | E3: 0.04 | F3: 0 | G3: =IFERROR((D3*E3-F3)/D3,"")
A4: I | B4: 2 | C4: 180000.01 | D4: 360000 | E4: 0.073 | F4: 5940 | G4: =IFERROR((D4*E4-F4)/D4,"")
A5: I | B5: 3 | C5: 360000.01 | D5: 720000 | E5: 0.095 | F5: 13860 | G5: =IFERROR((D5*E5-F5)/D5,"")
A6: I | B6: 4 | C6: 720000.01 | D6: 1800000 | E6: 0.107 | F6: 22500 | G6: =IFERROR((D6*E6-F6)/D6,"")
A7: I | B7: 5 | C7: 1800000 | D7: 3600000 | E7: 0.143 | F7: 87300 | G7: =IFERROR((D7*E7-F7)/D7,"")
A8: I | B8: 6 | C8: 3600000 | D8: 4800000 | E8: 0.19 | F8: 378000 | G8: =IFERROR((D8*E8-F8)/D8,"")
A9: III | B9: 1 | C9: 0 | D9: 180000 | E9: 0.06 | F9: 0 | G9: =IFERROR((D9*E9-F9)/D9,"")
A10: III | B10: 2 | C10: 180000.01 | D10: 360000 | E10: 0.112 | F10: 9360 | G10: =IFERROR((D10*E10-F10)/D10,"")
A11: III | B11: 3 | C11: 360000.01 | D11: 720000 | E11: 0.135 | F11: 17640 | G11: =IFERROR((D11*E11-F11)/D11,"")
A12: III | B12: 4 | C12: 720000.01 | D12: 1800000 | E12: 0.16 | F12: 35640 | G12: =IFERROR((D12*E12-F12)/D12,"")
A13: III | B13: 5 | C13: 1800000 | D13: 3600000 | E13: 0.21 | F13: 125640 | G13: =IFERROR((D13*E13-F13)/D13,"")
A14: III | B14: 6 | C14: 3600000 | D14: 4800000 | E14: 0.33 | F14: 648000 | G14: =IFERROR((D14*E14-F14)/D14,"")
A15: Fonte: B4, Lei Complementar 123/2006, anexos I e III (Simples Nacional, 2026)
A16: Nota: alíquota efetiva = (receita × alíquota nominal − parcela a deduzir) ÷ receita.

Sheet Tab 20
A1: Tabela 20 – Selic e IPCA: juros altos em 2026, com queda esperada até 2030
A2: Ano | B2: Tipo | C2: Selic meta | D2: IPCA em 12 meses | E2: Referência
A3: 2017 | B3: realizado | C3: 0.07 | D3: 0.0295 | E3: Selic 12/2017; IPCA 12/2017
A4: 2018 | B4: realizado | C4: 0.065 | D4: 0.0375 | E4: Selic 12/2018; IPCA 12/2018
A5: 2019 | B5: realizado | C5: 0.045 | D5: 0.0431 | E5: Selic 12/2019; IPCA 12/2019
A6: 2020 | B6: realizado | C6: 0.02 | D6: 0.0452 | E6: Selic 12/2020; IPCA 12/2020
A7: 2021 | B7: realizado | C7: 0.0925 | D7: 0.1006 | E7: Selic 12/2021; IPCA 12/2021
A8: 2022 | B8: realizado | C8: 0.1375 | D8: 0.0579 | E8: Selic 12/2022; IPCA 12/2022
A9: 2023 | B9: realizado | C9: 0.1175 | D9: 0.0462 | E9: Selic 12/2023; IPCA 12/2023
A10: 2024 | B10: realizado | C10: 0.1225 | D10: 0.0483 | E10: Selic 12/2024; IPCA 12/2024
A11: 2025 | B11: realizado | C11: 0.15 | D11: 0.0426 | E11: Selic 12/2025; IPCA 12/2025
A12: 2026 | B12: realizado | C12: 0.14 | D12: 0.0422 | E12: Selic 09/2026; IPCA 08/2026
A13: 2026 | B13: Focus (mediana) | C13: 0.1375 | D13: 0.049 | E13: 11/09/2026
A14: 2027 | B14: Focus (mediana) | C14: 0.12 | D14: 0.043 | E14: 11/09/2026
... A17: 2030 | B17: Focus (mediana) | C17: 0.1 | D17: 0.035 | E17: 11/09/2026
A18: Fonte: B4, Banco Central do Brasil: SGS (séries 432 e 13522) e Relatório Focus de 11/09/2026
A19: Nota: realizado = último valor do ano (2026 até a data indicada); Focus = mediana das expectativas para o fim do ano.

Sheet Tab 21
A1: Tabela 21 – IPCA em 12 meses: alimentação fora do domicílio sobe mais que o índice geral
A2: Mês | B2: Brasil: índice geral | C2: Brasil: alimentação fora do domicílio | D2: Salvador: índice geral | E2: Salvador: alimentação fora do domicílio
A3: 08/2024 | B3: 0.0424 | C3: 0.0455 | D3: 0.0371 | E3: 0.0338
A4: 08/2025 | B4: 0.0513 | C4: 0.085 | D4: 0.0494 | E4: 0.077
A5: 08/2026 | B5: 0.0422 | C5: 0.054 | D5: 0.0364 | E5: 0.0655
A6: Fonte: B4, IBGE, IPCA (tabela 7060, variação acumulada em 12 meses)

Sheet Dados B1
A1: Base – as 54 casas do B1 (valores; as Tabelas 1 a 8 calculam por fórmula sobre esta aba)
A2: casa | B2: metrópole | C2: região | D2: nota no Google | E2: avaliações no Google | F2: dias abertos | G2: horas por semana | H2: abre mais cedo (h) | I2: fecha mais tarde (h) | J2: abre segunda | K2: abre terça | L2: abre quarta | M2: abre quinta | N2: abre sexta | O2: abre sábado | P2: abre domingo | Q2: metrô até 500 m | R2: metrô até 1000 m | S2: distância ao metrô (m) | T2: distância ao shopping (m) | U2: seguidores | V2: posts desde o início | W2: idade do perfil (anos) | X2: posts 01/09 a 01/10/2026 | Y2: interações por post | Z2: engajamento | AA2: itens com preço | AB2: cardápio transcrito | AC2: couvert encontrado | AD2: couvert (R$) | AE2: bebida (R$) | AF2: entrada ou prato (R$) | AG2: cesta baixa (R$) | AH2: cesta mediana (R$) | AI2: cesta alta (R$) | AJ2: hambúrguer (R$) | AK2: batata (R$) | AL2: cerveja (R$) | AM2: refrigerante (R$) | AN2: drinks (R$) | AO2: títulos no acervo
A3: FORTALÚDICA - BURGERS & JOGOS | B3: Brasília | C3: Centro-Oeste | D3: 4.8 | E3: 105 | F3: 7 | G3: 46 | H3: 14 | I3: 24 | J3: 1 | K3: 1 | L3: 1 | M3: 1 | N3: 1 | O3: 1 | P3: 1 | Q3: 0 | R3: 1 | S3: 768 | T3: 305 | U3: 2711 | V3: 185 | W3: 1.26 | X3: 9 | Y3: 10.78 | Z3: 0.00398 | AA3: 51 | AB3: 1 | AC3: 0 | AE3: 8.5 | AF3: 30 | AG3: 32 | AH3: 38.5 | AI3: 45 | AJ3: 32 | AK3: 15 | AL3: 8 | AM3: 7
A4: Gruta BSB | B4: Brasília | C4: Centro-Oeste | D4: 4.9 | E4: 112 | F4: 5 | G4: 30 | H4: 14 | I4: 23 | J4: 0 | K4: 1 | L4: 1 | M4: 1 | N4: 1 | O4: 1 | P4: 0 | Q4: 0 | R4: 0 | S4: 3099 | T4: 76 | U4: 7631 | V4: 897 | W4: 5.63 | X4: 17 | Y4: 27 | Z4: 0.00354 | AB4: 0
A5: Inside Games | B5: Brasília | C5: Centro-Oeste | D5: 4.6 | E5: 640 | F5: 6 | G5: 64 | H5: 12 | I5: 24 | J5: 0 | K5: 1 | L5: 1 | M5: 1 | N5: 1 | O5: 1 | P5: 1 | Q5: 0 | R5: 2 | S5: 702 | T5: 1505 | U5: 6058 | V5: 2542 | W5: 9.33 | X5: 39 | Y5: 5 | Z5: 0.00083 | AA5: 24 | AB5: 1 | AC5: 0 | AE5: 6 | AF5: 6 | AG5: 11 | AH5: 12 | AI5: 15.5 | AL5: 8 | AM5: 5
A6: Loja de Jogos - Asgard | B6: Brasília | C6: Centro-Oeste | D6: 4.7 | E6: 754 | F6: 7 | G6: 63 | H6: 14 | I6: 23 | J6: 1 | K6: 1 | L6: 1 | M6: 1 | N6: 1 | O6: 1 | P6: 1 | Q6: 1 | R6: 1 | S6: 430 | T6: 169 | U6: 7305 | V6: 608 | W6: 9.02 | X6: 1 | Y6: 15 | Z6: 0.00205 | AA6: 39 | AB6: 1 | AC6: 1 | AD6: 17.5 | AE6: 17 | AF6: 33 | AG6: 54.5 | AH6: 67.5 | AI6: 81.5 | AJ6: 45 | AK6: 30.5 | AL6: 12 | AM6: 6 | AN6: 22 | AO6: 150
A7: Ludoteca BGC | B7: Brasília | C7: Centro-Oeste | D7: 4.7 | E7: 1379 | F7: 6 | G7: 63 | H7: 12 | I7: 23.5 | J7: 0 | K7: 1 | L7: 1 | M7: 1 | N7: 1 | O7: 1 | P7: 1 | Q7: 2 | R7: 2 | S7: 465 | T7: 747 | U7: 15000 | V7: 820 | W7: 10.37 | X7: 13 | Y7: 11.85 | Z7: 0.00079 | AA7: 60 | AB7: 1 | AC7: 1 | AD7: 30 | AE7: 9 | AF7: 31 | AG7: 64.5 | AH7: 70 | AI7: 76.75 | AL7: 8.5 | AM7: 6 | AN7: 14 | AO7: 952
A8: Utopia Games & Food | B8: Brasília | C8: Centro-Oeste | D8: 4.8 | E8: 159 | F8: 6 | G8: 44 | H8: 14 | I8: 24 | J8: 0 | K8: 1 | L8: 1 | M8: 1 | N8: 1 | O8: 1 | P8: 1 | Q8: 0 | R8: 0 | S8: 6361 | T8: 162 | U8: 2824 | V8: 208 | W8: 2.67 | X8: 27 | Y8: 39.3 | Z8: 0.01392 | AA8: 32 | AB8: 1 | AC8: 0 | AE8: 7 | AF8: 50 | AG8: 55 | AH8: 57 | AI8: 84.5 | AK8: 25.5 | AL8: 11 | AM8: 6
A9: Paladins Game Store | B9: Goiânia | C9: Centro-Oeste | D9: 4.7 | E9: 906 | F9: 7 | G9: 70 | H9: 10 | I9: 22 | J9: 1 | K9: 1 | L9: 1 | M9: 1 | N9: 1 | O9: 1 | P9: 1 | Q9: 0 | R9: 0 | T9: 5 | U9: 9690 | V9: 1376 | W9: 11.71 | X9: 1 | Y9: 157 | Z9: 0.0162 | AB9: 0 | AO9: 214
A10: Balboa's Hobby Games | B10: Fortaleza | C10: Nordeste | D10: 4.8 | E10: 881 | F10: 5 | G10: 27 | H10: 15 | I10: 22 | J10: 0 | K10: 0 | L10: 1 | M10: 1 | N10: 1 | O10: 1 | P10: 1 | Q10: 0 | R10: 0 | S10: 3702 | T10: 228 | U10: 21318 | V10: 1724 | W10: 12.37 | X10: 22 | Y10: 110.5 | Z10: 0.00518 | AA10: 36 | AB10: 1 | AC10: 0 | AE10: 8 | AF10: 30 | AG10: 35 | AH10: 38 | AI10: 45 | AJ10: 29.5 | AK10: 26.5 | AL10: 15 | AM10: 7.5 | AN10: 15 | AO10: 1833
A11: Dominaria Cards & Games | B11: Fortaleza | C11: Nordeste | D11: 4.7 | E11: 305 | F11: 7 | G11: 77 | H11: 8 | I11: 21 | J11: 1 | K11: 1 | L11: 1 | M11: 1 | N11: 1 | O11: 1 | P11: 1 | Q11: 1 | R11: 2 | S11: 95 | T11: 96 | AB11: 0
A12: Nala Land - Bar de Jogos de Tabuleiro em Recife | B12: Recife | C12: Nordeste | D12: 4.9 | E12: 206 | F12: 4 | G12: 28 | H12: 14 | I12: 24 | J12: 0 | K12: 0 | L12: 0 | M12: 1 | N12: 1 | O12: 1 | P12: 1 | Q12: 0 | R12: 0 | S12: 5144 | T12: 1138 | U12: 27673 | V12: 655 | W12: 5.4 | X12: 17 | Y12: 68.94 | Z12: 0.00249 | AA12: 25 | AB12: 1 | AC12: 0 | AE12: 12 | AF12: 22 | AG12: 29.5 | AH12: 34 | AI12: 37.5 | AJ12: 34 | AK12: 19 | AL12: 12 | AO12: 312
A13: São Jogue - Bela Vista | B13: Salvador | C13: Nordeste | D13: 4.8 | E13: 787 | F13: 7 | G13: 68 | H13: 12 | I13: 22 | J13: 1 | K13: 1 | L13: 1 | M13: 1 | N13: 1 | O13: 1 | P13: 1 | Q13: 1 | R13: 2 | S13: 387 | T13: 118 | U13: 38492 | V13: 2036 | W13: 8.91 | X13: 26 | Y13: 334.58 | Z13: 0.00869 | AA13: 56 | AB13: 1 | AC13: 0 | AE13: 16 | AF13: 32.5 | AG13: 36.25 | AH13: 48.5 | AI13: 60.5 | AJ13: 45 | AK13: 35 | AL13: 12 | AM13: 8.9 | AN13: 28 | AO13: 370
A14: Ludoteca Sidequest | B14: Belém | C14: Norte | D14: 4.8 | E14: 327 | F14: 5 | G14: 42 | H14: 14 | I14: 24 | J14: 0 | K14: 0 | L14: 1 | M14: 1 | N14: 1 | O14: 1 | P14: 1 | Q14: 0 | R14: 0 | T14: 52 | U14: 21601 | V14: 235 | W14: 2.98 | X14: 10 | Y14: 348.6 | Z14: 0.01614 | AA14: 60 | AB14: 1 | AC14: 1 | AD14: 25.5 | AE14: 13 | AF14: 35 | AG14: 56.75 | AH14: 73.5 | AI14: 81.25 | AJ14: 40 | AK14: 31 | AL14: 13 | AM14: 7 | AN14: 13 | AO14: 468
A15: Bardo Mago | B15: Belo Horizonte | C15: Sudeste | D15: 4.8 | E15: 823 | F15: 5 | G15: 37 | H15: 13 | I15: 24 | J15: 0 | K15: 0 | L15: 1 | M15: 1 | N15: 1 | O15: 1 | P15: 1 | Q15: 1 | R15: 1 | S15: 307 | T15: 723 | V15: 616 | W15: 2.42 | X15: 31 | Y15: 287.03 | AA15: 110 | AB15: 1 | AC15: 0 | AE15: 20 | AF15: 34 | AG15: 40.5 | AH15: 54 | AI15: 71.5 | AJ15: 42 | AL15: 12.5 | AM15: 8 | AN15: 26 | AO15: 588
A16: Comdado Bar e Jogos | B16: Belo Horizonte | C16: Sudeste | D16: 4.4 | E16: 158 | F16: 5 | G16: 45 | H16: 12 | I16: 25 | J16: 0 | K16: 0 | L16: 1 | M16: 1 | N16: 1 | O16: 1 | P16: 1 | Q16: 0 | R16: 0 | S16: 1142 | T16: 105 | U16: 10671 | V16: 190 | W16: 3.98 | X16: 2 | Y16: 52 | Z16: 0.00487 | AA16: 55 | AB16: 1 | AC16: 1 | AD16: 17.5 | AE16: 18 | AF16: 50 | AG16: 71 | AH16: 85.5 | AI16: 98.75 | AJ16: 50 | AL16: 12 | AN16: 25 | AO16: 190
A17: Garagem do Nerd | B17: Belo Horizonte | C17: Sudeste | D17: 4.9 | E17: 244 | F17: 5 | G17: 34 | H17: 13 | I17: 25 | J17: 0 | K17: 1 | L17: 1 | M17: 1 | N17: 1 | O17: 1 | P17: 0 | Q17: 0 | R17: 0 | S17: 1201 | T17: 754 | U17: 13420 | V17: 3023 | W17: 8.73 | X17: 30 | Y17: 17.97 | Z17: 0.00134 | AB17: 0
A18: La Tabuleria | B18: Belo Horizonte | C18: Sudeste | D18: 4.7 | E18: 138 | F18: 5 | G18: 42 | H18: 15 | I18: 25 | J18: 0 | K18: 0 | L18: 1 | M18: 1 | N18: 1 | O18: 1 | P18: 1 | Q18: 0 | R18: 0 | S18: 4984 | T18: 137 | W18: 2.64 | X18: 8 | Y18: 17.62 | AA18: 90 | AB18: 1 | AC18: 1 | AD18: 20 | AE18: 20 | AF18: 35 | AG18: 58.5 | AH18: 75 | AI18: 87.5 | AJ18: 42 | AK18: 37.5 | AL18: 12 | AM18: 8 | AN18: 25 | AO18: 192
A19: LudoCafé | B19: Belo Horizonte | C19: Sudeste | D19: 4.6 | E19: 585 | F19: 6 | G19: 41 | H19: 13 | I19: 24 | J19: 0 | K19: 1 | L19: 1 | M19: 1 | N19: 1 | O19: 1 | P19: 1 | Q19: 0 | R19: 0 | S19: 3205 | T19: 391 | AB19: 0 | AO19: 362
A20: Shelf Bar e Jogos | B20: Belo Horizonte | C20: Sudeste | D20: 4.6 | E20: 1505 | F20: 6 | G20: 56 | H20: 15 | I20: 25 | J20: 0 | K20: 1 | L20: 1 | M20: 1 | N20: 1 | O20: 1 | P20: 1 | Q20: 0 | R20: 0 | S20: 2556 | T20: 221 | U20: 31800 | V20: 630 | W20: 2.15 | X20: 32 | Y20: 52.44 | Z20: 0.00165 | AA20: 138 | AB20: 1 | AC20: 1 | AD20: 20 | AE20: 25 | AF20: 52 | AG20: 74 | AH20: 97 | AI20: 121 | AJ20: 54 | AK20: 40 | AL20: 13 | AM20: 12 | AN20: 28 | AO20: 836
A21: Game Of Boards | B21: Rio de Janeiro | C21: Sudeste | D21: 4.7 | E21: 1077 | F21: 5 | G21: 41 | H21: 14 | I21: 24 | J21: 0 | K21: 0 | L21: 1 | M21: 1 | N21: 1 | O21: 1 | P21: 1 | Q21: 0 | R21: 1 | S21: 555 | T21: 291 | U21: 18453 | V21: 3266 | W21: 10.55 | X21: 21 | Y21: 41.19 | Z21: 0.00223 | AB21: 0
A22: Luderia Carioca | B22: Rio de Janeiro | C22: Sudeste | D22: 4.7 | E22: 212 | F22: 5 | G22: 38 | H22: 14 | I22: 24 | J22: 0 | K22: 0 | L22: 1 | M22: 1 | N22: 1 | O22: 1 | P22: 1 | Q22: 2 | R22: 3 | S22: 302 | T22: 576 | U22: 16137 | V22: 84 | W22: 1.59 | X22: 5 | Y22: 165.8 | Z22: 0.01027 | AA22: 36 | AB22: 1 | AC22: 0 | AE22: 12 | AF22: 32 | AG22: 35 | AH22: 44 | AI22: 54.5 | AJ22: 38 | AK22: 24 | AL22: 16.5 | AM22: 9 | AO22: 780
A23: Magic Store Brazil | B23: Rio de Janeiro | C23: Sudeste | D23: 4.7 | E23: 465 | F23: 6 | G23: 32 | H23: 13 | I23: 21 | J23: 0 | K23: 1 | L23: 1 | M23: 1 | N23: 1 | O23: 1 | P23: 1 | Q23: 0 | R23: 0 | S23: 1216 | T23: 312 | U23: 23364 | V23: 308 | W23: 7.89 | X23: 4 | Y23: 33.75 | Z23: 0.00144 | AB23: 0
A24: RED jogos | B24: Rio de Janeiro | C24: Sudeste | D24: 4.7 | E24: 800 | F24: 6 | G24: 47 | H24: 11 | I24: 20 | J24: 1 | K24: 1 | L24: 1 | M24: 1 | N24: 1 | O24: 1 | P24: 0 | Q24: 2 | R24: 3 | S24: 161 | T24: 496 | U24: 21522 | V24: 1164 | W24: 11.02 | X24: 12 | Y24: 89.25 | Z24: 0.00415 | AB24: 0
A25: TabuClub | B25: Rio de Janeiro | C25: Sudeste | D25: 4.7 | E25: 105 | F25: 6 | G25: 43 | H25: 14 | I25: 24 | J25: 0 | K25: 1 | L25: 1 | M25: 1 | N25: 1 | O25: 1 | P25: 1 | Q25: 0 | R25: 0 | S25: 7638 | T25: 153 | W25: 3.23 | X25: 8 | Y25: 207.62 | AB25: 0 | AO25: 1357
A26: Arena BG | Jogos de Tabuleiro | Hamburgueria | B26: São Paulo | C26: Sudeste | D26: 4.8 | E26: 145 | F26: 5 | G26: 33 | H26: 14 | I26: 25 | J26: 0 | K26: 0 | L26: 1 | M26: 1 | N26: 1 | O26: 1 | P26: 1 | Q26: 1 | R26: 1 | S26: 351 | T26: 1796 | U26: 6682 | V26: 520 | W26: 2.44 | X26: 32 | Y26: 23.59 | Z26: 0.00353 | AA26: 78 | AB26: 1 | AC26: 1 | AD26: 12.5 | AE26: 11 | AF26: 45 | AG26: 52.25 | AH26: 68.5 | AI26: 96.75 | AJ26: 52.5 | AK26: 28.5 | AL26: 11 | AM26: 8 | AN26: 25 | AO26: 540
A27: Bodogami Restaurante e Cafeteria | B27: São Paulo | C27: Sudeste | D27: 4.6 | E27: 3386 | F27: 7 | G27: 77 | H27: 11 | I27: 22.5 | J27: 1 | K27: 1 | L27: 1 | M27: 1 | N27: 1 | O27: 1 | P27: 1 | Q27: 1 | R27: 2 | S27: 204 | T27: 163 | U27: 74000 | V27: 2374 | W27: 9.75 | X27: 4 | Y27: 113 | Z27: 0.00153 | AA27: 90 | AB27: 1 | AC27: 0 | AE27: 17 | AF27: 43 | AG27: 40 | AH27: 60 | AI27: 76 | AJ27: 49.5 | AK27: 39 | AL27: 16 | AM27: 8 | AN27: 36.5 | AO27: 934
A28: Bravo Jogos | B28: São Paulo | C28: Sudeste | D28: 4.9 | E28: 1719 | F28: 5 | G28: 55 | H28: 10 | I28: 21 | J28: 0 | K28: 1 | L28: 1 | M28: 1 | N28: 1 | O28: 1 | P28: 0 | Q28: 0 | R28: 0 | S28: 10228 | T28: 684 | U28: 65145 | V28: 1782 | X28: 14 | Y28: 528.57 | Z28: 0.00811 | AB28: 0
A29: Cartola Luderia Bar | B29: São Paulo | C29: Sudeste | D29: 4.7 | E29: 242 | F29: 3 | G29: 19.5 | H29: 17 | I29: 23.5 | J29: 0 | K29: 0 | L29: 0 | M29: 1 | N29: 1 | O29: 1 | P29: 0 | Q29: 0 | R29: 2 | S29: 607 | T29: 907 | U29: 11500 | V29: 670 | W29: 2.56 | X29: 21 | Y29: 51.67 | Z29: 0.00449 | AA29: 50 | AB29: 1 | AC29: 0 | AE29: 36 | AF29: 39 | AG29: 58.75 | AH29: 75 | AI29: 78 | AK29: 68 | AN29: 36
A30: Castelos Bar & Boardgames | B30: São Paulo | C30: Sudeste | D30: 4.6 | E30: 617 | F30: 5 | G30: 29 | H30: 14 | I30: 23 | J30: 0 | K30: 0 | L30: 1 | M30: 1 | N30: 1 | O30: 1 | P30: 1 | Q30: 0 | R30: 1 | S30: 577 | T30: 1006 | U30: 41545 | V30: 1358 | W30: 6.91 | X30: 1 | Y30: 20 | Z30: 0.00048 | AA30: 69 | AB30: 1 | AC30: 0 | AE30: 28.4 | AF30: 43.4 | AG30: 55.57 | AH30: 71.8 | AI30: 83.55 | AJ30: 43.9 | AK30: 39.9 | AL30: 15 | AM30: 9 | AN30: 37.9 | AO30: 225
A31: Coletivo Geek | B31: São Paulo | C31: Sudeste | D31: 4.7 | E31: 477 | F31: 6 | G31: 47 | H31: 13 | I31: 23 | J31: 0 | K31: 1 | L31: 1 | M31: 1 | N31: 1 | O31: 1 | P31: 1 | Q31: 0 | R31: 1 | S31: 555 | T31: 494 | U31: 13059 | V31: 501 | W31: 7.53 | X31: 3 | Y31: 54.67 | Z31: 0.00419 | AA31: 72 | AB31: 1 | AC31: 0 | AE31: 28 | AF31: 32 | AG31: 47.75 | AH31: 60 | AI31: 69 | AJ31: 28 | AK31: 33 | AL31: 22 | AM31: 8 | AN31: 30
A32: Covil Game Bar | B32: São Paulo | C32: Sudeste | D32: 4.6 | E32: 1714 | F32: 5 | G32: 32 | H32: 18 | I32: 25 | J32: 0 | K32: 0 | L32: 1 | M32: 1 | N32: 1 | O32: 1 | P32: 1 | Q32: 0 | R32: 0 | S32: 7180 | T32: 424 | U32: 206000 | V32: 790 | W32: 9.87 | X32: 13 | Y32: 7027.85 | Z32: 0.03412 | AA32: 71 | AB32: 1 | AC32: 0 | AE32: 18 | AF32: 34 | AG32: 43 | AH32: 52 | AI32: 60 | AJ32: 29 | AK32: 50 | AL32: 17 | AM32: 8 | AN32: 21.5 | AO32: 239
A33: Dungeon Games Store | B33: São Paulo | C33: Sudeste | D33: 4.9 | E33: 217 | F33: 5 | G33: 33 | H33: 13 | I33: 22 | J33: 0 | K33: 0 | L33: 1 | M33: 1 | N33: 1 | O33: 1 | P33: 1 | Q33: 0 | R33: 0 | S33: 16823 | T33: 1993 | U33: 2732 | V33: 270 | W33: 4.93 | X33: 5 | Y33: 30.6 | Z33: 0.0112 | AA33: 42 | AB33: 1 | AC33: 0 | AE33: 14 | AF33: 30 | AG33: 35.75 | AH33: 44 | AI33: 52.5 | AJ33: 31 | AK33: 30 | AL33: 12 | AM33: 8 | AN33: 28 | AO33: 90
A34: Encounter | Jogos de Tabuleiro | Board Games | B34: São Paulo | C34: Sudeste | D34: 4.8 | E34: 1123 | F34: 6 | G34: 45 | H34: 13 | I34: 25 | J34: 0 | K34: 1 | L34: 1 | M34: 1 | N34: 1 | O34: 1 | P34: 1 | Q34: 0 | R34: 1 | S34: 687 | T34: 835 | U34: 22391 | V34: 1163 | W34: 9.71 | X34: 15 | Y34: 72 | Z34: 0.00322 | AA34: 22 | AB34: 1 | AC34: 0 | AE34: 27.9 | AF34: 39.9 | AG34: 62.8 | AH34: 67.8 | AI34: 76.8 | AJ34: 38 | AK34: 24.9
A35: Fan Hour Games and Burgers | B35: São Paulo | C35: Sudeste | D35: 4.5 | E35: 2363 | F35: 6 | G35: 36.5 | H35: 13 | I35: 23 | J35: 0 | K35: 1 | L35: 1 | M35: 1 | N35: 1 | O35: 1 | P35: 1 | Q35: 0 | R35: 2 | S35: 628 | T35: 1205 | U35: 110000 | V35: 1403 | W35: 6.89 | X35: 25 | Y35: 128.44 | Z35: 0.00117 | AB35: 0
A36: Flow Games - Burgers, Cards & Comunidade | B36: São Paulo | C36: Sudeste | D36: 4.6 | E36: 503 | F36: 5 | G36: 37 | H36: 11 | I36: 22 | J36: 0 | K36: 1 | L36: 1 | M36: 1 | N36: 1 | O36: 1 | P36: 0 | Q36: 1 | R36: 1 | S36: 435 | T36: 818 | U36: 8944 | V36: 1666 | W36: 10.76 | X36: 17 | Y36: 24.24 | Z36: 0.00271 | AA36: 16 | AB36: 1 | AC36: 0 | AE36: 6 | AF36: 14 | AG36: 17 | AH36: 20 | AI36: 41.9 | AJ36: 12 | AK36: 10 | AL36: 6.5 | AM36: 6
A37: Jogasampa | B37: São Paulo | C37: Sudeste | D37: 4.7 | E37: 402 | F37: 6 | G37: 48 | H37: 13 | I37: 21 | J37: 0 | K37: 1 | L37: 1 | M37: 1 | N37: 1 | O37: 1 | P37: 1 | Q37: 0 | R37: 1 | S37: 587 | T37: 438 | U37: 5966 | V37: 756 | W37: 9.86 | X37: 8 | Y37: 13.88 | Z37: 0.00233 | AA37: 7 | AB37: 1 | AC37: 0 | AE37: 6 | AM37: 6 | AO37: 331
A38: Ludus Luderia | B38: São Paulo | C38: Sudeste | D38: 4.6 | E38: 5137 | F38: 4 | G38: 31 | H38: 13 | I38: 25 | J38: 0 | K38: 0 | L38: 0 | M38: 1 | N38: 1 | O38: 1 | P38: 1 | Q38: 0 | R38: 3 | S38: 768 | T38: 119 | U38: 90400 | W38: 4.97 | X38: 12 | Y38: 133.08 | Z38: 0.00147 | AA38: 161 | AB38: 1 | AC38: 1 | AD38: 0 | AE38: 34 | AF38: 48 | AG38: 63 | AH38: 82 | AI38: 92.5 | AJ38: 42 | AK38: 48 | AL38: 18.5 | AM38: 9 | AN38: 36 | AO38: 199
A39: OMNIVERSE | B39: São Paulo | C39: Sudeste | D39: 4.8 | E39: 1145 | F39: 5 | G39: 46 | H39: 12 | I39: 24 | J39: 0 | K39: 0 | L39: 1 | M39: 1 | N39: 1 | O39: 1 | P39: 1 | Q39: 0 | R39: 2 | S39: 820 | T39: 1083 | U39: 8510 | V39: 918 | W39: 13.68 | X39: 8 | Y39: 67.12 | Z39: 0.00789 | AB39: 0 | AO39: 59
A40: Pitta's Board Games | B40: São Paulo | C40: Sudeste | D40: 4.9 | E40: 663 | F40: 6 | G40: 58 | H40: 11 | I40: 22 | J40: 0 | K40: 1 | L40: 1 | M40: 1 | N40: 1 | O40: 1 | P40: 1 | Q40: 0 | R40: 1 | S40: 566 | T40: 1744 | U40: 23415 | V40: 2269 | W40: 11.21 | X40: 21 | Y40: 69.14 | Z40: 0.00295 | AB40: 0 | AO40: 227
A41: Place Games | B41: São Paulo | C41: Sudeste | D41: 4.8 | E41: 572 | F41: 5 | G41: 46 | H41: 10 | I41: 22 | J41: 0 | K41: 0 | L41: 1 | M41: 1 | N41: 1 | O41: 1 | P41: 1 | Q41: 0 | R41: 0 | S41: 4310 | T41: 251 | U41: 14021 | V41: 2362 | W41: 10.55 | X41: 23 | Y41: 89.78 | Z41: 0.0064 | AA41: 57 | AB41: 1 | AC41: 0 | AE41: 10.5 | AF41: 29 | AG41: 18.18 | AH41: 39.5 | AI41: 53.5 | AJ41: 38.9 | AK41: 33 | AL41: 13 | AM41: 11 | AO41: 633
A42: Play Easy | B42: São Paulo | C42: Sudeste | D42: 4.7 | E42: 1002 | F42: 6 | G42: 50 | H42: 12 | I42: 22 | J42: 1 | K42: 1 | L42: 1 | M42: 1 | N42: 1 | O42: 1 | P42: 0 | Q42: 0 | R42: 3 | S42: 563 | T42: 484 | U42: 21346 | V42: 2996 | W42: 9.33 | X42: 16 | Y42: 88.94 | Z42: 0.00417 | AA42: 16 | AB42: 1 | AC42: 0 | AE42: 7 | AF42: 25 | AG42: 17 | AH42: 32 | AI42: 34.5 | AK42: 16 | AL42: 10 | AM42: 6 | AO42: 438
A43: Tubaleria | B43: São Paulo | C43: Sudeste | D43: 5 | E43: 116 | F43: 5 | G43: 55 | H43: 11 | I43: 23 | J43: 0 | K43: 0 | L43: 1 | M43: 1 | N43: 1 | O43: 1 | P43: 1 | Q43: 0 | R43: 0 | S43: 1527 | T43: 305 | V43: 340 | W43: 1.95 | X43: 20 | Y43: 41.6 | AA43: 29 | AB43: 1 | AC43: 0 | AF43: 38 | AJ43: 48 | AK43: 35 | AO43: 221
A44: XPlace | B44: São Paulo | C44: Sudeste | D44: 4.7 | E44: 795 | F44: 6 | G44: 49 | H44: 11 | I44: 20 | J44: 1 | K44: 1 | L44: 1 | M44: 1 | N44: 1 | O44: 1 | P44: 0 | Q44: 1 | R44: 1 | S44: 364 | T44: 1486 | U44: 34668 | V44: 5277 | W44: 11.06 | X44: 31 | Y44: 140.87 | Z44: 0.00406 | AB44: 0
A45: Café Geek Cafeteria e Ludoteca | B45: Vitória | C45: Sudeste | D45: 5 | E45: 148 | F45: 4 | G45: 26 | H45: 14 | I45: 23 | J45: 0 | K45: 0 | L45: 0 | M45: 1 | N45: 1 | O45: 1 | P45: 1 | Q45: 0 | R45: 0 | T45: 926 | U45: 12159 | V45: 230 | W45: 5.21 | X45: 3 | Y45: 41.67 | Z45: 0.00343 | AA45: 67 | AB45: 1 | AC45: 0 | AE45: 12.5 | AF45: 10 | AG45: 15.75 | AH45: 22.5 | AI45: 30.25 | AK45: 18 | AL45: 12 | AM45: 7
A46: Alçapão Jogos | B46: Curitiba | C46: Sul | D46: 5 | E46: 219 | F46: 5 | G46: 36 | H46: 15 | I46: 24 | J46: 0 | K46: 0 | L46: 1 | M46: 1 | N46: 1 | O46: 1 | P46: 1 | Q46: 0 | R46: 0 | T46: 770 | U46: 13883 | V46: 303 | W46: 7.83 | X46: 3 | Y46: 24 | Z46: 0.00173 | AA46: 28 | AB46: 1 | AC46: 0 | AE46: 12 | AF46: 12 | AG46: 22 | AH46: 24 | AI46: 34 | AM46: 9 | AO46: 270
A47: BoardZ Game Pub | B47: Curitiba | C47: Sul | D47: 4.8 | E47: 776 | F47: 6 | G47: 35 | H47: 16 | I47: 24.5 | J47: 0 | K47: 1 | L47: 1 | M47: 1 | N47: 1 | O47: 1 | P47: 1 | Q47: 0 | R47: 0 | T47: 1175 | U47: 18698 | V47: 491 | W47: 6.66 | X47: 2 | Y47: 129.5 | Z47: 0.00693 | AA47: 103 | AB47: 1 | AC47: 0 | AE47: 17.5 | AF47: 30 | AG47: 43 | AH47: 47.5 | AI47: 58 | AJ47: 32 | AK47: 32 | AL47: 18 | AM47: 8 | AN47: 24
A48: Joyjoy Café | B48: Curitiba | C48: Sul | D48: 4.8 | E48: 690 | F48: 6 | G48: 37 | H48: 14 | I48: 23 | J48: 0 | K48: 1 | L48: 1 | M48: 1 | N48: 1 | O48: 1 | P48: 1 | Q48: 0 | R48: 0 | T48: 1152 | U48: 25555 | V48: 627 | W48: 6.66 | X48: 6 | Y48: 305.83 | Z48: 0.01197 | AB48: 0 | AO48: 1010
A49: Paladino Hobbies | B49: Curitiba | C49: Sul | D49: 4.8 | E49: 188 | F49: 4 | G49: 22 | H49: 12 | I49: 19 | J49: 0 | K49: 0 | L49: 1 | M49: 1 | N49: 1 | O49: 1 | P49: 0 | Q49: 0 | R49: 0 | T49: 293 | U49: 1432 | V49: 140 | W49: 6.55 | X49: 1 | Y49: 1 | Z49: 0.0007 | AB49: 0
A50: Taverna Game House | B50: Curitiba | C50: Sul | D50: 4.8 | E50: 625 | F50: 6 | G50: 48 | H50: 14 | I50: 22 | J50: 1 | K50: 1 | L50: 1 | M50: 1 | N50: 1 | O50: 1 | P50: 0 | Q50: 0 | R50: 0 | T50: 358 | U50: 3168 | V50: 1832 | W50: 9.05 | X50: 26 | Y50: 23.85 | Z50: 0.00753 | AB50: 0
A51: Vila Celta Hobby Store - Jogos e Café | B51: Curitiba | C51: Sul | D51: 4.8 | E51: 751 | F51: 7 | G51: 73.5 | H51: 10 | I51: 24 | J51: 1 | K51: 1 | L51: 1 | M51: 1 | N51: 1 | O51: 1 | P51: 1 | Q51: 0 | R51: 0 | T51: 590 | U51: 11711 | V51: 566 | W51: 9.89 | X51: 2 | Y51: 38 | Z51: 0.00324 | AB51: 0
A52: CCG Floripa | B52: Florianópolis | C52: Sul | D52: 4.8 | E52: 194 | F52: 5 | G52: 42 | H52: 13 | I52: 23 | J52: 0 | K52: 1 | L52: 1 | M52: 1 | N52: 1 | O52: 1 | P52: 0 | Q52: 0 | R52: 0 | T52: 294 | U52: 11321 | V52: 446 | W52: 5.13 | X52: 2 | Y52: 344.5 | Z52: 0.03043 | AA52: 9 | AB52: 1 | AC52: 0 | AF52: 36 | AJ52: 36 | AK52: 54
A53: Chef on Play | B53: Florianópolis | C53: Sul | D53: 4.6 | E53: 1204 | F53: 7 | G53: 35.5 | H53: 18.5 | I53: 24 | J53: 1 | K53: 1 | L53: 1 | M53: 1 | N53: 1 | O53: 1 | P53: 1 | Q53: 0 | R53: 0 | T53: 834 | U53: 10739 | V53: 517 | W53: 10.9 | X53: 0 | AA53: 100 | AB53: 1 | AC53: 0 | AE53: 6.8 | AF53: 25.9 | AG53: 28.4 | AH53: 32.7 | AI53: 37.6 | AJ53: 25.9 | AM53: 6.5 | AO53: 245
A54: Cineplay- Restaurante e Jogos | B54: Florianópolis | C54: Sul | D54: 4.5 | E54: 1154 | F54: 7 | G54: 43 | H54: 11 | I54: 24 | J54: 1 | K54: 1 | L54: 1 | M54: 1 | N54: 1 | O54: 1 | P54: 1 | Q54: 0 | R54: 0 | T54: 1681 | U54: 87929 | V54: 1689 | W54: 8.36 | X54: 25 | Y54: 202.28 | Z54: 0.0023 | AA54: 137 | AB54: 1 | AC54: 0 | AE54: 17.9 | AF54: 30.9 | AG54: 34.9 | AH54: 48.8 | AI54: 67.67 | AJ54: 29.9 | AK54: 29.2 | AL54: 17 | AM54: 6.75 | AN54: 20.9
A55: Arcadea Gaming Pub | B55: Porto Alegre | C55: Sul | D55: 4.2 | E55: 1087 | F55: 7 | G55: 42 | H55: 17 | I55: 24 | J55: 1 | K55: 1 | L55: 1 | M55: 1 | N55: 1 | O55: 1 | P55: 1 | Q55: 0 | R55: 0 | S55: 1300 | T55: 591 | U55: 45836 | V55: 2009 | W55: 7.1 | X55: 29 | Y55: 38.55 | Z55: 0.00084 | AA55: 95 | AB55: 1 | AC55: 0 | AE55: 25 | AF55: 40 | AG55: 52.75 | AH55: 65 | AI55: 84 | AJ55: 45 | AK55: 28 | AL55: 19 | AM55: 8 | AN55: 29
A56: Toca do Rato - Pizzaria e Jogos de Tabuleiro | B56: Porto Alegre | C56: Sul | D56: 4.8 | E56: 138 | F56: 6 | G56: 26.5 | H56: 18 | I56: 23 | J56: 1 | K56: 1 | L56: 1 | M56: 1 | N56: 1 | O56: 1 | P56: 0 | Q56: 0 | R56: 0 | S56: 15504 | T56: 583 | W56: 3.25 | X56: 9 | Y56: 36.22 | AA56: 25 | AB56: 1 | AC56: 0 | AE56: 7.5 | AF56: 64.45 | AG56: 64.67 | AH56: 71.95 | AI56: 81.5 | AM56: 7.5 | AO56: 287
A57: Fonte: B1, Google Places API (09/2026 e 15/10/2026), coletor de entorno do Google Maps (15/10/2026), Instagram (01/09 a 01/10/2026) e cardápios; arquivo B1_estatistica_descritiva_geral.xlsx (aba dados).
A58: Nota: 1 = sim, 0 = não nas colunas de dia e de cardápio; "couvert encontrado" 0 = não encontrado no cardápio, não "não cobra".
